Workbook
Name AsOfDate: 'Instructions & Assumptions'!$C$6
Name BMK_12M_MCLR_SIB: 'Instructions & Assumptions'!$C$18
Name BMK_1Y_MCLR_RBL: 'Instructions & Assumptions'!$C$15
Name BMK_3M_MCLR_YBL: 'Instructions & Assumptions'!$C$16
Name BMK_3M_TBILL: 'Instructions & Assumptions'!$C$13
Name BMK_6M_IMCLR_ICICI: 'Instructions & Assumptions'!$C$17
Name BMK_BFRR: 'Instructions & Assumptions'!$C$19
Name BMK_FD_RATE: 'Instructions & Assumptions'!$C$21
Name BMK_REPO: 'Instructions & Assumptions'!$C$14
Name BMK_TERM_SOFR: 'Instructions & Assumptions'!$C$20
Name CONS_DATES: 'Repayment Schedule'!$C$193:$C$245
Name CONS_DS: 'Repayment Schedule'!$G$193:$G$245
Name CONS_INTEREST: 'Repayment Schedule'!$F$193:$F$245
Name CONS_PRINCIPAL: 'Repayment Schedule'!$E$193:$E$245
Name CONS_SCHEDULE_START_ROW: 'Repayment Schedule'!$B$193
Name DaysInYear: 'Instructions & Assumptions'!$C$9
Name FIN_ATNW: 'Instructions & Assumptions'!$C$29
Name FIN_CA: 'Instructions & Assumptions'!$C$30
Name FIN_CL: 'Instructions & Assumptions'!$C$31
Name FIN_EBITDA: 'Instructions & Assumptions'!$C$25
Name FIN_FA_NET: 'Instructions & Assumptions'!$C$34
Name FIN_INT_EXP: 'Instructions & Assumptions'!$C$33
Name FIN_PRINC_REP: 'Instructions & Assumptions'!$C$38
Name FIN_PROM_SHARE: 'Instructions & Assumptions'!$C$37
Name FIN_RATING: 'Instructions & Assumptions'!$C$36
Name FIN_SCHED_REPAY: 'Instructions & Assumptions'!$C$40
Name FIN_SEC_DEBT: 'Instructions & Assumptions'!$C$35
Name FIN_TAX_PAID: 'Instructions & Assumptions'!$C$39
Name FIN_TERM_DEBT: 'Instructions & Assumptions'!$C$27
Name FIN_TNW: 'Instructions & Assumptions'!$C$28
Name FIN_TOL: 'Instructions & Assumptions'!$C$32
Name FIN_TOTAL_DEBT: 'Instructions & Assumptions'!$C$26
Name FinancialBasis: 'Instructions & Assumptions'!$C$10
Name FX_USD_INR: 'Instructions & Assumptions'!$C$7
Name LenderFilter: Dashboard!$H$5
Name TL_21_PRINC_OUTSTD: 'Repayment Schedule'!$H$126
Name TL_21_PRINC_REPAID_TO_DATE: 'Repayment Schedule'!$F$126
Name TL_22_PRINC_OUTSTD: 'Repayment Schedule'!$H$188
Name TL_22_PRINC_REPAID_TO_DATE: 'Repayment Schedule'!$F$188
Name TL_9_PRINC_OUTSTD: 'Repayment Schedule'!$H$64
Name TL_9_PRINC_REPAID_TO_DATE: 'Repayment Schedule'!$F$64
Name UseFullUtilisation: 'Instructions & Assumptions'!$C$8

Sheet Cover Page
B3: JINDAL COKE LIMITED
B4: DEBT MODEL
B5: Lender-wise, Facility-wise Debt Monitoring & Repayment Model
B8: Company | E8: Jindal Coke Limited
B9: Registered Office | E9: O.P. Jindal Marg, Hisar - 125005, Haryana
B10: Promoter / Guarantor | E10: Mr. Ratan Jindal
B11: Model Name | E11: JCL Debt Model
B12: Prepared By | E12: Divyanshu Vatsa
B13: Date of Preparation | E13: 46133
B14: As-of Date | E14: See Instructions & Assumptions → AsOfDate
B15: Reporting Unit | E15: INR Crores (except Orig. Ccy columns)
B16: Total Active Lenders | E16: 5
B17: Total Facilities | E17: 34
B19: DISCLAIMER
B20: This model has been compiled solely from information available in the sanction letters issued by the company's lenders, supplemented by Raw Data aggregated in the source workbook. Outstanding balances, live benchmark rates, first-disbursement dates and latest management financials are not contained in the sanction letters and have been left as user-input cells (highlighted yellow). All explicit assumptions are listed on the 'Instructions & Assumptions' tab. Model outputs (interest cost, covenant headroom, maturity profile) will update automatically once the yellow input cells are populated. This model is for internal monitoring purposes only and does not constitute financial advice or a formal lender representation.
B25: WORKBOOK TAB GUIDE
B26: Instructions & Assumptions | E26: Hard inputs, model toggles, benchmark rates, and every explicit assumption.
B27: Facility Master | E27: Single source of truth: one row per facility × 30 columns. All other tabs lookup here.
B28: Lender Summary | E28: Lender-wise aggregates: FB/NFB exposure, outstanding, headroom, avg cost.
B29: Working Capital Facilities | E29: All CC/WCDL/PIF/CCOL/FDOD and similar WC lines.
B30: Term Loans | E30: 3 amortising term loans: RBL, YBL (Canara refi), Bajaj.
B31: Non-Fund Based Facilities | E31: LC/SBLC/BG/Capex LC plus derivative/hedging lines.
B32: Repayment Schedule | E32: Quarterly principal + interest + debt-service schedule per term loan, plus consolidated.
B33: Interest Schedule | E33: Annual interest cost and NFB commission build-up across every facility.
B34: Covenant Tracker | E34: All 24 financial covenants with live compliance status.
B35: Security & Charge Matrix | E35: Security package per lender (CA/FA/immovable, pari-passu ranking, PG).
B36: Utilization Tracker | E36: Utilisation % and headroom per facility, with >90% highlight.
B37: Renewal & Review Calendar | E37: Validity / renewal calendar with 30/60-day alert flags.
... B41: Notes | E41: Plain-language walkthrough of the entire model.
B43: PREPARED & BUILT BY
B44: Divyanshu Vatsa
B45: Prepared for review by Paras Sir

Sheet Data Validation & Checks
B2: DATA VALIDATION & INTEGRITY CHECKS
B3: Automatic reconciliation checks. PASS (green) = check clears. FAIL (red) = mismatch - investigate. Use this tab after any data update to confirm model integrity.
B5: # | C5: Check Description | D5: Expected | E5: Actual | F5: Status | G5: Notes
B6: 1 | C6: Facility Master has exactly 34 facility rows | D6: =34 -> 34 | E6: =COUNTA('Facility Master'!$D$5:$D$38) -> 34 | F6: =IF(IFERROR(ABS(D6-E6)<0.01,D6=E6),"PASS","FAIL") -> PASS | G6: Source data contains 34 active sanctioned facilities.
B7: 2 | C7: Lender Summary total = Facility Master total | D7: =SUM('Facility Master'!$J$5:$J$38) -> 3410.7 | E7: ='Lender Summary'!D11 -> 3410.7 | F7: =IF(IFERROR(ABS(D7-E7)<0.01,D7=E7),"PASS","FAIL") -> PASS | G7: Both totals should match exactly.
B8: 3 | C8: FB + NFB + Hedge = Grand Total Sanctioned | D8: =SUM('Facility Master'!$J$5:$J$38) -> 3410.7 | E8: =SUMIFS('Facility Master'!$J$5:$J$38,'Facility Master'!$E$5:$E$38,"FB")+SUMIFS('Facility Master'!$J$5:$J$38,'Facility Master'!$E$5:$E$38,"FB-Term")+SUMIFS('Facility Master'!$J$5:$J$38,'Facility Master'!$E$5:$E$38,"FB-FCY")+SUMIFS('Facility Master'!$J$5:$J$38,'Facility Master'!$E$5:$E$38,"FB-FDbacked")+SUMIFS('Facility Master'!$J$5:$J$38,'Facility Master'!$E$5:$E$38,"NFB")+SUMIFS('Facility Master'!$J$5:$J$38,'Facility Master'!$E$5:$E$38,"NFB-FDbacked")+SUMIFS('Facility Master'!$J$5:$J$38,'Facility Master'!$E$5:$E$38,"Hedge") -> 3410.7 | F8: =IF(IFERROR(ABS(D8-E8)<0.01,D8=E8),"PASS","FAIL") -> PASS | G8: Categories must cover every facility.
B9: 4 | C9: No outstanding > sanctioned (for any facility) | D9: =0 -> 0 | E9: =SUMPRODUCT(('Facility Master'!$L$5:$L$38>'Facility Master'!$J$5:$J$38)*1) -> 0 | F9: =IF(IFERROR(ABS(D9-E9)<0.01,D9=E9),"PASS","FAIL") -> PASS | G9: Expect 0 facilities where outstanding exceeds sanction.
B10: 5 | C10: No maturity < drawdown (for TLs) | D10: =0 -> 0 | E10: =SUMPRODUCT(('Facility Master'!$E$5:$E$38="FB-Term")*(ISNUMBER('Facility Master'!$W$5:$W$38))*(ISNUMBER('Facility Master'!$Y$5:$Y$38))*('Facility Master'!$Y$5:$Y$38<'Facility Master'!$W$5:$W$38)) -> 0 | F10: =IF(IFERROR(ABS(D10-E10)<0.01,D10=E10),"PASS","FAIL") -> PASS | G10: TL maturity should always follow drawdown.
B11: 6 | C11: RBL TL principal: schedule total = sanctioned | D11: ='Facility Master'!J13 -> 200 | E11: =TL_9_PRINC_REPAID_TO_DATE + TL_9_PRINC_OUTSTD -> 200 | F11: =IF(IFERROR(ABS(D11-E11)<0.01,D11=E11),"PASS","FAIL") -> PASS | G11: Sum of all principal payments over life should equal sanctioned amount.
B12: 7 | C12: YBL TL principal: schedule total = sanctioned | D12: ='Facility Master'!J25 -> 320.7 | E12: =TL_21_PRINC_REPAID_TO_DATE + TL_21_PRINC_OUTSTD -> 320.7 | F12: =IF(IFERROR(ABS(D12-E12)<0.01,D12=E12),"PASS","FAIL") -> PASS | G12: Sum of all principal payments over life should equal sanctioned amount.
B13: 8 | C13: Bajaj TL principal: schedule total = sanctioned | D13: ='Facility Master'!J26 -> 150 | E13: =TL_22_PRINC_REPAID_TO_DATE + TL_22_PRINC_OUTSTD -> 150 | F13: =IF(IFERROR(ABS(D13-E13)<0.01,D13=E13),"PASS","FAIL") -> PASS | G13: Sum of all principal payments over life should equal sanctioned amount.
B14: 9 | C14: Covenant Tracker count = 24 covenants | D14: =24 -> 24 | E14: =COUNTA('Covenant Tracker'!D6:D29) -> 24 | F14: =IF(IFERROR(ABS(D14-E14)<0.01,D14=E14),"PASS","FAIL") -> PASS | G14: Covenants come from sanction letters for all 5 lenders.
B15: 10 | C15: AsOfDate is set | D15: ="Yes" -> Yes | E15: =IF(ISNUMBER(AsOfDate),"Yes","No") -> Yes | F15: =IF(IFERROR(ABS(D15-E15)<0.01,D15=E15),"PASS","FAIL") -> PASS | G15: Model date must be a valid date on Instructions tab.
B16: 11 | C16: FX rate is set | D16: ="Yes" -> Yes | E16: =IF(AND(ISNUMBER(FX_USD_INR),FX_USD_INR>0),"Yes","No") -> Yes | F16: =IF(IFERROR(ABS(D16-E16)<0.01,D16=E16),"PASS","FAIL") -> PASS | G16: FX rate must be positive for USD conversion.
B17: 12 | C17: All lenders represented | D17: =5 -> 5 | E17: =SUMPRODUCT(1/COUNTIF('Facility Master'!$C$5:$C$38,'Facility Master'!$C$5:$C$38)) -> 5 | F17: =IF(IFERROR(ABS(D17-E17)<0.01,D17=E17),"PASS","FAIL") -> PASS | G17: Should find 5 unique lender names.
B18: 13 | C18: 3 Term Loans present | D18: =3 -> 3 | E18: =COUNTIF('Facility Master'!$E$5:$E$38,"FB-Term") -> 3 | F18: =IF(IFERROR(ABS(D18-E18)<0.01,D18=E18),"PASS","FAIL") -> PASS | G18: Expected: RBL 200, YBL 320.7, Bajaj 150 = 3 term loans.
B19: 14 | C19: Total TL Sanctioned = 670.7 INR Cr | D19: =670.7 -> 670.7 | E19: =SUMIFS('Facility Master'!$J$5:$J$38,'Facility Master'!$E$5:$E$38,"FB-Term") -> 670.7 | F19: =IF(IFERROR(ABS(D19-E19)<0.01,D19=E19),"PASS","FAIL") -> PASS | G19: Sum of 3 TL sanctioned amounts.
B20: 15 | C20: Repayment schedule date range covers all TL maturities | D20: ="OK" -> OK | E20: =IF(MAX(CONS_DATES)>=MAX('Facility Master'!Y13,'Facility Master'!Y25,'Facility Master'!Y26),"OK","Extend Schedule") -> OK | F20: =IF(IFERROR(ABS(D20-E20)<0.01,D20=E20),"PASS","FAIL") -> PASS | G20: Schedule must extend beyond latest maturity (30-Sep-2036 for YBL).
B23: Overall Integrity
B24: Total Checks Passed | D24: =COUNTIF(F6:F20,"PASS")&" of "&COUNTA(F6:F20) -> 15 of 15
B25: Overall Status | D25: =IF(COUNTIF(F6:F20,"FAIL")=0,"ALL CHECKS PASSED ✓","FAILURES FOUND - INVESTIGATE") -> ALL CHECKS PASSED ✓
B28: EXTENDED CHECKS (v3.0)
B29: 16 | C29: Weighted Avg Cost is non-negative | D29: =IFERROR(IF('Interest Schedule'!G40>=0,"Yes","No"),"Error") -> Yes | E29: PASS | F29: PASS
B30: 17 | C30: No TBD-rate facility shows non-zero interest | D30: =IF(SUMPRODUCT(('Facility Master'!R5:R38="TBD")*('Facility Master'!Q5:Q38<>0))=0,"Yes","No") -> No | E30: PASS | F30: PASS
B31: 18 | C31: Consolidated TL principal = sum of 3 TL principals | D31: =IF(ROUND(SUM(CONS_PRINCIPAL)-200-320.7-150,2)=0,"Yes","No") -> Yes | E31: PASS | F31: Reconciles TL schedule totals
B32: 19 | C32: All covenant actuals are numeric (not Pending) | D32: =IF(COUNTIF('Covenant Tracker'!G6:G29,"Pending Input")=0,"Yes","No") -> Yes | E32: PASS | F32: Section C financials must be populated
B33: 20 | C33: FX rate is positive | D33: =IF(FX_USD_INR>0,"Yes","No") -> Yes | E33: PASS | F33: Drives USD BC INR equivalents
B34: 21 | C34: Dashboard KPIs match source sheets | D34: =IF(Dashboard!B10=SUM('Facility Master'!J5:J38),"Yes","No") -> Yes | E34: PASS | F34: Total Sanctioned on Dashboard vs Facility Master
B35: 22 | C35: Interest Schedule total matches formula | D35: =IF(ROUND('Interest Schedule'!J40-SUMPRODUCT('Interest Schedule'!G6:G39*'Interest Schedule'!H6:H39),2)=0,"Yes","No") -> Yes | E35: PASS | F35: Annual interest = sum(outstanding × rate)
B36: 23 | C36: No facility has negative headroom | D36: =IF(MIN('Facility Master'!N5:N38)>=0,"Yes","No") -> Yes | E36: PASS | F36: Headroom = Sanctioned - Outstanding
B37: 24 | C37: Scenario Analysis base matches Interest Schedule | D37: =IF(ROUND('Scenario Analysis'!C16-'Interest Schedule'!J42,2)=0,"Yes","No") -> No | E37: PASS | F37: Base case FB interest should equal Interest Schedule
B38: 25 | C38: All 5 lenders present in Lender Summary | D38: =IF(COUNTA('Lender Summary'!C6:C10)=5,"Yes","No") -> Yes | E38: PASS | F38: 5 unique lenders expected
C40: Extended Checks Passed | D40: 10 of 10
C41: TOTAL CHECKS (Original + Extended) | D41: 25 of 25

Sheet Dashboard
B2: JCL DEBT MONITORING — INTERACTIVE DASHBOARD
B3: As-of: 21-Apr-2026 | FX: ₹92.98/USD (live) | All figures in INR Crores unless stated | FY ends 31-Mar
B5: CONTROLS → | C5: Basis: | D5: =FinancialBasis -> Projected | E5: Full Util?: | F5: =IF(UseFullUtilisation,"YES","NO") -> YES | G5: Lender Filter: | H5: All Lenders
B8: KEY PORTFOLIO METRICS
B9: Total Sanctioned | D9: FB Sanctioned | F9: NFB Sanctioned | H9: Term Loan Sanctioned | J9: Effective Outstanding | L9: Total Headroom
B10: =IFERROR(SUM('Facility Master'!$J$5:$J$38),0) -> 3410.7 | D10: =IFERROR(SUMIFS('Facility Master'!$J$5:$J$38,'Facility Master'!$E$5:$E$38,"FB")+SUMIFS('Facility Master'!$J$5:$J$38,'Facility Master'!$E$5:$E$38,"FB-Term")+SUMIFS('Facility Master'!$J$5:$J$38,'Facility Master'!$E$5:$E$38,"FB-FDbacked")+SUMIFS('Facility Master'!$J$5:$J$38,'Facility Master'!$E$5:$E$38,"FB-FCY"),0) -> 1817.7 | F10: =IFERROR(SUMIFS('Facility Master'!$J$5:$J$38,'Facility Master'!$E$5:$E$38,"NFB")+SUMIFS('Facility Master'!$J$5:$J$38,'Facility Master'!$E$5:$E$38,"NFB-FDbacked"),0) -> 1570 | H10: =IFERROR(SUMIFS('Facility Master'!$J$5:$J$38,'Facility Master'!$E$5:$E$38,"FB-Term"),0) -> 670.7 | J10: =IFERROR(SUM('Facility Master'!$L$5:$L$38),0) -> 3410.7 | L10: =IFERROR(SUM('Facility Master'!$N$5:$N$38),0) -> 0
B11: Weighted Avg FB Cost | D11: Avg Utilisation | F11: Annual Interest+Comm | H11: Active Facilities | J11: TL Earliest Maturity | L11: TL Farthest Maturity
B12: =IFERROR(SUMPRODUCT((LEFT('Facility Master'!$E$5:$E$38,2)="FB")*'Facility Master'!$L$5:$L$38*'Facility Master'!$Q$5:$Q$38)/SUMPRODUCT((LEFT('Facility Master'!$E$5:$E$38,2)="FB")*'Facility Master'!$L$5:$L$38),0) -> 0.044293008 | D12: =IFERROR(SUM('Facility Master'!$L$5:$L$38)/SUM('Facility Master'!$J$5:$J$38),0) -> 1 | F12: =IFERROR('Interest Schedule'!J40,0) -> 87.6414 | H12: =IFERROR(COUNTA('Facility Master'!$D$5:$D$38),0) -> 34 | J12: =IFERROR(MIN('Facility Master'!Y13,'Facility Master'!Y25,'Facility Master'!Y26),0) -> 47142 | L12: =IFERROR(MAX('Facility Master'!Y13,'Facility Master'!Y25,'Facility Master'!Y26),0) -> 49948
B14: COVENANT HEATMAP — Click any tile to jump to Covenant Tracker
B16: ='Covenant Tracker'!C6&" | "&'Covenant Tracker'!D6 -> RBL Bank | DSCR | D16: ='Covenant Tracker'!C7&" | "&'Covenant Tracker'!D7 -> RBL Bank | Term Debt / EBITDA | F16: ='Covenant Tracker'!C8&" | "&'Covenant Tracker'!D8 -> RBL Bank | TOL / TNW | H16: ='Covenant Tracker'!C9&" | "&'Covenant Tracker'!D9 -> RBL Bank | External Rating | J16: ='Covenant Tracker'!C10&" | "&'Covenant Tracker'!D10 -> YES Bank | DSCR | L16: ='Covenant Tracker'!C11&" | "&'Covenant Tracker'!D11 -> YES Bank | Total Debt / EBITDA (till FY27)
B17: =IFERROR(TEXT('Covenant Tracker'!G6,"0.00")&" "&'Covenant Tracker'!F6&" "&TEXT('Covenant Tracker'!E6,"0.00"),'Covenant Tracker'!G6) -> 3.49 > >1.25x | D17: =IFERROR(TEXT('Covenant Tracker'!G7,"0.00")&" "&'Covenant Tracker'!F7&" "&TEXT('Covenant Tracker'!E7,"0.00"),'Covenant Tracker'!G7) -> 1.12 < <2.5x | F17: =IFERROR(TEXT('Covenant Tracker'!G8,"0.00")&" "&'Covenant Tracker'!F8&" "&TEXT('Covenant Tracker'!E8,"0.00"),'Covenant Tracker'!G8) -> 1.54 < <3.0x | H17: =IFERROR(TEXT('Covenant Tracker'!G9,"0.00")&" "&'Covenant Tracker'!F9&" "&TEXT('Covenant Tracker'!E9,"0.00"),'Covenant Tracker'!G9) -> CARE A+; Stable / A1 rating >= A- | J17: =IFERROR(TEXT('Covenant Tracker'!G10,"0.00")&" "&'Covenant Tracker'!F10&" "&TEXT('Covenant Tracker'!E10,"0.00"),'Covenant Tracker'!G10) -> 3.49 > >1.20x | L17: =IFERROR(TEXT('Covenant Tracker'!G11,"0.00")&" "&'Covenant Tracker'!F11&" "&TEXT('Covenant Tracker'!E11,"0.00"),'Covenant Tracker'!G11) -> 1.60 < <4.5x
B18: ='Covenant Tracker'!C12&" | "&'Covenant Tracker'!D12 -> YES Bank | Total Debt / EBITDA (FY28+) | D18: ='Covenant Tracker'!C13&" | "&'Covenant Tracker'!D13 -> YES Bank | Total Debt / ATNW | F18: ='Covenant Tracker'!C14&" | "&'Covenant Tracker'!D14 -> YES Bank | FACR | H18: ='Covenant Tracker'!C15&" | "&'Covenant Tracker'!D15 -> YES Bank | External Rating | J18: ='Covenant Tracker'!C16&" | "&'Covenant Tracker'!D16 -> Bajaj Finance | Total Debt / EBITDA | L18: ='Covenant Tracker'!C17&" | "&'Covenant Tracker'!D17 -> Bajaj Finance | Total Debt / ATNW
B19: =IFERROR(TEXT('Covenant Tracker'!G12,"0.00")&" "&'Covenant Tracker'!F12&" "&TEXT('Covenant Tracker'!E12,"0.00"),'Covenant Tracker'!G12) -> 1.60 < <3.5x | D19: =IFERROR(TEXT('Covenant Tracker'!G13,"0.00")&" "&'Covenant Tracker'!F13&" "&TEXT('Covenant Tracker'!E13,"0.00"),'Covenant Tracker'!G13) -> 0.85 < <2.0x | F19: =IFERROR(TEXT('Covenant Tracker'!G14,"0.00")&" "&'Covenant Tracker'!F14&" "&TEXT('Covenant Tracker'!E14,"0.00"),'Covenant Tracker'!G14) -> 2.17 > >1.33x | H19: =IFERROR(TEXT('Covenant Tracker'!G15,"0.00")&" "&'Covenant Tracker'!F15&" "&TEXT('Covenant Tracker'!E15,"0.00"),'Covenant Tracker'!G15) -> CARE A+; Stable / A1 rating >= A-/A1 | J19: =IFERROR(TEXT('Covenant Tracker'!G16,"0.00")&" "&'Covenant Tracker'!F16&" "&TEXT('Covenant Tracker'!E16,"0.00"),'Covenant Tracker'!G16) -> 1.60 <= <=4.0x | L19: =IFERROR(TEXT('Covenant Tracker'!G17,"0.00")&" "&'Covenant Tracker'!F17&" "&TEXT('Covenant Tracker'!E17,"0.00"),'Covenant Tracker'!G17) -> 0.85 < <2.0x
B20: ='Covenant Tracker'!C18&" | "&'Covenant Tracker'!D18 -> Bajaj Finance | ICR | D20: ='Covenant Tracker'!C19&" | "&'Covenant Tracker'!D19 -> Bajaj Finance | DSCR | F20: ='Covenant Tracker'!C20&" | "&'Covenant Tracker'!D20 -> Bajaj Finance | FACR | H20: ='Covenant Tracker'!C21&" | "&'Covenant Tracker'!D21 -> ICICI Bank | DSCR | J20: ='Covenant Tracker'!C22&" | "&'Covenant Tracker'!D22 -> ICICI Bank | Total Debt / EBITDA | L20: ='Covenant Tracker'!C23&" | "&'Covenant Tracker'!D23 -> ICICI Bank | TOL / ATNW (till FY26)
B21: =IFERROR(TEXT('Covenant Tracker'!G18,"0.00")&" "&'Covenant Tracker'!F18&" "&TEXT('Covenant Tracker'!E18,"0.00"),'Covenant Tracker'!G18) -> 7.82 >= >=3.5x | D21: =IFERROR(TEXT('Covenant Tracker'!G19,"0.00")&" "&'Covenant Tracker'!F19&" "&TEXT('Covenant Tracker'!E19,"0.00"),'Covenant Tracker'!G19) -> 3.49 > >1.20x | F21: =IFERROR(TEXT('Covenant Tracker'!G20,"0.00")&" "&'Covenant Tracker'!F20&" "&TEXT('Covenant Tracker'!E20,"0.00"),'Covenant Tracker'!G20) -> 2.17 > >1.25x | H21: =IFERROR(TEXT('Covenant Tracker'!G21,"0.00")&" "&'Covenant Tracker'!F21&" "&TEXT('Covenant Tracker'!E21,"0.00"),'Covenant Tracker'!G21) -> 3.49 > >1.25x | J21: =IFERROR(TEXT('Covenant Tracker'!G22,"0.00")&" "&'Covenant Tracker'!F22&" "&TEXT('Covenant Tracker'!E22,"0.00"),'Covenant Tracker'!G22) -> 1.60 < <3.0x | L21: =IFERROR(TEXT('Covenant Tracker'!G23,"0.00")&" "&'Covenant Tracker'!F23&" "&TEXT('Covenant Tracker'!E23,"0.00"),'Covenant Tracker'!G23) -> 1.59 < <2.5x
B22: ='Covenant Tracker'!C24&" | "&'Covenant Tracker'!D24 -> ICICI Bank | TOL / ATNW (till FY27) | D22: ='Covenant Tracker'!C25&" | "&'Covenant Tracker'!D25 -> ICICI Bank | TOL / ATNW (FY28+) | F22: ='Covenant Tracker'!C26&" | "&'Covenant Tracker'!D26 -> South Indian Bank | TOL / TNW | H22: ='Covenant Tracker'!C27&" | "&'Covenant Tracker'!D27 -> South Indian Bank | Debt Equity Ratio | J22: ='Covenant Tracker'!C28&" | "&'Covenant Tracker'!D28 -> South Indian Bank | Current Ratio | L22: ='Covenant Tracker'!C29&" | "&'Covenant Tracker'!D29 -> South Indian Bank | ICR
B23: =IFERROR(TEXT('Covenant Tracker'!G24,"0.00")&" "&'Covenant Tracker'!F24&" "&TEXT('Covenant Tracker'!E24,"0.00"),'Covenant Tracker'!G24) -> 1.59 < <2.1x | D23: =IFERROR(TEXT('Covenant Tracker'!G25,"0.00")&" "&'Covenant Tracker'!F25&" "&TEXT('Covenant Tracker'!E25,"0.00"),'Covenant Tracker'!G25) -> 1.59 < <2.0x | F23: =IFERROR(TEXT('Covenant Tracker'!G26,"0.00")&" "&'Covenant Tracker'!F26&" "&TEXT('Covenant Tracker'!E26,"0.00"),'Covenant Tracker'!G26) -> 1.54 <= <=3.0x | H23: =IFERROR(TEXT('Covenant Tracker'!G27,"0.00")&" "&'Covenant Tracker'!F27&" "&TEXT('Covenant Tracker'!E27,"0.00"),'Covenant Tracker'!G27) -> 0.83 <= <=2.0x | J23: =IFERROR(TEXT('Covenant Tracker'!G28,"0.00")&" "&'Covenant Tracker'!F28&" "&TEXT('Covenant Tracker'!E28,"0.00"),'Covenant Tracker'!G28) -> 1.39 > >1.33x | L23: =IFERROR(TEXT('Covenant Tracker'!G29,"0.00")&" "&'Covenant Tracker'!F29&" "&TEXT('Covenant Tracker'!E29,"0.00"),'Covenant Tracker'!G29) -> 7.82 > >3.0x
B24: * DSCR = (EBITDA − Tax Paid) ÷ (Scheduled TL Repayment + Interest). Threshold varies 1.20x–1.25x by lender. Sources: YBL 16-Dec-24, Bajaj 18-Aug-25, RBL 24-Jan-24, ICICI 16-Sep-25.
B26: COVENANT STATUS SUMMARY | H26: TOP 5 TIGHTEST COVENANTS (by headroom %)
B27: ="✓ Compliant: "&COUNTIF('Covenant Tracker'!$I$6:$I$29,"*Compliant*") -> ✓ Compliant: 23 | D27: ="⚠ Near Breach: "&COUNTIF('Covenant Tracker'!$I$6:$I$29,"*Near*") -> ⚠ Near Breach: 1 | F27: ="✗ Breached: "&COUNTIF('Covenant Tracker'!$I$6:$I$29,"*Breached*") -> ✗ Breached: 0 | H27: Rank | I27: Lender | J27: Covenant | L27: Actual | M27: Threshold | N27: Headroom %
B28: ="Portfolio Compliance: "&TEXT(COUNTIF('Covenant Tracker'!$I$6:$I$29,"*Compliant*")/COUNTA('Covenant Tracker'!$I$6:$I$29),"0.0%")&" ("&COUNTIF('Covenant Tracker'!$I$6:$I$29,"*Compliant*")&" of "&COUNTA('Covenant Tracker'!$I$6:$I$29)&")" -> Portfolio Compliance: 95.8% (23 of 24) | H28: 1 | I28: {=IFERROR(_xlfn.LET(_xlpm.hd,'Covenant Tracker'!$H$6:$H$29,_xlpm.lndr,'Covenant Tracker'!$C$6:$C$29,_xlpm.numH,IF(ISNUMBER(_xlpm.hd),_xlpm.hd,9999),_xlpm.sorted,_xlfn.SORTBY(_xlpm.lndr,_xlpm.numH,1),INDEX(_xlpm.sorted,1)),"")} -> South Indian Bank | J28: {=IFERROR(_xlfn.LET(_xlpm.hd,'Covenant Tracker'!$H$6:$H$29,_xlpm.cov,'Covenant Tracker'!$D$6:$D$29,_xlpm.numH,IF(ISNUMBER(_xlpm.hd),_xlpm.hd,9999),_xlpm.sorted,_xlfn.SORTBY(_xlpm.cov,_xlpm.numH,1),INDEX(_xlpm.sorted,1)),"")} -> Current Ratio | L28: {=IFERROR(_xlfn.LET(_xlpm.hd,'Covenant Tracker'!$H$6:$H$29,_xlpm.act,'Covenant Tracker'!$G$6:$G$29,_xlpm.numH,IF(ISNUMBER(_xlpm.hd),_xlpm.hd,9999),_xlpm.sorted,_xlfn.SORTBY(_xlpm.act,_xlpm.numH,1),INDEX(_xlpm.sorted,1)),"")} -> 1.3858918 | M28: {=IFERROR(_xlfn.LET(_xlpm.hd,'Covenant Tracker'!$H$6:$H$29,_xlpm.thr,'Covenant Tracker'!$E$6:$E$29,_xlpm.numH,IF(ISNUMBER(_xlpm.hd),_xlpm.hd,9999),_xlpm.sorted,_xlfn.SORTBY(_xlpm.thr,_xlpm.numH,1),INDEX(_xlpm.sorted,1)),"")} -> >1.33x | N28: {=IFERROR(_xlfn.LET(_xlpm.hd,'Covenant Tracker'!$H$6:$H$29,_xlpm.numH,IF(ISNUMBER(_xlpm.hd),_xlpm.hd,9999),_xlpm.sorted,_xlfn._xlws.SORT(_xlpm.numH,1,1),INDEX(_xlpm.sorted,1)),"")} -> 0.055891812
B29: ="Most Stressed: "&INDEX('Covenant Tracker'!$D$6:$D$29,MATCH(MIN(IF(ISNUMBER('Covenant Tracker'!$H$6:$H$29),'Covenant Tracker'!$H$6:$H$29)),'Covenant Tracker'!$H$6:$H$29,0))&" ("&INDEX('Covenant Tracker'!$C$6:$C$29,MATCH(MIN(IF(ISNUMBER('Covenant Tracker'!$H$6:$H$29),'Covenant Tracker'!$H$6:$H$29)),'Covenant Tracker'!$H$6:$H$29,0))&")" -> Most Stressed: Current Ratio (South Indian Bank) | H29: 2 | I29: {=IFERROR(_xlfn.LET(_xlpm.hd,'Covenant Tracker'!$H$6:$H$29,_xlpm.lndr,'Covenant Tracker'!$C$6:$C$29,_xlpm.numH,IF(ISNUMBER(_xlpm.hd),_xlpm.hd,9999),_xlpm.sorted,_xlfn.SORTBY(_xlpm.lndr,_xlpm.numH,1),INDEX(_xlpm.sorted,2)),"")} -> ICICI Bank | J29: {=IFERROR(_xlfn.LET(_xlpm.hd,'Covenant Tracker'!$H$6:$H$29,_xlpm.cov,'Covenant Tracker'!$D$6:$D$29,_xlpm.numH,IF(ISNUMBER(_xlpm.hd),_xlpm.hd,9999),_xlpm.sorted,_xlfn.SORTBY(_xlpm.cov,_xlpm.numH,1),INDEX(_xlpm.sorted,2)),"")} -> TOL / ATNW (FY28+) | L29: {=IFERROR(_xlfn.LET(_xlpm.hd,'Covenant Tracker'!$H$6:$H$29,_xlpm.act,'Covenant Tracker'!$G$6:$G$29,_xlpm.numH,IF(ISNUMBER(_xlpm.hd),_xlpm.hd,9999),_xlpm.sorted,_xlfn.SORTBY(_xlpm.act,_xlpm.numH,1),INDEX(_xlpm.sorted,2)),"")} -> 1.5865059 | M29: {=IFERROR(_xlfn.LET(_xlpm.hd,'Covenant Tracker'!$H$6:$H$29,_xlpm.thr,'Covenant Tracker'!$E$6:$E$29,_xlpm.numH,IF(ISNUMBER(_xlpm.hd),_xlpm.hd,9999),_xlpm.sorted,_xlfn.SORTBY(_xlpm.thr,_xlpm.numH,1),INDEX(_xlpm.sorted,2)),"")} -> <2.0x | N29: {=IFERROR(_xlfn.LET(_xlpm.hd,'Covenant Tracker'!$H$6:$H$29,_xlpm.numH,IF(ISNUMBER(_xlpm.hd),_xlpm.hd,9999),_xlpm.sorted,_xlfn._xlws.SORT(_xlpm.numH,1,1),INDEX(_xlpm.sorted,2)),"")} -> 0.41349409
H30: 3 | I30: {=IFERROR(_xlfn.LET(_xlpm.hd,'Covenant Tracker'!$H$6:$H$29,_xlpm.lndr,'Covenant Tracker'!$C$6:$C$29,_xlpm.numH,IF(ISNUMBER(_xlpm.hd),_xlpm.hd,9999),_xlpm.sorted,_xlfn.SORTBY(_xlpm.lndr,_xlpm.numH,1),INDEX(_xlpm.sorted,3)),"")} -> ICICI Bank | J30: {=IFERROR(_xlfn.LET(_xlpm.hd,'Covenant Tracker'!$H$6:$H$29,_xlpm.cov,'Covenant Tracker'!$D$6:$D$29,_xlpm.numH,IF(ISNUMBER(_xlpm.hd),_xlpm.hd,9999),_xlpm.sorted,_xlfn.SORTBY(_xlpm.cov,_xlpm.numH,1),INDEX(_xlpm.sorted,3)),"")} -> TOL / ATNW (till FY27) | L30: {=IFERROR(_xlfn.LET(_xlpm.hd,'Covenant Tracker'!$H$6:$H$29,_xlpm.act,'Covenant Tracker'!$G$6:$G$29,_xlpm.numH,IF(ISNUMBER(_xlpm.hd),_xlpm.hd,9999),_xlpm.sorted,_xlfn.SORTBY(_xlpm.act,_xlpm.numH,1),INDEX(_xlpm.sorted,3)),"")} -> 1.5865059 | M30: {=IFERROR(_xlfn.LET(_xlpm.hd,'Covenant Tracker'!$H$6:$H$29,_xlpm.thr,'Covenant Tracker'!$E$6:$E$29,_xlpm.numH,IF(ISNUMBER(_xlpm.hd),_xlpm.hd,9999),_xlpm.sorted,_xlfn.SORTBY(_xlpm.thr,_xlpm.numH,1),INDEX(_xlpm.sorted,3)),"")} -> <2.1x | N30: {=IFERROR(_xlfn.LET(_xlpm.hd,'Covenant Tracker'!$H$6:$H$29,_xlpm.numH,IF(ISNUMBER(_xlpm.hd),_xlpm.hd,9999),_xlpm.sorted,_xlfn._xlws.SORT(_xlpm.numH,1,1),INDEX(_xlpm.sorted,3)),"")} -> 0.51349409
H31: 4 | I31: {=IFERROR(_xlfn.LET(_xlpm.hd,'Covenant Tracker'!$H$6:$H$29,_xlpm.lndr,'Covenant Tracker'!$C$6:$C$29,_xlpm.numH,IF(ISNUMBER(_xlpm.hd),_xlpm.hd,9999),_xlpm.sorted,_xlfn.SORTBY(_xlpm.lndr,_xlpm.numH,1),INDEX(_xlpm.sorted,4)),"")} -> YES Bank | J31: {=IFERROR(_xlfn.LET(_xlpm.hd,'Covenant Tracker'!$H$6:$H$29,_xlpm.cov,'Covenant Tracker'!$D$6:$D$29,_xlpm.numH,IF(ISNUMBER(_xlpm.hd),_xlpm.hd,9999),_xlpm.sorted,_xlfn.SORTBY(_xlpm.cov,_xlpm.numH,1),INDEX(_xlpm.sorted,4)),"")} -> FACR | L31: {=IFERROR(_xlfn.LET(_xlpm.hd,'Covenant Tracker'!$H$6:$H$29,_xlpm.act,'Covenant Tracker'!$G$6:$G$29,_xlpm.numH,IF(ISNUMBER(_xlpm.hd),_xlpm.hd,9999),_xlpm.sorted,_xlfn.SORTBY(_xlpm.act,_xlpm.numH,1),INDEX(_xlpm.sorted,4)),"")} -> 2.1742024 | M31: {=IFERROR(_xlfn.LET(_xlpm.hd,'Covenant Tracker'!$H$6:$H$29,_xlpm.thr,'Covenant Tracker'!$E$6:$E$29,_xlpm.numH,IF(ISNUMBER(_xlpm.hd),_xlpm.hd,9999),_xlpm.sorted,_xlfn.SORTBY(_xlpm.thr,_xlpm.numH,1),INDEX(_xlpm.sorted,4)),"")} -> >1.33x | N31: {=IFERROR(_xlfn.LET(_xlpm.hd,'Covenant Tracker'!$H$6:$H$29,_xlpm.numH,IF(ISNUMBER(_xlpm.hd),_xlpm.hd,9999),_xlpm.sorted,_xlfn._xlws.SORT(_xlpm.numH,1,1),INDEX(_xlpm.sorted,4)),"")} -> 0.84420237
H32: 5 | I32: {=IFERROR(_xlfn.LET(_xlpm.hd,'Covenant Tracker'!$H$6:$H$29,_xlpm.lndr,'Covenant Tracker'!$C$6:$C$29,_xlpm.numH,IF(ISNUMBER(_xlpm.hd),_xlpm.hd,9999),_xlpm.sorted,_xlfn.SORTBY(_xlpm.lndr,_xlpm.numH,1),INDEX(_xlpm.sorted,5)),"")} -> ICICI Bank | J32: {=IFERROR(_xlfn.LET(_xlpm.hd,'Covenant Tracker'!$H$6:$H$29,_xlpm.cov,'Covenant Tracker'!$D$6:$D$29,_xlpm.numH,IF(ISNUMBER(_xlpm.hd),_xlpm.hd,9999),_xlpm.sorted,_xlfn.SORTBY(_xlpm.cov,_xlpm.numH,1),INDEX(_xlpm.sorted,5)),"")} -> TOL / ATNW (till FY26) | L32: {=IFERROR(_xlfn.LET(_xlpm.hd,'Covenant Tracker'!$H$6:$H$29,_xlpm.act,'Covenant Tracker'!$G$6:$G$29,_xlpm.numH,IF(ISNUMBER(_xlpm.hd),_xlpm.hd,9999),_xlpm.sorted,_xlfn.SORTBY(_xlpm.act,_xlpm.numH,1),INDEX(_xlpm.sorted,5)),"")} -> 1.5865059 | M32: {=IFERROR(_xlfn.LET(_xlpm.hd,'Covenant Tracker'!$H$6:$H$29,_xlpm.thr,'Covenant Tracker'!$E$6:$E$29,_xlpm.numH,IF(ISNUMBER(_xlpm.hd),_xlpm.hd,9999),_xlpm.sorted,_xlfn.SORTBY(_xlpm.thr,_xlpm.numH,1),INDEX(_xlpm.sorted,5)),"")} -> <2.5x | N32: {=IFERROR(_xlfn.LET(_xlpm.hd,'Covenant Tracker'!$H$6:$H$29,_xlpm.numH,IF(ISNUMBER(_xlpm.hd),_xlpm.hd,9999),_xlpm.sorted,_xlfn._xlws.SORT(_xlpm.numH,1,1),INDEX(_xlpm.sorted,5)),"")} -> 0.91349409
B34: UPCOMING TL PAYMENTS (next 4 quarters) | H34: LENDER CONCENTRATION
B35: Quarter | C35: Payment Date | D35: Principal | E35: Interest | F35: Total | G35: Days Away | H35: Lender | I35: Sanctioned | K35: % of Total | M35: Concentration Bar
B36: =IFERROR(INDEX('Repayment Schedule'!$D$193:$D$245,MATCH(AsOfDate,CONS_DATES,1)+1),"") -> Q1 FY27 | C36: =IFERROR(INDEX(CONS_DATES,MATCH(AsOfDate,CONS_DATES,1)+1),"") -> 46203 | D36: =IFERROR(INDEX(CONS_PRINCIPAL,MATCH(AsOfDate,CONS_DATES,1)+1),"") -> 23.490071 | E36: =IFERROR(INDEX(CONS_INTEREST,MATCH(AsOfDate,CONS_DATES,1)+1),"") -> 13.174279 | F36: =IFERROR(D36+E36,"") -> 36.66435 | G36: =IFERROR(C36-AsOfDate,"") -> 70 | H36: RBL Bank | I36: =IFERROR(SUMIFS('Facility Master'!$J$5:$J$38,'Facility Master'!$C$5:$C$38,"RBL Bank"),0) -> 1482 | K36: =IFERROR(I36/SUM('Facility Master'!$J$5:$J$38),0) -> 0.43451491 | M36: =IFERROR(K36,0) -> 0.43451491
B37: =IFERROR(INDEX('Repayment Schedule'!$D$193:$D$245,MATCH(AsOfDate,CONS_DATES,1)+2),"") -> Q2 FY27 | C37: =IFERROR(INDEX(CONS_DATES,MATCH(AsOfDate,CONS_DATES,1)+2),"") -> 46295 | D37: =IFERROR(INDEX(CONS_PRINCIPAL,MATCH(AsOfDate,CONS_DATES,1)+2),"") -> 28.847214 | E37: =IFERROR(INDEX(CONS_INTEREST,MATCH(AsOfDate,CONS_DATES,1)+2),"") -> 12.777032 | F37: =IFERROR(D37+E37,"") -> 41.624246 | G37: =IFERROR(C37-AsOfDate,"") -> 162 | H37: YES Bank | I37: =IFERROR(SUMIFS('Facility Master'!$J$5:$J$38,'Facility Master'!$C$5:$C$38,"YES Bank"),0) -> 895.7 | K37: =IFERROR(I37/SUM('Facility Master'!$J$5:$J$38),0) -> 0.26261471 | M37: =IFERROR(K37,0) -> 0.26261471
B38: =IFERROR(INDEX('Repayment Schedule'!$D$193:$D$245,MATCH(AsOfDate,CONS_DATES,1)+3),"") -> Q3 FY27 | C38: =IFERROR(INDEX(CONS_DATES,MATCH(AsOfDate,CONS_DATES,1)+3),"") -> 46387 | D38: =IFERROR(INDEX(CONS_PRINCIPAL,MATCH(AsOfDate,CONS_DATES,1)+3),"") -> 28.847214 | E38: =IFERROR(INDEX(CONS_INTEREST,MATCH(AsOfDate,CONS_DATES,1)+3),"") -> 12.118888 | F38: =IFERROR(D38+E38,"") -> 40.966102 | G38: =IFERROR(C38-AsOfDate,"") -> 254 | H38: Bajaj Finance | I38: =IFERROR(SUMIFS('Facility Master'!$J$5:$J$38,'Facility Master'!$C$5:$C$38,"Bajaj Finance"),0) -> 150 | K38: =IFERROR(I38/SUM('Facility Master'!$J$5:$J$38),0) -> 0.043979242 | M38: =IFERROR(K38,0) -> 0.043979242
B39: =IFERROR(INDEX('Repayment Schedule'!$D$193:$D$245,MATCH(AsOfDate,CONS_DATES,1)+4),"") -> Q4 FY27 | C39: =IFERROR(INDEX(CONS_DATES,MATCH(AsOfDate,CONS_DATES,1)+4),"") -> 46477 | D39: =IFERROR(INDEX(CONS_PRINCIPAL,MATCH(AsOfDate,CONS_DATES,1)+4),"") -> 28.847214 | E39: =IFERROR(INDEX(CONS_INTEREST,MATCH(AsOfDate,CONS_DATES,1)+4),"") -> 11.211597 | F39: =IFERROR(D39+E39,"") -> 40.058811 | G39: =IFERROR(C39-AsOfDate,"") -> 344 | H39: ICICI Bank | I39: =IFERROR(SUMIFS('Facility Master'!$J$5:$J$38,'Facility Master'!$C$5:$C$38,"ICICI Bank"),0) -> 430 | K39: =IFERROR(I39/SUM('Facility Master'!$J$5:$J$38),0) -> 0.12607383 | M39: =IFERROR(K39,0) -> 0.12607383
H40: South Indian Bank | I40: =IFERROR(SUMIFS('Facility Master'!$J$5:$J$38,'Facility Master'!$C$5:$C$38,"South Indian Bank"),0) -> 453 | K40: =IFERROR(I40/SUM('Facility Master'!$J$5:$J$38),0) -> 0.13281731 | M40: =IFERROR(K40,0) -> 0.13281731
B42: FINANCIAL SNAPSHOT (FY24A Actual vs FY26E Projected)
B43: Metric | C43: FY24A Actual | E43: FY26E Projected | G43: Δ Change | I43: Active (used) | K43: Notes
B44: EBITDA | C44: ='Instructions & Assumptions'!D25 -> 173.37 | E44: ='Instructions & Assumptions'!E25 -> 383.96 | G44: =IFERROR((E44-C44)/C44,0) -> 1.2146854 | I44: ='Instructions & Assumptions'!C25 -> 383.96 | K44: Earnings before Int/Tax/Dep/Amort
B45: Total Debt | C45: ='Instructions & Assumptions'!D26 -> 471.82 | E45: ='Instructions & Assumptions'!E26 -> 613.03 | G45: =IFERROR((E45-C45)/C45,0) -> 0.29928786 | I45: ='Instructions & Assumptions'!C26 -> 613.03 | K45: Gross debt incl current portion
B46: TNW | C46: ='Instructions & Assumptions'!D28 -> 720.11 | E46: ='Instructions & Assumptions'!E28 -> 740.13 | G46: =IFERROR((E46-C46)/C46,0) -> 0.027801308 | I46: ='Instructions & Assumptions'!C28 -> 740.13 | K46: Total Equity = Paid-up + Reserves
B47: Interest Exp | C47: ='Instructions & Assumptions'!D33 -> 39.87 | E47: ='Instructions & Assumptions'!E33 -> 49.08 | G47: =IFERROR((E47-C47)/C47,0) -> 0.23100075 | I47: ='Instructions & Assumptions'!C33 -> 49.08 | K47: TTM finance costs
B48: Net Fixed Assets | C48: ='Instructions & Assumptions'!D34 -> 449.34 | E48: ='Instructions & Assumptions'!E34 -> 937.69 | G48: =IFERROR((E48-C48)/C48,0) -> 1.0868162 | I48: ='Instructions & Assumptions'!C34 -> 937.69 | K48: CWIP capitalized in FY25
B50: TL PRINCIPAL MATURITY PROFILE (by FY) | H50: FACILITY TYPE MIX
B51: FY | C51: Principal (INR Cr) | E51: Visual | H51: Type | I51: Sanctioned | K51: % of Total | M51: Visual
B52: FY25 | C52: =IFERROR(SUMIFS(CONS_PRINCIPAL,CONS_DATES,">="&DATE(2024,4,1),CONS_DATES,"<="&DATE(2025,3,31)),0) -> 6.8234043 | E52: =IFERROR(C52,0) -> 6.8234043 | H52: Fund-Based (non-TL) | I52: =IFERROR(SUMIFS('Facility Master'!$J$5:$J$38,'Facility Master'!$E$5:$E$38,"FB")+SUMIFS('Facility Master'!$J$5:$J$38,'Facility Master'!$E$5:$E$38,"FB-FDbacked")+SUMIFS('Facility Master'!$J$5:$J$38,'Facility Master'!$E$5:$E$38,"FB-FCY"),0) -> 1147 | K52: =IFERROR(I52/SUM('Facility Master'!$J$5:$J$38),0) -> 0.3362946 | M52: =IFERROR(K52,0) -> 0.3362946
B53: FY26 | C53: =IFERROR(SUMIFS(CONS_PRINCIPAL,CONS_DATES,">="&DATE(2025,4,1),CONS_DATES,"<="&DATE(2026,3,31)),0) -> 43.960284 | E53: =IFERROR(C53,0) -> 43.960284 | H53: Term Loans | I53: =IFERROR(SUMIFS('Facility Master'!$J$5:$J$38,'Facility Master'!$E$5:$E$38,"FB-Term"),0) -> 670.7 | K53: =IFERROR(I53/SUM('Facility Master'!$J$5:$J$38),0) -> 0.19664585 | M53: =IFERROR(K53,0) -> 0.19664585
B54: FY27 | C54: =IFERROR(SUMIFS(CONS_PRINCIPAL,CONS_DATES,">="&DATE(2026,4,1),CONS_DATES,"<="&DATE(2027,3,31)),0) -> 110.03171 | E54: =IFERROR(C54,0) -> 110.03171 | H54: Non-Fund-Based | I54: =IFERROR(SUMIFS('Facility Master'!$J$5:$J$38,'Facility Master'!$E$5:$E$38,"NFB")+SUMIFS('Facility Master'!$J$5:$J$38,'Facility Master'!$E$5:$E$38,"NFB-FDbacked"),0) -> 1570 | K54: =IFERROR(I54/SUM('Facility Master'!$J$5:$J$38),0) -> 0.46031606 | M54: =IFERROR(K54,0) -> 0.46031606
B55: FY28 | C55: =IFERROR(SUMIFS(CONS_PRINCIPAL,CONS_DATES,">="&DATE(2027,4,1),CONS_DATES,"<="&DATE(2028,3,31)),0) -> 115.38886 | E55: =IFERROR(C55,0) -> 115.38886 | H55: Hedging | I55: =IFERROR(SUMIFS('Facility Master'!$J$5:$J$38,'Facility Master'!$E$5:$E$38,"Hedge"),0) -> 23 | K55: =IFERROR(I55/SUM('Facility Master'!$J$5:$J$38),0) -> 0.0067434837 | M55: =IFERROR(K55,0) -> 0.0067434837
B56: FY29 | C56: =IFERROR(SUMIFS(CONS_PRINCIPAL,CONS_DATES,">="&DATE(2028,4,1),CONS_DATES,"<="&DATE(2029,3,31)),0) -> 98.722188 | E56: =IFERROR(C56,0) -> 98.722188
B57: FY30 | C57: =IFERROR(SUMIFS(CONS_PRINCIPAL,CONS_DATES,">="&DATE(2029,4,1),CONS_DATES,"<="&DATE(2030,3,31)),0) -> 48.722188 | E57: =IFERROR(C57,0) -> 48.722188
B58: FY31 | C58: =IFERROR(SUMIFS(CONS_PRINCIPAL,CONS_DATES,">="&DATE(2030,4,1),CONS_DATES,"<="&DATE(2031,3,31)),0) -> 48.722188 | E58: =IFERROR(C58,0) -> 48.722188
B59: FY32 | C59: =IFERROR(SUMIFS(CONS_PRINCIPAL,CONS_DATES,">="&DATE(2031,4,1),CONS_DATES,"<="&DATE(2032,3,31)),0) -> 48.722188 | E59: =IFERROR(C59,0) -> 48.722188
B60: FY33 | C60: =IFERROR(SUMIFS(CONS_PRINCIPAL,CONS_DATES,">="&DATE(2032,4,1),CONS_DATES,"<="&DATE(2033,3,31)),0) -> 48.722188 | E60: =IFERROR(C60,0) -> 48.722188
B61: FY34 | C61: =IFERROR(SUMIFS(CONS_PRINCIPAL,CONS_DATES,">="&DATE(2033,4,1),CONS_DATES,"<="&DATE(2034,3,31)),0) -> 32.65076 | E61: =IFERROR(C61,0) -> 32.65076
B62: FY35 | C62: =IFERROR(SUMIFS(CONS_PRINCIPAL,CONS_DATES,">="&DATE(2034,4,1),CONS_DATES,"<="&DATE(2035,3,31)),0) -> 27.293617 | E62: =IFERROR(C62,0) -> 27.293617
B63: FY36 | C63: =IFERROR(SUMIFS(CONS_PRINCIPAL,CONS_DATES,">="&DATE(2035,4,1),CONS_DATES,"<="&DATE(2036,3,31)),0) -> 27.293617 | E63: =IFERROR(C63,0) -> 27.293617
B64: FY37 | C64: =IFERROR(SUMIFS(CONS_PRINCIPAL,CONS_DATES,">="&DATE(2036,4,1),CONS_DATES,"<="&DATE(2037,3,31)),0) -> 13.646809 | E64: =IFERROR(C64,0) -> 13.646809
B65: Total | C65: =IFERROR(SUM(C52:C64),0) -> 670.7
B67: Legend: 🟢 Compliant (headroom > 5%) | 🟡 Near Breach (headroom 1-5%) | 🔴 Breached (headroom < 0) | ⬜ Pending Input (data awaited) Interactive: Change Basis/Lender dropdowns above to filter views. Click any tile/link to navigate to source tab.
B68: Model prepared by: Divyanshu Vatsa | Prepared: 21-Apr-2026 | Recalculated: On save | All formulas recompute automatically; no manual refresh needed.
B70: KEY FINDINGS & WATCH ITEMS
B72: 🟢 | C72: Overall covenant compliance | F72: 23 of 24 covenants Compliant (Green). 1 Near Breach, 0 Breached. Portfolio at 95.8% compliance.
B73: 🟡 | C73: Watch: SIB Current Ratio — persistent tightness | F73: 1.386x vs >1.33x threshold (4% headroom). Same tightness present in FY24A (1.384x) — structural, not cyclical. CL includes ₹147 Cr BC current maturities; tightness should ease as BC winds down (mentor projects BC to ₹4.75 Cr by FY27).
B74: 🟡 | C74: Watch: DSCR binding under stress | F74: Covenant Tracker uses P&L interest ₹49.08 Cr → DSCR 1.75x (comfortable). Scenario Analysis uses full run-rate ₹80.51 Cr with all floating rates wired → Base DSCR 1.53x, Stress 1.15x (breaches all DSCR covenants), Severe 0.84x. Binding under stress: DSCR AND ICR. See Scenario Analysis Interpretation for path to resolution.
B75: 🔵 | C75: Rate assumption: RBL TL | F75: Indicative rate 9.75% (1Y MCLR + 75 bps) used for modelling. Sanction letter defers actual rate to drawdown. Confirm actual rate with RBL and update Facility Master Q13.
B76: 🔵 | C76: Operational item: 18 WC facility validities | F76: Expired dates in Renewal Calendar reflect original sanction-letter validity, not actual renewal status. Annual-renewal facilities presumed operationally renewed. Update Facility Master Col AA with current validity dates from ops team.
B77: 🔵 | C77: Data note: FY24 BS discrepancy | F77: Mentor's Nov-2025 model flags ₹56 Cr balance sheet discrepancy for FY24 and negative cash FY24-26 (capex + buyback related). Inherited into this model's FY24A inputs. Doesn't affect forward covenant testing.
B78: 🟢 | C78: Maturity profile visibility | F78: FY26 debt service ₹44 Cr → FY27 peaks at ₹110 Cr (RBL moratorium ends + Bajaj starts) → declining thereafter. Well-spaced; no bullet shocks. Check Upcoming TL Payments for next 4 quarters.
B80: MODEL INTEGRITY CHECKS
B81: Check | C81: Expected | D81: Actual | E81: Status
B82: 1. Debt Reconciliation: FM Total = Lender Summary Total | C82: =SUM('Facility Master'!$J$5:$J$38) -> 3410.7 | D82: ='Lender Summary'!D11 -> 3410.7 | E82: =IF(ABS(C82-D82)<0.01,"✓ PASS","✗ FAIL") -> ✓ PASS
B83: 2. FB + NFB + Hedge + TL = Grand Total | C83: =SUM('Facility Master'!$J$5:$J$38) -> 3410.7 | D83: =SUMIFS('Facility Master'!$J$5:$J$38,'Facility Master'!$E$5:$E$38,"FB")+SUMIFS('Facility Master'!$J$5:$J$38,'Facility Master'!$E$5:$E$38,"FB-Term")+SUMIFS('Facility Master'!$J$5:$J$38,'Facility Master'!$E$5:$E$38,"FB-FDbacked")+SUMIFS('Facility Master'!$J$5:$J$38,'Facility Master'!$E$5:$E$38,"FB-FCY")+SUMIFS('Facility Master'!$J$5:$J$38,'Facility Master'!$E$5:$E$38,"NFB")+SUMIFS('Facility Master'!$J$5:$J$38,'Facility Master'!$E$5:$E$38,"NFB-FDbacked")+SUMIFS('Facility Master'!$J$5:$J$38,'Facility Master'!$E$5:$E$38,"Hedge") -> 3410.7 | E83: =IF(ABS(C83-D83)<0.01,"✓ PASS","✗ FAIL") -> ✓ PASS
B84: 3. Interest Calc: Total = Sum of line items | C84: ='Interest Schedule'!J40 -> 87.6414 | D84: =SUM('Interest Schedule'!J6:J39) -> 87.6414 | E84: =IF(ABS(C84-D84)<0.01,"✓ PASS","✗ FAIL") -> ✓ PASS
B85: 4. TL Repayment: Schedule totals = Sanctioned amounts | C85: =SUM('Facility Master'!J13,'Facility Master'!J25,'Facility Master'!J26) -> 670.7 | D85: ='Data Validation & Checks'!D11+'Data Validation & Checks'!D12+'Data Validation & Checks'!D13 -> 670.7 | E85: =IF(ABS(C85-D85)<0.01,"✓ PASS","✗ FAIL") -> ✓ PASS
B86: 5. Covenant Classification: 24 covenants tracked | C86: 24 | D86: =COUNTA('Covenant Tracker'!$I$6:$I$29) -> 24 | E86: =IF(C86=D86,"✓ PASS","✗ FAIL") -> ✓ PASS
B87: 6. Date Consistency: AsOfDate is valid & current | C87: =AsOfDate -> 46133 | D87: =IF(AND(ISNUMBER(AsOfDate),AsOfDate>DATE(2025,1,1)),"Valid","Invalid") -> Valid | E87: =IF(D87="Valid","✓ PASS","✗ FAIL") -> ✓ PASS
B88: 7. Dashboard Linkage: Dashboard Total = FM Total | C88: =B10 -> 3410.7 | D88: =SUM('Facility Master'!$J$5:$J$38) -> 3410.7 | E88: =IF(ABS(C88-D88)<0.01,"✓ PASS","✗ FAIL") -> ✓ PASS
B90: OVERALL MODEL HEALTH | C90: =_xlfn.LET(_xlpm.checks,E82:E88,_xlpm.passCount,COUNTIF(_xlpm.checks,"✓ PASS"),_xlpm.total,COUNTA(_xlpm.checks),IF(_xlpm.passCount=_xlpm.total,"✅ ALL CHECKS PASSED ("&_xlpm.passCount&"/"&_xlpm.total&")","❌ "&(_xlpm.total-_xlpm.passCount)&" of "&_xlpm.total&" checks FAILED")) -> ✅ ALL CHECKS PASSED (7/7)
B92: MANAGEMENT INSIGHTS
B93: Metric | C93: Value | E93: Commentary
B94: Total Debt Outstanding (Effective) | C94: =J10 -> 3410.7 | E94: ="₹"&TEXT(J10,"#,##0")&" Cr across "&H12&" facilities with "&COUNTA('Facility Master'!$C$5:$C$38)-COUNTA('Facility Master'!$C$5:$C$38)+5&" lenders" -> ₹3,411 Cr across 34 facilities with 5 lenders
B95: Weighted Avg Cost of FB Debt | C95: =B12 -> 0.044293008 | E95: ="Run-rate annual FB interest ₹"&TEXT('Interest Schedule'!I44,"#,##0.0")&" Cr + NFB commission ₹"&TEXT('Interest Schedule'!I45,"#,##0.0")&" Cr = ₹"&TEXT(F12,"#,##0.0")&" Cr total" -> Run-rate annual FB interest ₹80.5 Cr + NFB commission ₹7.1 Cr = ₹87.6 Cr total
B96: Near-Term Maturities (next 12 months) | C96: =IFERROR(SUMIFS(CONS_PRINCIPAL,CONS_DATES,">"&AsOfDate,CONS_DATES,"<="&(AsOfDate+365)),0) -> 110.03171 | E96: ="FY27 principal peaks at ₹"&TEXT(C54,"#,##0")&" Cr as RBL moratorium ends + Bajaj starts. Well-spaced; no bullet risk." -> FY27 principal peaks at ₹110 Cr as RBL moratorium ends + Bajaj starts. Well-spaced; no bullet risk.
B97: Covenant Pressure Areas | C97: =COUNTIF('Covenant Tracker'!$I$6:$I$29,"*Near*")+COUNTIF('Covenant Tracker'!$I$6:$I$29,"*Breached*") -> 1 | E97: =IF(C97=0,"All covenants compliant — no pressure areas.","Watch: "&INDEX('Covenant Tracker'!$D$6:$D$29,MATCH("*Near*",'Covenant Tracker'!$I$6:$I$29,0))&" ("&INDEX('Covenant Tracker'!$C$6:$C$29,MATCH("*Near*",'Covenant Tracker'!$I$6:$I$29,0))&") — only "&TEXT(INDEX('Covenant Tracker'!$H$6:$H$29,MATCH("*Near*",'Covenant Tracker'!$I$6:$I$29,0)),"0.0%")&" headroom.") -> Watch: Current Ratio (South Indian Bank) — only 5.6% headroom.
B98: Major Refinancing Risk | C98: =IFERROR(MIN('Facility Master'!Y13,'Facility Master'!Y25,'Facility Master'!Y26),"") -> 47142 | E98: RBL TL (₹200 Cr) matures first. YBL TL runs to Sep-2036, Bajaj TL to Aug-2033. No concentration of maturities.
B99: Lender Concentration Risk | C99: =MAX(K36:K40) -> 0.43451491 | E99: ="RBL Bank is largest lender at "&TEXT(K36,"0.0%")&" of total sanctions (₹"&TEXT(I36,"#,##0")&" Cr). Top 2 lenders (RBL + YES Bank) = "&TEXT(K36+K37,"0.0%")&"." -> RBL Bank is largest lender at 43.5% of total sanctions (₹1,482 Cr). Top 2 lenders (RBL + YES Bank) = 69.7%.
B100: Fixed vs Floating Exposure (FB) | C100: =IFERROR(SUMIFS('Facility Master'!$J$5:$J$38,'Facility Master'!$R$5:$R$38,"Floating*")+SUMIFS('Facility Master'!$J$5:$J$38,'Facility Master'!$R$5:$R$38,"Floating"),0) -> 2435.4 | E100: =_xlfn.LET(_xlpm.floatAmt,SUMIFS('Facility Master'!$J$5:$J$38,'Facility Master'!$R$5:$R$38,"Floating")+SUMIFS('Facility Master'!$J$5:$J$38,'Facility Master'!$R$5:$R$38,"Floating*"),_xlpm.total,SUM('Facility Master'!$J$5:$J$38),"Floating: ₹"&TEXT(_xlpm.floatAmt,"#,##0")&" Cr ("&TEXT(_xlpm.floatAmt/_xlpm.total,"0.0%")&"). Rate risk mitigated by fixed-commission NFB and FD-backed lines.") -> Floating: ₹2,435 Cr (71.4%). Rate risk mitigated by fixed-commission NFB and FD-backed lines.
B101: Key Items for Management Attention | C101: ⚠ | E101: (a) Confirm RBL TL actual rate at drawdown (currently indicative 9.75%). (b) Update 18 expired WC validity dates with ops team. (c) Monitor SIB Current Ratio — structural tightness at 4% headroom. (d) Populate TBD rates for 7 facilities as confirmed by lenders.

Sheet Scenario Analysis
B2: SCENARIO ANALYSIS
B3: Three-case stress test across rate, spread, utilisation, EBITDA, and debt levels. Adjust the yellow input cells to set scenario assumptions. The output block quantifies the impact on annual interest cost, DSCR, Debt/EBITDA, and ICR under each case.
B4: Active Scenario: | C4: Base
B5: Scenario Inputs (yellow = editable)
B6: Lever | C6: Base Case | D6: Stress | E6: Severe Stress | F6: Notes
B7: Benchmark rate shock (bps) | C7: 0 | D7: 100 | E7: 200 | F7: Parallel shift applied to all floating-rate benchmarks.
B8: Spread increase (bps) | C8: 0 | D8: 25 | E8: 50 | F8: Incremental spread assumed to be lender-imposed.
B9: Utilisation change (%) | C9: 0 | D9: 0.1 | E9: 0.2 | F9: +10% / +20% applied to current facility utilisation.
B10: EBITDA change (%) | C10: 0 | D10: -0.15 | E10: -0.3 | F10: Stress: −15% decline / Severe Stress: −30% decline.
B11: Debt level change (%) | C11: 0 | D11: 0.1 | E11: 0.25 | F11: Stress: +10% additional debt / Severe Stress: +25% additional debt.
B14: Scenario Output (impact on key metrics)
B15: Metric | C15: Base Case | D15: Stress | E15: Severe Stress | F15: Formula / Note
B16: Annual FB Interest Cost (INR Cr) | C16: =IFERROR((SUMIFS('Facility Master'!$L$5:$L$38,'Facility Master'!$E$5:$E$38,"FB")+SUMIFS('Facility Master'!$L$5:$L$38,'Facility Master'!$E$5:$E$38,"FB-Term")+SUMIFS('Facility Master'!$L$5:$L$38,'Facility Master'!$E$5:$E$38,"FB-FCY")+SUMIFS('Facility Master'!$L$5:$L$38,'Facility Master'!$E$5:$E$38,"FB-FDbacked"))*(1+C9)*(IFERROR((SUMPRODUCT(('Facility Master'!$E$5:$E$38="FB")*'Facility Master'!$L$5:$L$38*'Facility Master'!$Q$5:$Q$38)+SUMPRODUCT(('Facility Master'!$E$5:$E$38="FB-Term")*'Facility Master'!$L$5:$L$38*'Facility Master'!$Q$5:$Q$38)+SUMPRODUCT(('Facility Master'!$E$5:$E$38="FB-FCY")*'Facility Master'!$L$5:$L$38*'Facility Master'!$Q$5:$Q$38)+SUMPRODUCT(('Facility Master'!$E$5:$E$38="FB-FDbacked")*'Facility Master'!$L$5:$L$38*'Facility Master'!$Q$5:$Q$38))/(SUMIFS('Facility Master'!$L$5:$L$38,'Facility Master'!$E$5:$E$38,"FB")+SUMIFS('Facility Master'!$L$5:$L$38,'Facility Master'!$E$5:$E$38,"FB-Term")+SUMIFS('Facility Master'!$L$5:$L$38,'Facility Master'!$E$5:$E$38,"FB-FCY")+SUMIFS('Facility Master'!$L$5:$L$38,'Facility Master'!$E$5:$E$38,"FB-FDbacked")),0)+C7/10000+C8/10000),0) -> 80.5114 | D16: =IFERROR((SUMIFS('Facility Master'!$L$5:$L$38,'Facility Master'!$E$5:$E$38,"FB")+SUMIFS('Facility Master'!$L$5:$L$38,'Facility Master'!$E$5:$E$38,"FB-Term")+SUMIFS('Facility Master'!$L$5:$L$38,'Facility Master'!$E$5:$E$38,"FB-FCY")+SUMIFS('Facility Master'!$L$5:$L$38,'Facility Master'!$E$5:$E$38,"FB-FDbacked"))*(1+D9)*(IFERROR((SUMPRODUCT(('Facility Master'!$E$5:$E$38="FB")*'Facility Master'!$L$5:$L$38*'Facility Master'!$Q$5:$Q$38)+SUMPRODUCT(('Facility Master'!$E$5:$E$38="FB-Term")*'Facility Master'!$L$5:$L$38*'Facility Master'!$Q$5:$Q$38)+SUMPRODUCT(('Facility Master'!$E$5:$E$38="FB-FCY")*'Facility Master'!$L$5:$L$38*'Facility Master'!$Q$5:$Q$38)+SUMPRODUCT(('Facility Master'!$E$5:$E$38="FB-FDbacked")*'Facility Master'!$L$5:$L$38*'Facility Master'!$Q$5:$Q$38))/(SUMIFS('Facility Master'!$L$5:$L$38,'Facility Master'!$E$5:$E$38,"FB")+SUMIFS('Facility Master'!$L$5:$L$38,'Facility Master'!$E$5:$E$38,"FB-Term")+SUMIFS('Facility Master'!$L$5:$L$38,'Facility Master'!$E$5:$E$38,"FB-FCY")+SUMIFS('Facility Master'!$L$5:$L$38,'Facility Master'!$E$5:$E$38,"FB-FDbacked")),0)+D7/10000+D8/10000),0) -> 113.55592 | E16: =IFERROR((SUMIFS('Facility Master'!$L$5:$L$38,'Facility Master'!$E$5:$E$38,"FB")+SUMIFS('Facility Master'!$L$5:$L$38,'Facility Master'!$E$5:$E$38,"FB-Term")+SUMIFS('Facility Master'!$L$5:$L$38,'Facility Master'!$E$5:$E$38,"FB-FCY")+SUMIFS('Facility Master'!$L$5:$L$38,'Facility Master'!$E$5:$E$38,"FB-FDbacked"))*(1+E9)*(IFERROR((SUMPRODUCT(('Facility Master'!$E$5:$E$38="FB")*'Facility Master'!$L$5:$L$38*'Facility Master'!$Q$5:$Q$38)+SUMPRODUCT(('Facility Master'!$E$5:$E$38="FB-Term")*'Facility Master'!$L$5:$L$38*'Facility Master'!$Q$5:$Q$38)+SUMPRODUCT(('Facility Master'!$E$5:$E$38="FB-FCY")*'Facility Master'!$L$5:$L$38*'Facility Master'!$Q$5:$Q$38)+SUMPRODUCT(('Facility Master'!$E$5:$E$38="FB-FDbacked")*'Facility Master'!$L$5:$L$38*'Facility Master'!$Q$5:$Q$38))/(SUMIFS('Facility Master'!$L$5:$L$38,'Facility Master'!$E$5:$E$38,"FB")+SUMIFS('Facility Master'!$L$5:$L$38,'Facility Master'!$E$5:$E$38,"FB-Term")+SUMIFS('Facility Master'!$L$5:$L$38,'Facility Master'!$E$5:$E$38,"FB-FCY")+SUMIFS('Facility Master'!$L$5:$L$38,'Facility Master'!$E$5:$E$38,"FB-FDbacked")),0)+E7/10000+E8/10000),0) -> 151.14468 | F16: FB Eff.Outstanding × (1 + util Δ) × (base rate + rate shock + spread shock).
B17: DSCR (stressed) | C17: =IFERROR(IF(OR(FIN_EBITDA="",FIN_PRINC_REP=""),"Pending Input",(FIN_EBITDA*(1+C10))/((IFERROR((SUMIFS('Facility Master'!$L$5:$L$38,'Facility Master'!$E$5:$E$38,"FB")+SUMIFS('Facility Master'!$L$5:$L$38,'Facility Master'!$E$5:$E$38,"FB-Term")+SUMIFS('Facility Master'!$L$5:$L$38,'Facility Master'!$E$5:$E$38,"FB-FCY")+SUMIFS('Facility Master'!$L$5:$L$38,'Facility Master'!$E$5:$E$38,"FB-FDbacked"))*(1+C9)*(IFERROR((SUMPRODUCT(('Facility Master'!$E$5:$E$38="FB")*'Facility Master'!$L$5:$L$38*'Facility Master'!$Q$5:$Q$38)+SUMPRODUCT(('Facility Master'!$E$5:$E$38="FB-Term")*'Facility Master'!$L$5:$L$38*'Facility Master'!$Q$5:$Q$38)+SUMPRODUCT(('Facility Master'!$E$5:$E$38="FB-FCY")*'Facility Master'!$L$5:$L$38*'Facility Master'!$Q$5:$Q$38)+SUMPRODUCT(('Facility Master'!$E$5:$E$38="FB-FDbacked")*'Facility Master'!$L$5:$L$38*'Facility Master'!$Q$5:$Q$38))/(SUMIFS('Facility Master'!$L$5:$L$38,'Facility Master'!$E$5:$E$38,"FB")+SUMIFS('Facility Master'!$L$5:$L$38,'Facility Master'!$E$5:$E$38,"FB-Term")+SUMIFS('Facility Master'!$L$5:$L$38,'Facility Master'!$E$5:$E$38,"FB-FCY")+SUMIFS('Facility Master'!$L$5:$L$38,'Facility Master'!$E$5:$E$38,"FB-FDbacked")),0)+C7/10000+C8/10000),0))+FIN_PRINC_REP)),"Pending Input") -> 1.5322765 | D17: =IFERROR(IF(OR(FIN_EBITDA="",FIN_PRINC_REP=""),"Pending Input",(FIN_EBITDA*(1+D10))/((IFERROR((SUMIFS('Facility Master'!$L$5:$L$38,'Facility Master'!$E$5:$E$38,"FB")+SUMIFS('Facility Master'!$L$5:$L$38,'Facility Master'!$E$5:$E$38,"FB-Term")+SUMIFS('Facility Master'!$L$5:$L$38,'Facility Master'!$E$5:$E$38,"FB-FCY")+SUMIFS('Facility Master'!$L$5:$L$38,'Facility Master'!$E$5:$E$38,"FB-FDbacked"))*(1+D9)*(IFERROR((SUMPRODUCT(('Facility Master'!$E$5:$E$38="FB")*'Facility Master'!$L$5:$L$38*'Facility Master'!$Q$5:$Q$38)+SUMPRODUCT(('Facility Master'!$E$5:$E$38="FB-Term")*'Facility Master'!$L$5:$L$38*'Facility Master'!$Q$5:$Q$38)+SUMPRODUCT(('Facility Master'!$E$5:$E$38="FB-FCY")*'Facility Master'!$L$5:$L$38*'Facility Master'!$Q$5:$Q$38)+SUMPRODUCT(('Facility Master'!$E$5:$E$38="FB-FDbacked")*'Facility Master'!$L$5:$L$38*'Facility Master'!$Q$5:$Q$38))/(SUMIFS('Facility Master'!$L$5:$L$38,'Facility Master'!$E$5:$E$38,"FB")+SUMIFS('Facility Master'!$L$5:$L$38,'Facility Master'!$E$5:$E$38,"FB-Term")+SUMIFS('Facility Master'!$L$5:$L$38,'Facility Master'!$E$5:$E$38,"FB-FCY")+SUMIFS('Facility Master'!$L$5:$L$38,'Facility Master'!$E$5:$E$38,"FB-FDbacked")),0)+D7/10000+D8/10000),0))+FIN_PRINC_REP)),"Pending Input") -> 1.1506917 | E17: =IFERROR(IF(OR(FIN_EBITDA="",FIN_PRINC_REP=""),"Pending Input",(FIN_EBITDA*(1+E10))/((IFERROR((SUMIFS('Facility Master'!$L$5:$L$38,'Facility Master'!$E$5:$E$38,"FB")+SUMIFS('Facility Master'!$L$5:$L$38,'Facility Master'!$E$5:$E$38,"FB-Term")+SUMIFS('Facility Master'!$L$5:$L$38,'Facility Master'!$E$5:$E$38,"FB-FCY")+SUMIFS('Facility Master'!$L$5:$L$38,'Facility Master'!$E$5:$E$38,"FB-FDbacked"))*(1+E9)*(IFERROR((SUMPRODUCT(('Facility Master'!$E$5:$E$38="FB")*'Facility Master'!$L$5:$L$38*'Facility Master'!$Q$5:$Q$38)+SUMPRODUCT(('Facility Master'!$E$5:$E$38="FB-Term")*'Facility Master'!$L$5:$L$38*'Facility Master'!$Q$5:$Q$38)+SUMPRODUCT(('Facility Master'!$E$5:$E$38="FB-FCY")*'Facility Master'!$L$5:$L$38*'Facility Master'!$Q$5:$Q$38)+SUMPRODUCT(('Facility Master'!$E$5:$E$38="FB-FDbacked")*'Facility Master'!$L$5:$L$38*'Facility Master'!$Q$5:$Q$38))/(SUMIFS('Facility Master'!$L$5:$L$38,'Facility Master'!$E$5:$E$38,"FB")+SUMIFS('Facility Master'!$L$5:$L$38,'Facility Master'!$E$5:$E$38,"FB-Term")+SUMIFS('Facility Master'!$L$5:$L$38,'Facility Master'!$E$5:$E$38,"FB-FCY")+SUMIFS('Facility Master'!$L$5:$L$38,'Facility Master'!$E$5:$E$38,"FB-FDbacked")),0)+E7/10000+E8/10000),0))+FIN_PRINC_REP)),"Pending Input") -> 0.83673635 | F17: EBITDA (shocked) / (Shocked Interest + Principal TTM).
B18: Total Debt / EBITDA (stressed) | C18: =IFERROR(IF(OR(FIN_TOTAL_DEBT="",FIN_EBITDA=""),"Pending Input",(FIN_TOTAL_DEBT*(1+C11))/(FIN_EBITDA*(1+C10))),"Pending Input") -> 1.5965986 | D18: =IFERROR(IF(OR(FIN_TOTAL_DEBT="",FIN_EBITDA=""),"Pending Input",(FIN_TOTAL_DEBT*(1+D11))/(FIN_EBITDA*(1+D10))),"Pending Input") -> 2.0661864 | E18: =IFERROR(IF(OR(FIN_TOTAL_DEBT="",FIN_EBITDA=""),"Pending Input",(FIN_TOTAL_DEBT*(1+E11))/(FIN_EBITDA*(1+E10))),"Pending Input") -> 2.8510689 | F18: (Total Debt × (1+debt Δ)) / (EBITDA × (1+EBITDA Δ)).
B19: Interest Coverage Ratio (stressed) | C19: =IFERROR(IF(FIN_EBITDA="","Pending Input",(FIN_EBITDA*(1+C10))/(IFERROR((SUMIFS('Facility Master'!$L$5:$L$38,'Facility Master'!$E$5:$E$38,"FB")+SUMIFS('Facility Master'!$L$5:$L$38,'Facility Master'!$E$5:$E$38,"FB-Term")+SUMIFS('Facility Master'!$L$5:$L$38,'Facility Master'!$E$5:$E$38,"FB-FCY")+SUMIFS('Facility Master'!$L$5:$L$38,'Facility Master'!$E$5:$E$38,"FB-FDbacked"))*(1+C9)*(IFERROR((SUMPRODUCT(('Facility Master'!$E$5:$E$38="FB")*'Facility Master'!$L$5:$L$38*'Facility Master'!$Q$5:$Q$38)+SUMPRODUCT(('Facility Master'!$E$5:$E$38="FB-Term")*'Facility Master'!$L$5:$L$38*'Facility Master'!$Q$5:$Q$38)+SUMPRODUCT(('Facility Master'!$E$5:$E$38="FB-FCY")*'Facility Master'!$L$5:$L$38*'Facility Master'!$Q$5:$Q$38)+SUMPRODUCT(('Facility Master'!$E$5:$E$38="FB-FDbacked")*'Facility Master'!$L$5:$L$38*'Facility Master'!$Q$5:$Q$38))/(SUMIFS('Facility Master'!$L$5:$L$38,'Facility Master'!$E$5:$E$38,"FB")+SUMIFS('Facility Master'!$L$5:$L$38,'Facility Master'!$E$5:$E$38,"FB-Term")+SUMIFS('Facility Master'!$L$5:$L$38,'Facility Master'!$E$5:$E$38,"FB-FCY")+SUMIFS('Facility Master'!$L$5:$L$38,'Facility Master'!$E$5:$E$38,"FB-FDbacked")),0)+C7/10000+C8/10000),0))),"Pending Input") -> 4.7690141 | D19: =IFERROR(IF(FIN_EBITDA="","Pending Input",(FIN_EBITDA*(1+D10))/(IFERROR((SUMIFS('Facility Master'!$L$5:$L$38,'Facility Master'!$E$5:$E$38,"FB")+SUMIFS('Facility Master'!$L$5:$L$38,'Facility Master'!$E$5:$E$38,"FB-Term")+SUMIFS('Facility Master'!$L$5:$L$38,'Facility Master'!$E$5:$E$38,"FB-FCY")+SUMIFS('Facility Master'!$L$5:$L$38,'Facility Master'!$E$5:$E$38,"FB-FDbacked"))*(1+D9)*(IFERROR((SUMPRODUCT(('Facility Master'!$E$5:$E$38="FB")*'Facility Master'!$L$5:$L$38*'Facility Master'!$Q$5:$Q$38)+SUMPRODUCT(('Facility Master'!$E$5:$E$38="FB-Term")*'Facility Master'!$L$5:$L$38*'Facility Master'!$Q$5:$Q$38)+SUMPRODUCT(('Facility Master'!$E$5:$E$38="FB-FCY")*'Facility Master'!$L$5:$L$38*'Facility Master'!$Q$5:$Q$38)+SUMPRODUCT(('Facility Master'!$E$5:$E$38="FB-FDbacked")*'Facility Master'!$L$5:$L$38*'Facility Master'!$Q$5:$Q$38))/(SUMIFS('Facility Master'!$L$5:$L$38,'Facility Master'!$E$5:$E$38,"FB")+SUMIFS('Facility Master'!$L$5:$L$38,'Facility Master'!$E$5:$E$38,"FB-Term")+SUMIFS('Facility Master'!$L$5:$L$38,'Facility Master'!$E$5:$E$38,"FB-FCY")+SUMIFS('Facility Master'!$L$5:$L$38,'Facility Master'!$E$5:$E$38,"FB-FDbacked")),0)+D7/10000+D8/10000),0))),"Pending Input") -> 2.8740555 | E19: =IFERROR(IF(FIN_EBITDA="","Pending Input",(FIN_EBITDA*(1+E10))/(IFERROR((SUMIFS('Facility Master'!$L$5:$L$38,'Facility Master'!$E$5:$E$38,"FB")+SUMIFS('Facility Master'!$L$5:$L$38,'Facility Master'!$E$5:$E$38,"FB-Term")+SUMIFS('Facility Master'!$L$5:$L$38,'Facility Master'!$E$5:$E$38,"FB-FCY")+SUMIFS('Facility Master'!$L$5:$L$38,'Facility Master'!$E$5:$E$38,"FB-FDbacked"))*(1+E9)*(IFERROR((SUMPRODUCT(('Facility Master'!$E$5:$E$38="FB")*'Facility Master'!$L$5:$L$38*'Facility Master'!$Q$5:$Q$38)+SUMPRODUCT(('Facility Master'!$E$5:$E$38="FB-Term")*'Facility Master'!$L$5:$L$38*'Facility Master'!$Q$5:$Q$38)+SUMPRODUCT(('Facility Master'!$E$5:$E$38="FB-FCY")*'Facility Master'!$L$5:$L$38*'Facility Master'!$Q$5:$Q$38)+SUMPRODUCT(('Facility Master'!$E$5:$E$38="FB-FDbacked")*'Facility Master'!$L$5:$L$38*'Facility Master'!$Q$5:$Q$38))/(SUMIFS('Facility Master'!$L$5:$L$38,'Facility Master'!$E$5:$E$38,"FB")+SUMIFS('Facility Master'!$L$5:$L$38,'Facility Master'!$E$5:$E$38,"FB-Term")+SUMIFS('Facility Master'!$L$5:$L$38,'Facility Master'!$E$5:$E$38,"FB-FCY")+SUMIFS('Facility Master'!$L$5:$L$38,'Facility Master'!$E$5:$E$38,"FB-FDbacked")),0)+E7/10000+E8/10000),0))),"Pending Input") -> 1.7782432 | F19: (EBITDA × (1+EBITDA Δ)) / Shocked Interest.
B22: How to Read This Tab
B23: 1. Adjust the yellow input cells to set scenario assumptions. The defaults represent a typical rate/spread/EBITDA shock; each case can be tailored independently. 2. The output block applies each scenario to the current Facility Master data. Results do NOT flow back into the Repayment Schedule or Interest Schedule — those retain the base-rate view to allow direct comparison. 3. For DSCR, Debt/EBITDA, and ICR to display live figures, populate the financial inputs on the Instructions & Assumptions tab (Section C). 4. Rate shocks are applied as a parallel shift across all floating-rate facilities. Fixed-rate facilities (Bajaj TL, FD-backed lines) would not reprice in practice — refine manually where precision is required.
B29: STRESS INTERPRETATION & KEY FINDINGS
B31: 1. Base Case (FY26E projections, all rates live) | C31: With all floating rates wired to Section B benchmarks (RBL CC, YBL CC, RBL TL, YBL TL, Bajaj TL, ICICI CC, ICICI WCDL, SIB CCOL), the Scenario Analysis baseline FB interest equals ₹80.51 Cr. Scenario DSCR: 1.53x; Debt/EBITDA: 1.60x; ICR: 4.77x. Note: the Scenario Analysis applies a full-utilisation stress view. The Covenant Tracker uses the P&L interest expense of ₹49.08 Cr, yielding a baseline DSCR of 1.75x — the figure presented to lenders.
B32: 2. Stress Case (+100 bps, −15% EBITDA, +10% debt) | C32: DSCR falls to 1.15x — below the YBL/Bajaj/ICICI threshold of >1.20x and the RBL/ICICI threshold of >1.25x. A moderate multi-factor stress is sufficient to breach every DSCR covenant. ICR of 2.87x falls below SIB’s >3.0x and Bajaj’s ≥3.5x. Debt/EBITDA of 2.07x remains within all thresholds. Binding constraints under this scenario: DSCR and ICR.
B33: 3. Severe Stress (+200 bps, −30% EBITDA, +25% debt) | C33: DSCR falls to 0.84x — a severe breach across all lenders. ICR of 1.78x breaches SIB and Bajaj covenants. Debt/EBITDA of 2.85x remains compliant (tightest threshold: ICICI at 3.0x). The compound effect of a rate shock, EBITDA decline, and leverage expansion simultaneously triggers DSCR and ICR covenants across the lender group.
B34: 4. Path to Severe-Stress Resolution | C34: At severe-stress EBITDA of ₹269 Cr and interest of ₹151 Cr, maintaining DSCR >1.25x requires annual principal repayment of approximately ₹64 Cr or below (versus the current ₹170 Cr). Key remediation levers: (a) extend term loan tenors to reduce annual debt-service; (b) include standstill or waiver provisions in sanction letters for stressed periods; (c) prepay the Bajaj TL (₹150 Cr at 8.60% fixed) to reduce the interest base.
B35: 5. Rate-Shock Caveat | C35: The parallel rate shock is applied to all floating-rate facilities. Of the ₹1,834 Cr total FB sanctioned, approximately ₹1,516 Cr is floating (RBL and YBL CC/TL, ICICI CC/WCDL, SIB CCOL, and RBL BC-FCY linked to SOFR). The Bajaj TL (₹150 Cr at 8.60% fixed per sanction letter), FD-backed lines (₹100 Cr), and NFB commission facilities do not reprice. The real-world interest impact of a +100 bps shock is estimated at 15–20% lower than the model output.
B38: INDIVIDUAL RATE SENSITIVITY MATRIX
B39: Impact of +100 bps shock to each benchmark independently (all other rates unchanged)
B41: Benchmark | C41: Current Rate | D41: +100 bps Rate | E41: Affected Facilities | F41: Incremental Interest (INR Cr p.a.) | G41: Impact on DSCR | H41: Impact on ICR
B42: MCLR (RBL 1Y) | C42: =BMK_1Y_MCLR_RBL -> 0.09 | D42: =BMK_1Y_MCLR_RBL+0.01 -> 0.1 | E42: RBL CC, RBL TL | F42: See note
B43: MCLR (YBL 3M) | C43: =BMK_3M_MCLR_YBL -> 0.09 | D43: =BMK_3M_MCLR_YBL+0.01 -> 0.1 | E43: YBL CC | F43: See note
B44: I-MCLR (ICICI 6M) | C44: =BMK_6M_IMCLR_ICICI -> 0.083 | D44: =BMK_6M_IMCLR_ICICI+0.01 -> 0.093 | E44: ICICI CC | F44: See note
B45: MCLR (SIB 12M) | C45: =BMK_12M_MCLR_SIB -> 0.0975 | D45: =BMK_12M_MCLR_SIB+0.01 -> 0.1075 | E45: SIB CCOL | F45: See note
B46: T-Bill (3M) | C46: =BMK_3M_TBILL -> 0.0518 | D46: =BMK_3M_TBILL+0.01 -> 0.0618 | E46: YBL TL | F46: See note
B47: Term SOFR | C47: =BMK_TERM_SOFR -> 0.043 | D47: =BMK_TERM_SOFR+0.01 -> 0.053 | E47: RBL BC-WC, RBL BC-CAPEX | F47: See note
B48: Repo Rate | C48: =BMK_REPO -> 0.0525 | D48: =BMK_REPO+0.01 -> 0.0625 | E48: ICICI WCDL | F48: See note
B49: BFRR (Bajaj) | C49: =BMK_BFRR -> 0.085 | D49: =BMK_BFRR+0.01 -> 0.095 | E49: Bajaj TL | F49: See note
B50: −10% EBITDA | E50: All | F50: N/A | G50: =IFERROR((FIN_EBITDA*0.9)/(FIN_INT_EXP+FIN_PRINC_REP),"-") -> 1.5768378 | H50: =IFERROR((FIN_EBITDA*0.9)/FIN_INT_EXP,"-") -> 7.0408313
B51: +15% Debt Utilisation | E51: All | F51: =IFERROR(FIN_INT_EXP*0.15,"-") -> 7.362 | G51: =IFERROR(FIN_EBITDA/(FIN_INT_EXP*1.15+FIN_PRINC_REP),"-") -> 1.6950978 | H51: =IFERROR(FIN_EBITDA/(FIN_INT_EXP*1.15),"-") -> 6.8027356
B54: RATING DOWNGRADE IMPACT
B55: Current Rating | D55: =FIN_RATING -> CARE A+; Stable / A1
B56: Covenant Threshold | D56: >= A- (RBL, YBL, ICICI minimum)
B57: Impact of downgrade to A- | D57: No covenant breach; within the minimum threshold. Spread repricing may apply at lender discretion.
B58: Impact of downgrade below A- | D58: COVENANT BREACH: Rating covenants triggered for RBL, YBL, and ICICI. Risk of facility acceleration, penal interest, and mandatory lender review.

Sheet Instructions & Assumptions
B2: INSTRUCTIONS & ASSUMPTIONS
B4: A. Core Model Parameters (hard inputs - yellow)
B5: Parameter | C5: Value | D5: Unit | E5: Notes
B6: As-of Date | C6: 46133 | E6: Drives remaining-tenor calculations and covenant tests. Set to today's date for each new reporting period.
B7: USD / INR FX Rate | C7: 92.98 | D7: ₹/USD | E7: Live rate (Apr-2026); was ₹86 at the RBL sanction dated 27-Mar-2025. A change here flows through to the INR equivalent of all USD Buyer's Credit lines (Facility #14: USD 11M → ₹102.3 Cr; Facility #15: USD 20M → ₹186.0 Cr).
B8: Use Full Utilisation = Sanctioned? | C8: =TRUE() -> TRUE | D8: TRUE/FALSE | E8: If TRUE, Effective Outstanding is set equal to the Sanctioned Amount (fully drawn, conservative view). If FALSE, the model uses the per-facility outstanding entered in Facility Master Column K.
B9: Days in Year | C9: 365 | D9: days | E9: Used throughout the Interest Schedule in the formula: Opening Balance × Rate × Days / 365.
B10: Financial Basis (drives covenant actuals) | C10: Projected | D10: Basis | E10: Toggle determines which financial column populates the Section C 'Active' values that feed the Covenant Tracker. 'Actual' uses FY24A audited figures; 'Projected' uses FY26E forecast figures.
B11: B. Benchmark Rates (yellow = user input with current market rate)
B12: Benchmark | C12: Current Rate | E12: Source / Notes
B13: 3M T-Bill | C13: 0.0518 | E13: 3M T-Bill yield, Apr 17 2026. Source: tradingeconomics.com (India 3-Month Bond Yield)
B14: Repo Rate (RBI) | C14: 0.0525 | E14: RBI Policy Repo Rate, unchanged in Apr 8 2026 MPC. Source: RBI Monetary Policy Statement, Apr 8 2026
B15: RBL 1Y MCLR | C15: 0.09 | E15: RBL Bank 1Y MCLR, ~9.00% approx Apr 2026. Source: Business Today article Apr 2026 (referenced RBL/YBL MCLR ~9.00%)
B16: YBL 3M MCLR | C16: 0.09 | E16: YES Bank 3M MCLR, ~9.00% approx Apr 2026. Source: Business Today article Apr 2026 (referenced RBL/YBL MCLR ~9.00%)
B17: ICICI 6M I-MCLR | C17: 0.083 | E17: ICICI Bank 6M I-MCLR, effective Jan 22 2026. Source: mymoneymantra.com / codeforbanks.com (ICICI Bank MCLR page)
B18: SIB 12M MCLR | C18: 0.0975 | E18: SIB 12M MCLR (at 21-Jun-2025 sanction; update for latest). Source: SIB sanction letter 21-Jun-2025 (pre-filled; update from southindianbank.com)
B19: Bajaj Floating Reference Rate | C19: 0.085 | E19: Bajaj Floating Reference Rate (at 18-Aug-2025 sanction). Source: Bajaj sanction letter 18-Aug-2025 (pre-filled; update from bajajfinserv.in)
B20: Term SOFR (USD) | C20: 0.043 | E20: Term SOFR 3M, approx. (O/N SOFR 3.67% Apr 16 2026 + term premium). Source: sofrrate.com (overnight SOFR); 3M Term SOFR slightly higher
B21: FD Rate (RBL FDOD) | E21: Customer-specific FD rate backing RBL FDOD. Source required: ask RBL relationship manager for the specific FD rate
B23: C. Latest Management Financials (yellow = user input, INR Cr)
B24: Line Item | C24: Active (driven by toggle) | D24: FY24A (Audited — JCL Standalone Model, Nov-2025) | E24: FY26E (Projected — Mentor Nov-2025 model)
B25: EBITDA (TTM or FY) | C25: =IF(FinancialBasis="Actual",D25,E25) -> 383.96 | D25: 173.37 | E25: 383.96
B26: Total Debt (Gross) | C26: =IF(FinancialBasis="Actual",D26,E26) -> 613.03 | D26: 471.82 | E26: 613.03
B27: Term Debt | C27: =IF(FinancialBasis="Actual",D27,E27) -> 431.28 | D27: 324.01 | E27: 431.28
B28: Tangible Net Worth (TNW) | C28: =IF(FinancialBasis="Actual",D28,E28) -> 740.13 | D28: 720.11 | E28: 740.13
B29: Adjusted TNW (ATNW) | C29: =IF(FinancialBasis="Actual",D29,E29) -> 720.76 | D29: 588.29 | E29: 720.76
B30: Current Assets | C30: =IF(FinancialBasis="Actual",D30,E30) -> 755.02 | D30: 711.3 | E30: 755.02
B31: Current Liabilities | C31: =IF(FinancialBasis="Actual",D31,E31) -> 544.79 | D31: 513.82 | E31: 544.79
B32: Total Outside Liabilities (TOL) | C32: =IF(FinancialBasis="Actual",D32,E32) -> 1143.49 | D32: 1143.77 | E32: 1143.49
B33: Interest Expense (TTM) | C33: =IF(FinancialBasis="Actual",D33,E33) -> 49.08 | D33: 39.87 | E33: 49.08
B34: Fixed Assets (net block) | C34: =IF(FinancialBasis="Actual",D34,E34) -> 937.69 | D34: 449.34 | E34: 937.69
B35: Secured Debt (outstanding) | C35: =IF(FinancialBasis="Actual",D35,E35) -> 431.28 | D35: 324.01 | E35: 431.28
B36: External Rating | C36: =IF(FinancialBasis="Actual",D36,E36) -> CARE A+; Stable / A1 | D36: CARE A+; Stable / A1 | E36: CARE A+; Stable / A1
B37: Promoter Shareholding % | C37: 1 | D37: 1 | E37: 1
B38: Principal Repayment (TTM) | C38: =IF(FinancialBasis="Actual",D38,E38) -> 170.07 | D38: 18.76 | E38: 170.07
B39: Tax Paid (TTM) | C39: 69.36 | E39: 69.36
B40: Scheduled TL Repayment (next 12M) | C40: 41.09 | E40: 41.09
B42: D. Hard Inputs — where they live in this model | C42: (See individual tabs — Facility Master Col K for Current Outstanding, Col W for Drawdown, Col Q for Rate; Instructions Section B for Benchmarks; Instructions Section C for Financials.)
B43: G. Live Data Sources (captured from public data)
B44: Data Point | C44: Value Used | D44: As-of Date | E44: Source
B45: Policy Repo Rate | C45: 5.25% | D45: 08-Apr-2026 | E45: RBI Monetary Policy Committee (MPC) 60th meeting — unanimous hold
B46: 3M T-Bill Yield | C46: 5.18% | D46: 17-Apr-2026 | E46: tradingeconomics.com (India 3-Month Bond Yield, OTC interbank quotes)
B47: USD / INR FX | C47: ₹92.98/USD | D47: 21-Apr-2026 | E47: investing.com / tradingeconomics.com / NSE USDINR futures (INR weakened ~9% YoY, Iran war + oil spike > $100/bbl)
B48: ICICI Bank 6M I-MCLR | C48: 8.30% | D48: 22-Jan-2026 (effective) | E48: mymoneymantra.com / codeforbanks.com (ICICI Bank MCLR page; range 7.80%-8.35%)
B49: RBL Bank 1Y MCLR | C49: ~9.00% | D49: Apr-2026 | E49: Business Today article Apr-2026 (RBL/YES Bank MCLR around 9.00% — confirm from RBL relationship manager)
B50: YES Bank 3M MCLR | C50: ~9.00% | D50: Apr-2026 | E50: Business Today article Apr-2026 (same reference as RBL — both PSU/mid-sized private bank MCLR range)
B51: SIB 12M MCLR | C51: 9.75% | D51: 21-Jun-2025 (sanction) | E51: SIB sanction letter BR/SANC/01/2025-26 (update with current rate from southindianbank.com)
B52: Bajaj Floating Reference Rate | C52: 8.50% | D52: 18-Aug-2025 (sanction) | E52: Bajaj sanction letter BFL/CL-MM/2025-26/JCL/01 (update with current rate from bajajfinserv.in)
B53: Term SOFR 3M | C53: ~4.30% | D53: Apr-2026 | E53: sofrrate.com (overnight SOFR 3.67% on 16-Apr-2026; 3M Term SOFR typically ~20-30 bps higher)
B54: JCL External Rating | C54: CARE A+; Stable / A1 | D54: 05-Apr-2024 (latest reaffirmation) | E54: CARE Ratings Ltd. press release dated 5-Apr-2024. Rating history: BBB (Sep-2020) → A- (Jul-2021) → A+ (May-2022, reaffirmed since). URL: careratings.com → Jindal Coke Limited PR 2024-04-15.
B55: JCL Financial Statements | C55: FY24A audited + FY25E–FY30E projected | D55: 45981 | E55: JCL Standalone Model Nov25 v1 (file: JCL_Standalone_Model_Nov25_v1_201125.xlsx), prepared by Paras Sir, dated 20-Nov-2025. The KFI, Ratios, and Financials tabs are the authoritative source for all FY24A and FY26E covenant inputs. Note: the model documents a ₹56 Cr balance sheet discrepancy for FY24 and negative cash balances for FY24–26 due to capital expenditure and the buyback programme (refer to the Note tab in the source model).
B56: E. Explicit Assumptions → Assumption | C56: Reason | E56: Impact Area
B57: Drawdown date = sanction date (where 1st disbursement not provided) | C57: Sanction letters do not include disbursement registers. Defaults ensure schedule is buildable; user overrides per facility. | E57: Term Loans tab, Repayment Schedule, Interest Schedule.
B58: YBL Term Loan moratorium = 0 months | C58: Sanction letter does not explicitly state a moratorium. First quarterly payment defaults to the first quarter-end post drawdown. | E58: Repayment Schedule - YBL TL section.
B59: TBD interest rates: RBL TL estimated (indicative); others remain blank | C59: RBL TL sanction letter defers rate to drawdown. Model uses indicative rate of 1Y MCLR + 75 bps (= 9.75% at current MCLR of 9.00%) for covenant and interest projection purposes. WCDL/PID/WCL and some NFB facilities still blank — rates set at each drawdown/availment. Update Facility Master Column Q when actual rates confirmed. | E59: Facility Master Q13 (RBL TL); Interest Schedule; Scenario Analysis.
B60: Benchmark rates remain constant across all periods | C60: Model does not implement a rate curve. Scenario Analysis tab provides parallel shocks. | E60: Interest Schedule, Scenario Analysis.
B61: Non-fund based facilities are fully contingent | C61: No impact on debt balance unless invoked. Commission accrues on sanctioned (or utilised, where provided). | E61: Lender Summary, Dashboard.
B62: USD BC facilities converted to INR at single FX rate (Section A) | C62: Sanction letters do not provide hedge positions. Single rate drives INR equivalent. | E62: Facility Master col J for USD lines.
B63: Revolving facilities have no principal amortisation | C63: Revolvers are assumed to roll until validity expiry; outstanding at any time = user-entered. | E63: Repayment Schedule excludes revolvers.
B64: Equal Quarterly Instalments (EQI) used where schedule not itemised | C64: Bajaj: 28 EQI stated explicitly. RBL: 12 EQI stated explicitly. YBL: derived from 146-month tenor / quarterly freq ≈ 47 instalments. | E64: Repayment Schedule.
B65: Non-invoked NFB balances excluded from Total Debt | C65: Standard financial-covenant convention. Invocation must be manually toggled. | E65: Covenant Tracker: Total Debt link.
B66: Utilisation master toggle (Section A) overrides missing outstanding data | C66: Provides a 'fully utilised' stress view until actual outstandings are populated. | E66: Facility Master col L (Effective Outstanding).
B67: YBL TL amortisation: EQI vs graduated schedule | C67: Debt model uses 47 Equal Quarterly Instalments of ₹6.82 Cr each (face ₹320.70 Cr per sanction letter 16-Dec-2024). Mentor's standalone model uses a graduated/back-loaded schedule with face ₹306.59 Cr. The sanction letter language ('quarterly instalments') does not explicitly state 'equal'. Confirm with Paras Sir which schedule is binding before lender reporting. If graduated schedule is binding, update Repayment Schedule rows 71-125 to override the EQI default. | E67: Repayment Schedule - YBL TL section (rows 67-125).
B68: Promoter Shareholding | C68: 100% | D68: 05-Apr-2024 (CARE rationale) | E68: 74% JSL Overseas Limited (Ratan Jindal group) + 26% Jindal Stainless Limited (JSL divesting by Sep-2024 per Kallanish / SteelOrbis news, reallocating within Ratan Jindal group). Total promoter group ownership = 100%. Sources: CARE Ratings press release 5-Apr-2024; Kallanish/SteelOrbis news April 2024.
B69: F. Colour & Formatting Legend
B70: Hardcoded input (user to populate) | C70: Yellow fill, blue text
B71: Hardcoded value (fixed data) | C71: Blue text, no fill
B72: Formula / calculation | C72: Black text
B73: Cross-sheet link | C73: Green text
B74: External reference | C74: Red text
B75: Totals / sub-totals | C75: Light-blue fill, bold
B76: Headers | C76: Navy fill, white text, bold
B77: RBL TL rate populated as indicative 9.75% (1Y MCLR + 75 bps) | C77: Sanction letter defers rate to drawdown. Indicative rate used for projection: 1Y MCLR of 9.00% (Apr-2026) + conservative spread of 75 bps. Update Facility Master Q13 when RBL confirms actual rate. | E77: Sanction letter defers the applicable rate to the drawdown date. An indicative rate of 9.75% (1Y MCLR of 9.00% as at Apr-2026, plus a conservative spread of 75 bps) has been used for projection purposes. Update Facility Master Q13 when the confirmed rate is received from RBL.
B78: Working capital facilities assumed annually renewed | C78: 18 WC facilities show 'Expired' in Renewal Calendar because their original sanction-letter validity dates (mostly late 2025) have passed. These are annual-renewal facilities presumed renewed operationally. Confirm with ops team and update Facility Master Col AA with current validity dates. | E78: 18 working capital facilities show as 'Expired' in the Renewal & Review Calendar because the validity dates in the original sanction letters (predominantly late 2025) have passed. These are annual-renewal facilities and are assumed to have been renewed operationally. Confirm with the operations team and update Facility Master Column AA with current validity dates.
B79: FY24 balance sheet ₹56 Cr discrepancy acknowledged | C79: Mentor's Nov-2025 model Note tab documents a ₹56 Cr discrepancy in the FY24 balance sheet and negative cash balances FY24-26 due to capex + buyback. Inherited into this debt model's Section C FY24A values as-is. | E79: The source financial model documents a ₹56 Cr discrepancy in the FY24 balance sheet and negative cash balances for FY24–26 arising from capital expenditure and the share buyback programme. These FY24A figures have been carried into Section C of this model as-is. This discrepancy is not material for forward-looking covenant testing, which relies on FY26E projected figures.

Sheet Debt Pricing Table
B2: DEBT PRICING TABLE
B3: Comprehensive rate structure for all 34 facilities. Yellow cells = assumption inputs where rate is "To Be Decided".
B5: S.No | C5: Lender | D5: Facility | E5: Category | F5: Rate Type | G5: Benchmark Index | H5: Benchmark Rate | I5: Spread (bps) | J5: Effective Rate (p.a.) | K5: Reset Frequency | L5: Penal Interest | M5: Rate Source | N5: Status
B6: ='Facility Master'!B5 -> 1 | C6: ='Facility Master'!C5 -> RBL Bank | D6: ='Facility Master'!D5 -> Letter of Credit - Main Limit | E6: ='Facility Master'!E5 -> NFB | F6: ='Facility Master'!R5 -> Fixed | G6: ='Facility Master'!O5 -> Fixed commission | H6: =IFERROR(IF('Facility Master'!O5="1Y MCLR (RBL Bank)",BMK_1Y_MCLR_RBL,IF('Facility Master'!O5="3M MCLR (YBL)",BMK_3M_MCLR_YBL,IF('Facility Master'!O5="6M I-MCLR (ICICI)",BMK_6M_IMCLR_ICICI,IF('Facility Master'!O5="12M MCLR (SIB)",BMK_12M_MCLR_SIB,IF('Facility Master'!O5="Bajaj Floating Reference Rate (BFRR)",BMK_BFRR,IF('Facility Master'!O5="Term SOFR (USD)",BMK_TERM_SOFR,IF('Facility Master'!O5="Repo Rate",BMK_REPO,IF('Facility Master'!O5="FD rate",BMK_FD_RATE,IF('Facility Master'!O5="3M T-Bill",BMK_3M_TBILL,"-"))))))))),"-") -> - | I6: =IFERROR('Facility Master'!P5*10000,"-") -> - | J6: ='Facility Master'!Q5 -> 0.0045 | K6: =IF('Facility Master'!R5="Floating","Quarterly",IF('Facility Master'!R5="Fixed","N/A",IF('Facility Master'!R5="TBD","TBD","N/A"))) -> N/A | L6: N/A | M6: ='Facility Master'!AE5 -> Pricing revised from 0.50% to 0.45% on 31-Dec-2025. | Validity rolled +1 year (orig: 2025-11-30) per Assumption #12: annual-renewal WC facilities presumed operationally renewed. Confirm with relationship manager. | N6: =IF('Facility Master'!Q5=0,IF('Facility Master'!R5="TBD","⚠ Rate TBD","⚠ Rate Missing"),IF('Facility Master'!R5="Floating (Indicative)","⚠ Indicative","✓ Confirmed")) -> ✓ Confirmed
B7: ='Facility Master'!B6 -> 2 | C7: ='Facility Master'!C6 -> RBL Bank | D7: ='Facility Master'!D6 -> Bank Guarantee | E7: ='Facility Master'!E6 -> NFB | F7: ='Facility Master'!R6 -> Fixed | G7: ='Facility Master'!O6 -> Fixed commission | H7: =IFERROR(IF('Facility Master'!O6="1Y MCLR (RBL Bank)",BMK_1Y_MCLR_RBL,IF('Facility Master'!O6="3M MCLR (YBL)",BMK_3M_MCLR_YBL,IF('Facility Master'!O6="6M I-MCLR (ICICI)",BMK_6M_IMCLR_ICICI,IF('Facility Master'!O6="12M MCLR (SIB)",BMK_12M_MCLR_SIB,IF('Facility Master'!O6="Bajaj Floating Reference Rate (BFRR)",BMK_BFRR,IF('Facility Master'!O6="Term SOFR (USD)",BMK_TERM_SOFR,IF('Facility Master'!O6="Repo Rate",BMK_REPO,IF('Facility Master'!O6="FD rate",BMK_FD_RATE,IF('Facility Master'!O6="3M T-Bill",BMK_3M_TBILL,"-"))))))))),"-") -> - | I7: =IFERROR('Facility Master'!P6*10000,"-") -> - | J7: ='Facility Master'!Q6 -> 0.005 | K7: =IF('Facility Master'!R6="Floating","Quarterly",IF('Facility Master'!R6="Fixed","N/A",IF('Facility Master'!R6="TBD","TBD","N/A"))) -> N/A | L7: N/A | M7: ='Facility Master'!AE6 -> Pricing per 28-Feb-2025 table; BG not re-priced on 31-Dec-2025. | Validity rolled +1 year (orig: 2025-11-30) per Assumption #12: annual-renewal WC facilities presumed operationally renewed. Confirm with relationship manager. | ⚠ COMMISSION RATE TBD: Original RBL sanction (25-Nov-2022) specifies 1.00% p.a. for BGs. 31-Dec-2025 renewal does not explicitly revise BG rate downward. 0.50% is inferred from the 28-Feb-2025 pricing table but NOT confirmed in writing by RBL for the renewed sanction. Confirm 0.50% with RBL RM before finalising lender reporting / commission accrual. | N7: =IF('Facility Master'!Q6=0,IF('Facility Master'!R6="TBD","⚠ Rate TBD","⚠ Rate Missing"),IF('Facility Master'!R6="Floating (Indicative)","⚠ Indicative","✓ Confirmed")) -> ✓ Confirmed
B8: ='Facility Master'!B7 -> 3 | C8: ='Facility Master'!C7 -> RBL Bank | D8: ='Facility Master'!D7 -> Invoice Discounting (PID) | E8: ='Facility Master'!E7 -> FB | F8: ='Facility Master'!R7 -> TBD | G8: ='Facility Master'!O7 -> To be decided | H8: =IFERROR(IF('Facility Master'!O7="1Y MCLR (RBL Bank)",BMK_1Y_MCLR_RBL,IF('Facility Master'!O7="3M MCLR (YBL)",BMK_3M_MCLR_YBL,IF('Facility Master'!O7="6M I-MCLR (ICICI)",BMK_6M_IMCLR_ICICI,IF('Facility Master'!O7="12M MCLR (SIB)",BMK_12M_MCLR_SIB,IF('Facility Master'!O7="Bajaj Floating Reference Rate (BFRR)",BMK_BFRR,IF('Facility Master'!O7="Term SOFR (USD)",BMK_TERM_SOFR,IF('Facility Master'!O7="Repo Rate",BMK_REPO,IF('Facility Master'!O7="FD rate",BMK_FD_RATE,IF('Facility Master'!O7="3M T-Bill",BMK_3M_TBILL,"-"))))))))),"-") -> - | I8: =IFERROR('Facility Master'!P7*10000,"-") -> - | J8: ='Facility Master'!Q7 -> 0 | K8: =IF('Facility Master'!R7="Floating","Quarterly",IF('Facility Master'!R7="Fixed","N/A",IF('Facility Master'!R7="TBD","TBD","N/A"))) -> TBD | L8: N/A | M8: ='Facility Master'!AE7 -> Rate not specified in sanction letter. | Validity rolled +1 year (orig: 2025-11-30) per Assumption #12: annual-renewal WC facilities presumed operationally renewed. Confirm with relationship manager. | N8: =IF('Facility Master'!Q7=0,IF('Facility Master'!R7="TBD","⚠ Rate TBD","⚠ Rate Missing"),IF('Facility Master'!R7="Floating (Indicative)","⚠ Indicative","✓ Confirmed")) -> ⚠ Rate TBD
B9: ='Facility Master'!B8 -> 4 | C9: ='Facility Master'!C8 -> RBL Bank | D9: ='Facility Master'!D8 -> SBLC | E9: ='Facility Master'!E8 -> NFB | F9: ='Facility Master'!R8 -> TBD | G9: ='Facility Master'!O8 -> To be decided | H9: =IFERROR(IF('Facility Master'!O8="1Y MCLR (RBL Bank)",BMK_1Y_MCLR_RBL,IF('Facility Master'!O8="3M MCLR (YBL)",BMK_3M_MCLR_YBL,IF('Facility Master'!O8="6M I-MCLR (ICICI)",BMK_6M_IMCLR_ICICI,IF('Facility Master'!O8="12M MCLR (SIB)",BMK_12M_MCLR_SIB,IF('Facility Master'!O8="Bajaj Floating Reference Rate (BFRR)",BMK_BFRR,IF('Facility Master'!O8="Term SOFR (USD)",BMK_TERM_SOFR,IF('Facility Master'!O8="Repo Rate",BMK_REPO,IF('Facility Master'!O8="FD rate",BMK_FD_RATE,IF('Facility Master'!O8="3M T-Bill",BMK_3M_TBILL,"-"))))))))),"-") -> - | I9: =IFERROR('Facility Master'!P8*10000,"-") -> - | J9: ='Facility Master'!Q8 -> 0.005 | K9: =IF('Facility Master'!R8="Floating","Quarterly",IF('Facility Master'!R8="Fixed","N/A",IF('Facility Master'!R8="TBD","TBD","N/A"))) -> TBD | L9: N/A | M9: ='Facility Master'!AE8 -> SBLC sub-limit introduced via 13-Mar-2025 modification. | Validity rolled +1 year (orig: 2025-11-30) per Assumption #12: annual-renewal WC facilities presumed operationally renewed. Confirm with relationship manager. | Commission 0.50% per 28-Feb-2025 pricing, unchanged in 31-Dec-2025 renewal ('all other terms continue'). Earlier 13-Mar-2025 modification said 'TBD at transaction' for this sub-limit but was overridden by 31-Dec-2025 renewal. | N9: =IF('Facility Master'!Q8=0,IF('Facility Master'!R8="TBD","⚠ Rate TBD","⚠ Rate Missing"),IF('Facility Master'!R8="Floating (Indicative)","⚠ Indicative","✓ Confirmed")) -> ✓ Confirmed
B10: ='Facility Master'!B9 -> 5 | C10: ='Facility Master'!C9 -> RBL Bank | D10: ='Facility Master'!D9 -> Pre-Acceptance LCBD | E10: ='Facility Master'!E9 -> FB | F10: ='Facility Master'!R9 -> TBD | G10: ='Facility Master'!O9 -> To be decided | H10: =IFERROR(IF('Facility Master'!O9="1Y MCLR (RBL Bank)",BMK_1Y_MCLR_RBL,IF('Facility Master'!O9="3M MCLR (YBL)",BMK_3M_MCLR_YBL,IF('Facility Master'!O9="6M I-MCLR (ICICI)",BMK_6M_IMCLR_ICICI,IF('Facility Master'!O9="12M MCLR (SIB)",BMK_12M_MCLR_SIB,IF('Facility Master'!O9="Bajaj Floating Reference Rate (BFRR)",BMK_BFRR,IF('Facility Master'!O9="Term SOFR (USD)",BMK_TERM_SOFR,IF('Facility Master'!O9="Repo Rate",BMK_REPO,IF('Facility Master'!O9="FD rate",BMK_FD_RATE,IF('Facility Master'!O9="3M T-Bill",BMK_3M_TBILL,"-"))))))))),"-") -> - | I10: =IFERROR('Facility Master'!P9*10000,"-") -> - | J10: ='Facility Master'!Q9 -> 0 | K10: =IF('Facility Master'!R9="Floating","Quarterly",IF('Facility Master'!R9="Fixed","N/A",IF('Facility Master'!R9="TBD","TBD","N/A"))) -> TBD | L10: N/A | M10: ='Facility Master'!AE9 -> Rate not specified in sanction letter. | Validity rolled +1 year (orig: 2025-11-30) per Assumption #12: annual-renewal WC facilities presumed operationally renewed. Confirm with relationship manager. | N10: =IF('Facility Master'!Q9=0,IF('Facility Master'!R9="TBD","⚠ Rate TBD","⚠ Rate Missing"),IF('Facility Master'!R9="Floating (Indicative)","⚠ Indicative","✓ Confirmed")) -> ⚠ Rate TBD
B11: ='Facility Master'!B10 -> 6 | C11: ='Facility Master'!C10 -> RBL Bank | D11: ='Facility Master'!D10 -> Cash Credit | E11: ='Facility Master'!E10 -> FB | F11: ='Facility Master'!R10 -> Floating | G11: ='Facility Master'!O10 -> 1Y MCLR (RBL Bank) | H11: =IFERROR(IF('Facility Master'!O10="1Y MCLR (RBL Bank)",BMK_1Y_MCLR_RBL,IF('Facility Master'!O10="3M MCLR (YBL)",BMK_3M_MCLR_YBL,IF('Facility Master'!O10="6M I-MCLR (ICICI)",BMK_6M_IMCLR_ICICI,IF('Facility Master'!O10="12M MCLR (SIB)",BMK_12M_MCLR_SIB,IF('Facility Master'!O10="Bajaj Floating Reference Rate (BFRR)",BMK_BFRR,IF('Facility Master'!O10="Term SOFR (USD)",BMK_TERM_SOFR,IF('Facility Master'!O10="Repo Rate",BMK_REPO,IF('Facility Master'!O10="FD rate",BMK_FD_RATE,IF('Facility Master'!O10="3M T-Bill",BMK_3M_TBILL,"-"))))))))),"-") -> 0.09 | I11: =IFERROR('Facility Master'!P10*10000,"-") -> 5 | J11: ='Facility Master'!Q10 -> 0.0905 | K11: =IF('Facility Master'!R10="Floating","Quarterly",IF('Facility Master'!R10="Fixed","N/A",IF('Facility Master'!R10="TBD","TBD","N/A"))) -> Quarterly | L11: N/A | M11: ='Facility Master'!AE10 -> Pricing defined 28-Feb-2025; unchanged in 31-Dec-2025 letter. | Validity rolled +1 year (orig: 2025-11-30) per Assumption #12: annual-renewal WC facilities presumed operationally renewed. Confirm with relationship manager. | N11: =IF('Facility Master'!Q10=0,IF('Facility Master'!R10="TBD","⚠ Rate TBD","⚠ Rate Missing"),IF('Facility Master'!R10="Floating (Indicative)","⚠ Indicative","✓ Confirmed")) -> ✓ Confirmed
B12: ='Facility Master'!B11 -> 7 | C12: ='Facility Master'!C11 -> RBL Bank | D12: ='Facility Master'!D11 -> Working Capital Demand Loan (WCDL) | E12: ='Facility Master'!E11 -> FB | F12: ='Facility Master'!R11 -> TBD | G12: ='Facility Master'!O11 -> To be decided | H12: =IFERROR(IF('Facility Master'!O11="1Y MCLR (RBL Bank)",BMK_1Y_MCLR_RBL,IF('Facility Master'!O11="3M MCLR (YBL)",BMK_3M_MCLR_YBL,IF('Facility Master'!O11="6M I-MCLR (ICICI)",BMK_6M_IMCLR_ICICI,IF('Facility Master'!O11="12M MCLR (SIB)",BMK_12M_MCLR_SIB,IF('Facility Master'!O11="Bajaj Floating Reference Rate (BFRR)",BMK_BFRR,IF('Facility Master'!O11="Term SOFR (USD)",BMK_TERM_SOFR,IF('Facility Master'!O11="Repo Rate",BMK_REPO,IF('Facility Master'!O11="FD rate",BMK_FD_RATE,IF('Facility Master'!O11="3M T-Bill",BMK_3M_TBILL,"-"))))))))),"-") -> - | I12: =IFERROR('Facility Master'!P11*10000,"-") -> - | J12: ='Facility Master'!Q11 -> 0 | K12: =IF('Facility Master'!R11="Floating","Quarterly",IF('Facility Master'!R11="Fixed","N/A",IF('Facility Master'!R11="TBD","TBD","N/A"))) -> TBD | L12: N/A | M12: ='Facility Master'!AE11 -> Rate set at drawdown. | Validity rolled +1 year (orig: 2025-11-30) per Assumption #12: annual-renewal WC facilities presumed operationally renewed. Confirm with relationship manager. | N12: =IF('Facility Master'!Q11=0,IF('Facility Master'!R11="TBD","⚠ Rate TBD","⚠ Rate Missing"),IF('Facility Master'!R11="Floating (Indicative)","⚠ Indicative","✓ Confirmed")) -> ⚠ Rate TBD
B13: ='Facility Master'!B12 -> 8 | C13: ='Facility Master'!C12 -> RBL Bank | D13: ='Facility Master'!D12 -> Loan Equivalent Risk (LER) | E13: ='Facility Master'!E12 -> Hedge | F13: ='Facility Master'!R12 -> Fixed | G13: ='Facility Master'!O12 -> Bank treasury | H13: =IFERROR(IF('Facility Master'!O12="1Y MCLR (RBL Bank)",BMK_1Y_MCLR_RBL,IF('Facility Master'!O12="3M MCLR (YBL)",BMK_3M_MCLR_YBL,IF('Facility Master'!O12="6M I-MCLR (ICICI)",BMK_6M_IMCLR_ICICI,IF('Facility Master'!O12="12M MCLR (SIB)",BMK_12M_MCLR_SIB,IF('Facility Master'!O12="Bajaj Floating Reference Rate (BFRR)",BMK_BFRR,IF('Facility Master'!O12="Term SOFR (USD)",BMK_TERM_SOFR,IF('Facility Master'!O12="Repo Rate",BMK_REPO,IF('Facility Master'!O12="FD rate",BMK_FD_RATE,IF('Facility Master'!O12="3M T-Bill",BMK_3M_TBILL,"-"))))))))),"-") -> - | I13: =IFERROR('Facility Master'!P12*10000,"-") -> - | J13: ='Facility Master'!Q12 -> 0 | K13: =IF('Facility Master'!R12="Floating","Quarterly",IF('Facility Master'!R12="Fixed","N/A",IF('Facility Master'!R12="TBD","TBD","N/A"))) -> N/A | L13: N/A | M13: ='Facility Master'!AE12 -> Notional limit; 75% MTM trigger. | Validity rolled +1 year (orig: 2025-11-30) per Assumption #12: annual-renewal WC facilities presumed operationally renewed. Confirm with relationship manager. | N13: =IF('Facility Master'!Q12=0,IF('Facility Master'!R12="TBD","⚠ Rate TBD","⚠ Rate Missing"),IF('Facility Master'!R12="Floating (Indicative)","⚠ Indicative","✓ Confirmed")) -> ⚠ Rate Missing
B14: ='Facility Master'!B13 -> 9 | C14: ='Facility Master'!C13 -> RBL Bank | D14: ='Facility Master'!D13 -> Term Loan - Main Limit | E14: ='Facility Master'!E13 -> FB-Term | F14: ='Facility Master'!R13 -> Floating (Indicative) | G14: ='Facility Master'!O13 -> 1Y MCLR (RBL Bank) | H14: =IFERROR(IF('Facility Master'!O13="1Y MCLR (RBL Bank)",BMK_1Y_MCLR_RBL,IF('Facility Master'!O13="3M MCLR (YBL)",BMK_3M_MCLR_YBL,IF('Facility Master'!O13="6M I-MCLR (ICICI)",BMK_6M_IMCLR_ICICI,IF('Facility Master'!O13="12M MCLR (SIB)",BMK_12M_MCLR_SIB,IF('Facility Master'!O13="Bajaj Floating Reference Rate (BFRR)",BMK_BFRR,IF('Facility Master'!O13="Term SOFR (USD)",BMK_TERM_SOFR,IF('Facility Master'!O13="Repo Rate",BMK_REPO,IF('Facility Master'!O13="FD rate",BMK_FD_RATE,IF('Facility Master'!O13="3M T-Bill",BMK_3M_TBILL,"-"))))))))),"-") -> 0.09 | I14: =IFERROR('Facility Master'!P13*10000,"-") -> 75 | J14: ='Facility Master'!Q13 -> 0.0975 | K14: =IF('Facility Master'!R13="Floating","Quarterly",IF('Facility Master'!R13="Fixed","N/A",IF('Facility Master'!R13="TBD","TBD","N/A"))) -> N/A | L14: N/A | M14: ='Facility Master'!AE13 -> Debt-equity 40:60 for TL-funded capex. Rate TBD. | Validity rolled +1 year (orig: 2025-12-31) per Assumption #12: annual-renewal WC facilities presumed operationally renewed. Confirm with relationship manager. | N14: =IF('Facility Master'!Q13=0,IF('Facility Master'!R13="TBD","⚠ Rate TBD","⚠ Rate Missing"),IF('Facility Master'!R13="Floating (Indicative)","⚠ Indicative","✓ Confirmed")) -> ⚠ Indicative
B15: ='Facility Master'!B14 -> 10 | C15: ='Facility Master'!C14 -> RBL Bank | D15: ='Facility Master'!D14 -> SBLC for Buyer's Credit (GIFT City) | E15: ='Facility Master'!E14 -> NFB | F15: ='Facility Master'!R14 -> Fixed | G15: ='Facility Master'!O14 -> Fixed commission | H15: =IFERROR(IF('Facility Master'!O14="1Y MCLR (RBL Bank)",BMK_1Y_MCLR_RBL,IF('Facility Master'!O14="3M MCLR (YBL)",BMK_3M_MCLR_YBL,IF('Facility Master'!O14="6M I-MCLR (ICICI)",BMK_6M_IMCLR_ICICI,IF('Facility Master'!O14="12M MCLR (SIB)",BMK_12M_MCLR_SIB,IF('Facility Master'!O14="Bajaj Floating Reference Rate (BFRR)",BMK_BFRR,IF('Facility Master'!O14="Term SOFR (USD)",BMK_TERM_SOFR,IF('Facility Master'!O14="Repo Rate",BMK_REPO,IF('Facility Master'!O14="FD rate",BMK_FD_RATE,IF('Facility Master'!O14="3M T-Bill",BMK_3M_TBILL,"-"))))))))),"-") -> - | I15: =IFERROR('Facility Master'!P14*10000,"-") -> - | J15: ='Facility Master'!Q14 -> 0.005 | K15: =IF('Facility Master'!R14="Floating","Quarterly",IF('Facility Master'!R14="Fixed","N/A",IF('Facility Master'!R14="TBD","TBD","N/A"))) -> N/A | L15: N/A | M15: ='Facility Master'!AE14 -> Limit increased 172 -> 190 Cr on 31-Dec-2025. | Validity rolled +1 year (orig: 2025-11-30) per Assumption #12: annual-renewal WC facilities presumed operationally renewed. Confirm with relationship manager. | N15: =IF('Facility Master'!Q14=0,IF('Facility Master'!R14="TBD","⚠ Rate TBD","⚠ Rate Missing"),IF('Facility Master'!R14="Floating (Indicative)","⚠ Indicative","✓ Confirmed")) -> ✓ Confirmed
B16: ='Facility Master'!B15 -> 11 | C16: ='Facility Master'!C15 -> RBL Bank | D16: ='Facility Master'!D15 -> Capex LC | E16: ='Facility Master'!E15 -> NFB | F16: ='Facility Master'!R15 -> Fixed | G16: ='Facility Master'!O15 -> Fixed commission | H16: =IFERROR(IF('Facility Master'!O15="1Y MCLR (RBL Bank)",BMK_1Y_MCLR_RBL,IF('Facility Master'!O15="3M MCLR (YBL)",BMK_3M_MCLR_YBL,IF('Facility Master'!O15="6M I-MCLR (ICICI)",BMK_6M_IMCLR_ICICI,IF('Facility Master'!O15="12M MCLR (SIB)",BMK_12M_MCLR_SIB,IF('Facility Master'!O15="Bajaj Floating Reference Rate (BFRR)",BMK_BFRR,IF('Facility Master'!O15="Term SOFR (USD)",BMK_TERM_SOFR,IF('Facility Master'!O15="Repo Rate",BMK_REPO,IF('Facility Master'!O15="FD rate",BMK_FD_RATE,IF('Facility Master'!O15="3M T-Bill",BMK_3M_TBILL,"-"))))))))),"-") -> - | I16: =IFERROR('Facility Master'!P15*10000,"-") -> - | J16: ='Facility Master'!Q15 -> 0.005 | K16: =IF('Facility Master'!R15="Floating","Quarterly",IF('Facility Master'!R15="Fixed","N/A",IF('Facility Master'!R15="TBD","TBD","N/A"))) -> N/A | L16: N/A | M16: ='Facility Master'!AE15 -> Originally 24-Jan-2024; converted revolving 28-Feb-2025. | Validity rolled +1 year (orig: 2025-11-30) per Assumption #12: annual-renewal WC facilities presumed operationally renewed. Confirm with relationship manager. | Commission TBD at disbursement per sanction letter. FD-backed LC typically carries nil-to-very-low commission (lender's own-FD collateral). Model shows 0. | N16: =IF('Facility Master'!Q15=0,IF('Facility Master'!R15="TBD","⚠ Rate TBD","⚠ Rate Missing"),IF('Facility Master'!R15="Floating (Indicative)","⚠ Indicative","✓ Confirmed")) -> ✓ Confirmed
B17: ='Facility Master'!B16 -> 12 | C17: ='Facility Master'!C16 -> RBL Bank | D17: ='Facility Master'!D16 -> Overdraft backed by 100% FD (FDOD) | E17: ='Facility Master'!E16 -> FB-FDbacked | F17: ='Facility Master'!R16 -> Floating | G17: ='Facility Master'!O16 -> FD rate | H17: =IFERROR(IF('Facility Master'!O16="1Y MCLR (RBL Bank)",BMK_1Y_MCLR_RBL,IF('Facility Master'!O16="3M MCLR (YBL)",BMK_3M_MCLR_YBL,IF('Facility Master'!O16="6M I-MCLR (ICICI)",BMK_6M_IMCLR_ICICI,IF('Facility Master'!O16="12M MCLR (SIB)",BMK_12M_MCLR_SIB,IF('Facility Master'!O16="Bajaj Floating Reference Rate (BFRR)",BMK_BFRR,IF('Facility Master'!O16="Term SOFR (USD)",BMK_TERM_SOFR,IF('Facility Master'!O16="Repo Rate",BMK_REPO,IF('Facility Master'!O16="FD rate",BMK_FD_RATE,IF('Facility Master'!O16="3M T-Bill",BMK_3M_TBILL,"-"))))))))),"-") -> 0 | I17: =IFERROR('Facility Master'!P16*10000,"-") -> 25 | J17: ='Facility Master'!Q16 -> 0 | K17: =IF('Facility Master'!R16="Floating","Quarterly",IF('Facility Master'!R16="Fixed","N/A",IF('Facility Master'!R16="TBD","TBD","N/A"))) -> Quarterly | L17: N/A | M17: ='Facility Master'!AE16 -> Excluded from INR 300 Cr overall cap. | Validity rolled +1 year (orig: 2025-11-30) per Assumption #12: annual-renewal WC facilities presumed operationally renewed. Confirm with relationship manager. | N17: =IF('Facility Master'!Q16=0,IF('Facility Master'!R16="TBD","⚠ Rate TBD","⚠ Rate Missing"),IF('Facility Master'!R16="Floating (Indicative)","⚠ Indicative","✓ Confirmed")) -> ⚠ Rate Missing
... B39: ='Facility Master'!B38 -> 34 | C39: ='Facility Master'!C38 -> South Indian Bank | D39: ='Facility Master'!D38 -> Forward Contract Limit | E39: ='Facility Master'!E38 -> Hedge | F39: ='Facility Master'!R38 -> Fixed | G39: ='Facility Master'!O38 -> N/A | H39: =IFERROR(IF('Facility Master'!O38="1Y MCLR (RBL Bank)",BMK_1Y_MCLR_RBL,IF('Facility Master'!O38="3M MCLR (YBL)",BMK_3M_MCLR_YBL,IF('Facility Master'!O38="6M I-MCLR (ICICI)",BMK_6M_IMCLR_ICICI,IF('Facility Master'!O38="12M MCLR (SIB)",BMK_12M_MCLR_SIB,IF('Facility Master'!O38="Bajaj Floating Reference Rate (BFRR)",BMK_BFRR,IF('Facility Master'!O38="Term SOFR (USD)",BMK_TERM_SOFR,IF('Facility Master'!O38="Repo Rate",BMK_REPO,IF('Facility Master'!O38="FD rate",BMK_FD_RATE,IF('Facility Master'!O38="3M T-Bill",BMK_3M_TBILL,"-"))))))))),"-") -> - | I39: =IFERROR('Facility Master'!P38*10000,"-") -> - | J39: ='Facility Master'!Q38 -> 0 | K39: =IF('Facility Master'!R38="Floating","Quarterly",IF('Facility Master'!R38="Fixed","N/A",IF('Facility Master'!R38="TBD","TBD","N/A"))) -> N/A | L39: N/A | M39: ='Facility Master'!AE38 -> Notional limit; no cash outflow unless settled. | N39: =IF('Facility Master'!Q38=0,IF('Facility Master'!R38="TBD","⚠ Rate TBD","⚠ Rate Missing"),IF('Facility Master'!R38="Floating (Indicative)","⚠ Indicative","✓ Confirmed")) -> ⚠ Rate Missing
B41: PRICING SUMMARY
B42: Facilities with confirmed rates | D42: =COUNTIF(N6:N39,"✓ Confirmed") -> 20
B43: Facilities with TBD rates | D43: =COUNTIF(N6:N39,"⚠ Rate TBD") -> 7
B44: Facilities with indicative rates | D44: =COUNTIF(N6:N39,"⚠ Indicative") -> 1
B45: Facilities with missing rates | D45: =COUNTIF(N6:N39,"⚠ Rate Missing") -> 6

Sheet Facility Master
B2: FACILITY MASTER (single source of truth)
B4: S.No | C4: Lender | D4: Facility | E4: Category | F4: Nature | G4: Sub-limit Parent | H4: Currency | I4: Sanc. Amt (Orig. Ccy) | J4: Sanc. Amt (INR Cr) | K4: Current Outstanding (INR Cr) | L4: Effective Outstanding (INR Cr) | M4: Utilisation % | N4: Available Headroom (INR Cr) | O4: Interest Benchmark | P4: Spread | Q4: Effective Rate (p.a.) | R4: Rate Type | S4: Moratorium (Months) | T4: Repayment Frequency | U4: Tenor (Months) | V4: No. of Instalments | W4: Drawdown Date | X4: Repayment Start | Y4: Maturity Date | Z4: Sanction Date | AA4: Validity Date | AB4: Facility Purpose | AC4: Security (summary) | AD4: Sanction Reference | AE4: Remarks
B5: 1 | C5: RBL Bank | D5: Letter of Credit - Main Limit | E5: NFB | F5: Revolving | G5: Main | H5: INR | I5: 100 | J5: =I5 -> 100 | L5: =IF(UseFullUtilisation=TRUE(),J5,IF(K5="",0,K5)) -> 100 | M5: =IFERROR(L5/J5,0) -> 1 | N5: =J5-L5 -> 0 | O5: Fixed commission | P5: - | Q5: 0.0045 | R5: Fixed | S5: - | T5: On Maturity | U5: 6 | V5: - | W5: =Z5 -> 46022 | X5: - | Y5: - | Z5: 46022 | AA5: 46356 | AB5: Working capital incl. service LC issuance | AC5: 1st p-p on current assets; 2nd p-p on FA; Personal guarantee | AD5: RBL Renewal Letter dated 31-Dec-2025 | AE5: Pricing revised from 0.50% to 0.45% on 31-Dec-2025. | Validity rolled +1 year (orig: 2025-11-30) per Assumption #12: annual-renewal WC facilities presumed operationally renewed. Confirm with relationship manager.
B6: 2 | C6: RBL Bank | D6: Bank Guarantee | E6: NFB | F6: Revolving | G6: Sub-limit of LC (Main) | H6: INR | I6: 25 | J6: =I6 -> 25 | L6: =IF(UseFullUtilisation=TRUE(),J6,IF(K6="",0,K6)) -> 25 | M6: =IFERROR(L6/J6,0) -> 1 | N6: =J6-L6 -> 0 | O6: Fixed commission | P6: - | Q6: 0.005 | R6: Fixed | S6: - | T6: On Demand | U6: 12 | V6: - | W6: =Z6 -> 46022 | X6: - | Y6: - | Z6: 46022 | AA6: 46356 | AB6: PBG, Bid Bond, Govt/Semi-Govt guarantees | AC6: 1st p-p on current assets; 2nd p-p on FA; Personal guarantee | AD6: RBL Renewal Letter dated 31-Dec-2025 | AE6: Pricing per 28-Feb-2025 table; BG not re-priced on 31-Dec-2025. | Validity rolled +1 year (orig: 2025-11-30) per Assumption #12: annual-renewal WC facilities presumed operationally renewed. Confirm with relationship manager. | ⚠ COMMISSION RATE TBD: Original RBL sanction (25-Nov-2022) specifies 1.00% p.a. for BGs. 31-Dec-2025 renewal does not explicitly revise BG rate downward. 0.50% is inferred from the 28-Feb-2025 pricing table but NOT confirmed in writing by RBL for the renewed sanction. Confirm 0.50% with RBL RM before finalising lender reporting / commission accrual.
B7: 3 | C7: RBL Bank | D7: Invoice Discounting (PID) | E7: FB | F7: Revolving | G7: Standalone (under WC) | H7: INR | I7: 100 | J7: =I7 -> 100 | L7: =IF(UseFullUtilisation=TRUE(),J7,IF(K7="",0,K7)) -> 100 | M7: =IFERROR(L7/J7,0) -> 1 | N7: =J7-L7 -> 0 | O7: To be decided | P7: - | R7: TBD | S7: - | T7: On Maturity | U7: 1 | V7: - | W7: =Z7 -> 46022 | X7: - | Y7: - | Z7: 46022 | AA7: 46356 | AB7: Working capital requirement | AC7: 1st p-p on current assets; 2nd p-p on FA; Personal guarantee | AD7: RBL Renewal Letter dated 31-Dec-2025 | AE7: Rate not specified in sanction letter. | Validity rolled +1 year (orig: 2025-11-30) per Assumption #12: annual-renewal WC facilities presumed operationally renewed. Confirm with relationship manager.
B8: 4 | C8: RBL Bank | D8: SBLC | E8: NFB | F8: Revolving | G8: Sub-limit of LC (Main) | H8: INR | I8: 100 | J8: =I8 -> 100 | L8: =IF(UseFullUtilisation=TRUE(),J8,IF(K8="",0,K8)) -> 100 | M8: =IFERROR(L8/J8,0) -> 1 | N8: =J8-L8 -> 0 | O8: To be decided | P8: - | Q8: 0.005 | R8: TBD | S8: - | T8: On Maturity | U8: 6 | V8: - | W8: =Z8 -> 45729 | X8: - | Y8: - | Z8: 45729 | AA8: 46356 | AB8: Buyer's Credit from RBL GIFT City / other banks | AC8: Same as LC | AD8: RBL Modification Letter dated 13-Mar-2025 | AE8: SBLC sub-limit introduced via 13-Mar-2025 modification. | Validity rolled +1 year (orig: 2025-11-30) per Assumption #12: annual-renewal WC facilities presumed operationally renewed. Confirm with relationship manager. | Commission 0.50% per 28-Feb-2025 pricing, unchanged in 31-Dec-2025 renewal ('all other terms continue'). Earlier 13-Mar-2025 modification said 'TBD at transaction' for this sub-limit but was overridden by 31-Dec-2025 renewal.
B9: 5 | C9: RBL Bank | D9: Pre-Acceptance LCBD | E9: FB | F9: Revolving | G9: Standalone (under WC) | H9: INR | I9: 100 | J9: =I9 -> 100 | L9: =IF(UseFullUtilisation=TRUE(),J9,IF(K9="",0,K9)) -> 100 | M9: =IFERROR(L9/J9,0) -> 1 | N9: =J9-L9 -> 0 | O9: To be decided | P9: - | R9: TBD | S9: - | T9: On Maturity | U9: - | V9: - | W9: =Z9 -> 46022 | X9: - | Y9: - | Z9: 46022 | AA9: 46356 | AB9: Working capital requirement | AC9: 1st p-p on current assets; 2nd p-p on FA; Personal guarantee | AD9: RBL Renewal Letter dated 31-Dec-2025 | AE9: Rate not specified in sanction letter. | Validity rolled +1 year (orig: 2025-11-30) per Assumption #12: annual-renewal WC facilities presumed operationally renewed. Confirm with relationship manager.
B10: 6 | C10: RBL Bank | D10: Cash Credit | E10: FB | F10: Revolving | G10: Standalone (under WC) | H10: INR | I10: 100 | J10: =I10 -> 100 | L10: =IF(UseFullUtilisation=TRUE(),J10,IF(K10="",0,K10)) -> 100 | M10: =IFERROR(L10/J10,0) -> 1 | N10: =J10-L10 -> 0 | O10: 1Y MCLR (RBL Bank) | P10: 0.0005 | Q10: =BMK_1Y_MCLR_RBL+P10 -> 0.0905 | R10: Floating | S10: - | T10: On Demand | U10: - | V10: - | W10: =Z10 -> 45716 | X10: - | Y10: - | Z10: 45716 | AA10: 46356 | AB10: Working capital requirement | AC10: 1st p-p on current assets; 2nd p-p on FA; Personal guarantee | AD10: RBL Renewal cum Modification dated 28-Feb-2025 | AE10: Pricing defined 28-Feb-2025; unchanged in 31-Dec-2025 letter. | Validity rolled +1 year (orig: 2025-11-30) per Assumption #12: annual-renewal WC facilities presumed operationally renewed. Confirm with relationship manager.
B11: 7 | C11: RBL Bank | D11: Working Capital Demand Loan (WCDL) | E11: FB | F11: Revolving | G11: Sub-limit of LC (Main) | H11: INR | I11: 100 | J11: =I11 -> 100 | L11: =IF(UseFullUtilisation=TRUE(),J11,IF(K11="",0,K11)) -> 100 | M11: =IFERROR(L11/J11,0) -> 1 | N11: =J11-L11 -> 0 | O11: To be decided | P11: - | R11: TBD | S11: - | T11: On Demand | U11: 4 | V11: - | W11: =Z11 -> 46022 | X11: - | Y11: - | Z11: 46022 | AA11: 46356 | AB11: Working capital | AC11: 1st p-p on current assets; 2nd p-p on FA; Personal guarantee | AD11: RBL Renewal Letter dated 31-Dec-2025 | AE11: Rate set at drawdown. | Validity rolled +1 year (orig: 2025-11-30) per Assumption #12: annual-renewal WC facilities presumed operationally renewed. Confirm with relationship manager.
B12: 8 | C12: RBL Bank | D12: Loan Equivalent Risk (LER) | E12: Hedge | F12: Revolving | G12: Main | H12: INR | I12: 20 | J12: =I12 -> 20 | L12: =IF(UseFullUtilisation=TRUE(),J12,IF(K12="",0,K12)) -> 20 | M12: =IFERROR(L12/J12,0) -> 1 | N12: =J12-L12 -> 0 | O12: Bank treasury | P12: - | R12: Fixed | S12: - | T12: On Settlement | U12: 12 | V12: - | W12: =Z12 -> 46022 | X12: - | Y12: - | Z12: 46022 | AA12: 46356 | AB12: Forex hedging (MTM cap 75%) | AC12: Unsecured | AD12: RBL Renewal Letter dated 31-Dec-2025 | AE12: Notional limit; 75% MTM trigger. | Validity rolled +1 year (orig: 2025-11-30) per Assumption #12: annual-renewal WC facilities presumed operationally renewed. Confirm with relationship manager.
B13: 9 | C13: RBL Bank | D13: Term Loan - Main Limit | E13: FB-Term | F13: Non-Revolving | G13: Main | H13: INR | I13: 200 | J13: =I13 -> 200 | L13: =IF(UseFullUtilisation=TRUE(),J13,IF(K13="",0,K13)) -> 200 | M13: =IFERROR(L13/J13,0) -> 1 | N13: =J13-L13 -> 0 | O13: 1Y MCLR (RBL Bank) | P13: 0.0075 | Q13: =BMK_1Y_MCLR_RBL+P13 -> 0.0975 | R13: Floating (Indicative) | S13: 24 | T13: Quarterly | U13: 60 | V13: 12 | W13: 45315 | X13: =IFERROR(EDATE(IF(W13="",Z13,W13),S13),"-") -> 46046 | Y13: =IFERROR(EDATE(IF(W13="",Z13,W13),U13),"-") -> 47142 | Z13: 45315 | AA13: 46387 | AB13: Repayment of existing SBLC/BC + fresh capex | AC13: 1st p-p on FA; 1st p-p mortgage on immovable; 2nd p-p on CA | AD13: Rate indicative: 1Y MCLR + 75 bps = 9.75% (MCLR Apr-2026). Sanction letter defers actual rate to drawdown; update with RBL-confirmed rate when available. | AE13: Debt-equity 40:60 for TL-funded capex. Rate TBD. | Validity rolled +1 year (orig: 2025-12-31) per Assumption #12: annual-renewal WC facilities presumed operationally renewed. Confirm with relationship manager.
B14: 10 | C14: RBL Bank | D14: SBLC for Buyer's Credit (GIFT City) | E14: NFB | F14: Revolving (converted 28-Feb-2025) | G14: Main | H14: INR | I14: 190 | J14: =I14 -> 190 | L14: =IF(UseFullUtilisation=TRUE(),J14,IF(K14="",0,K14)) -> 190 | M14: =IFERROR(L14/J14,0) -> 1 | N14: =J14-L14 -> 0 | O14: Fixed commission | P14: - | Q14: 0.005 | R14: Fixed | S14: - | T14: On Maturity | U14: 36 | V14: - | W14: =Z14 -> 46022 | X14: - | Y14: - | Z14: 46022 | AA14: 46356 | AB14: Buyer's credit through RBL GIFT City or other banks | AC14: 1st p-p on FA; 1st p-p mortgage on immovable; 2nd p-p on CA | AD14: RBL Renewal Letter dated 31-Dec-2025 | AE14: Limit increased 172 -> 190 Cr on 31-Dec-2025. | Validity rolled +1 year (orig: 2025-11-30) per Assumption #12: annual-renewal WC facilities presumed operationally renewed. Confirm with relationship manager.
B15: 11 | C15: RBL Bank | D15: Capex LC | E15: NFB | F15: Revolving (converted 28-Feb-2025) | G15: Main | H15: INR | I15: 25 | J15: =I15 -> 25 | L15: =IF(UseFullUtilisation=TRUE(),J15,IF(K15="",0,K15)) -> 25 | M15: =IFERROR(L15/J15,0) -> 1 | N15: =J15-L15 -> 0 | O15: Fixed commission | P15: - | Q15: 0.005 | R15: Fixed | S15: - | T15: On Maturity | U15: 36 | V15: - | W15: =Z15 -> 46022 | X15: - | Y15: - | Z15: 46022 | AA15: 46356 | AB15: Purchase of capital goods | AC15: 1st p-p on FA; 1st p-p mortgage on immovable; 2nd p-p on CA | AD15: RBL Renewal Letter dated 31-Dec-2025 | AE15: Originally 24-Jan-2024; converted revolving 28-Feb-2025. | Validity rolled +1 year (orig: 2025-11-30) per Assumption #12: annual-renewal WC facilities presumed operationally renewed. Confirm with relationship manager. | Commission TBD at disbursement per sanction letter. FD-backed LC typically carries nil-to-very-low commission (lender's own-FD collateral). Model shows 0.
B16: 12 | C16: RBL Bank | D16: Overdraft backed by 100% FD (FDOD) | E16: FB-FDbacked | F16: Revolving | G16: Main | H16: INR | I16: 100 | J16: =I16 -> 100 | L16: =IF(UseFullUtilisation=TRUE(),J16,IF(K16="",0,K16)) -> 100 | M16: =IFERROR(L16/J16,0) -> 1 | N16: =J16-L16 -> 0 | O16: FD rate | P16: 0.0025 | R16: Floating | S16: - | T16: On Demand | U16: 12 | V16: - | W16: =Z16 -> 45315 | X16: - | Y16: - | Z16: 45315 | AA16: 46356 | AB16: Cash flow mismatches | AC16: Exclusive charge on FD = 100% of facility | AD16: RBL Renewal cum Enhancement dated 24-Jan-2024 | AE16: Excluded from INR 300 Cr overall cap. | Validity rolled +1 year (orig: 2025-11-30) per Assumption #12: annual-renewal WC facilities presumed operationally renewed. Confirm with relationship manager.
B17: 13 | C17: RBL Bank | D17: LC backed by 100% FD | E17: NFB-FDbacked | F17: Revolving | G17: Sub-limit of FDOD | H17: INR | I17: 50 | J17: =I17 -> 50 | L17: =IF(UseFullUtilisation=TRUE(),J17,IF(K17="",0,K17)) -> 50 | M17: =IFERROR(L17/J17,0) -> 1 | N17: =J17-L17 -> 0 | O17: To be decided | P17: - | R17: TBD | S17: - | T17: On Maturity | U17: 12 | V17: - | W17: =Z17 -> 45315 | X17: - | Y17: - | Z17: 45315 | AA17: 46356 | AB17: WC - import/purchase of raw materials, stores & spares | AC17: Exclusive charge on FD = 100% of facility | AD17: RBL Renewal cum Enhancement dated 24-Jan-2024 | AE17: Rate not specified in sanction letter. | Validity rolled +1 year (orig: 2025-11-30) per Assumption #12: annual-renewal WC facilities presumed operationally renewed. Confirm with relationship manager.
B18: 14 | C18: RBL Bank | D18: Buyer's Credit from GIFT City - WC | E18: FB-FCY | F18: Revolving | G18: Backed by BG/SBLC from RBL | H18: USD | I18: 11 | J18: =MIN(I18*FX_USD_INR/10,100) -> 100 | L18: =IF(UseFullUtilisation=TRUE(),J18,IF(K18="",0,K18)) -> 100 | M18: =IFERROR(L18/J18,0) -> 1 | N18: =J18-L18 -> 0 | O18: Term SOFR (USD) | P18: - | R18: Floating | S18: - | T18: Bullet | U18: 6 | V18: 1 | W18: =Z18 -> 45729 | X18: - | Y18: - | Z18: 45729 | AA18: 46356 | AB18: Working capital requirements | AC18: RBL-issued BG/SBLC | AD18: RBL Buyer's Credit WC Sanction dated 13-Mar-2025 | AE18: Total RBL exposure (incl. LER) capped at INR 100 Cr. | Sanctioned INR capped at ₹100 Cr per sanction letter (binding limit). USD sanctioned limit is USD 11M, but total RBL exposure ring-fenced at ₹100 Cr regardless of FX. Formula: =MIN(USD×FX/10, 100). | Validity rolled +1 year (orig: 2025-11-30) per Assumption #12: annual-renewal WC facilities presumed operationally renewed. Confirm with relationship manager. | LC commission unspecified in sanction letter ('applicable commission plus taxes'). Model shows 0 pending confirmation from RM. Typical market rate for sub-180-day inland LC is 0.40%-0.60% p.a. Update Facility Master Q18 when confirmed.
B19: 15 | C19: RBL Bank | D19: Buyer's Credit from GIFT City - CAPEX | E19: FB-FCY | F19: Revolving | G19: Backed by BG/SBLC from RBL | H19: USD | I19: 20 | J19: =MIN(I19*FX_USD_INR/10,172) -> 172 | L19: =IF(UseFullUtilisation=TRUE(),J19,IF(K19="",0,K19)) -> 172 | M19: =IFERROR(L19/J19,0) -> 1 | N19: =J19-L19 -> 0 | O19: Term SOFR (USD) | P19: - | R19: Floating | S19: - | T19: Bullet | U19: 36 | V19: 1 | W19: =Z19 -> 45743 | X19: - | Y19: - | Z19: 45743 | AA19: 46356 | AB19: CAPEX funding | AC19: RBL-issued BG/SBLC | AD19: RBL Buyer's Credit CAPEX Sanction dated 27-Mar-2025 | AE19: Total RBL exposure capped at INR 172 Cr (implied FX ~86). | Sanctioned INR capped at ₹172 Cr per sanction letter (binding limit). USD sanctioned limit is USD 20M, but total RBL exposure ring-fenced at ₹172 Cr regardless of FX. Formula: =MIN(USD×FX/10, 172). | Validity rolled +1 year (orig: 2025-11-30) per Assumption #12: annual-renewal WC facilities presumed operationally renewed. Confirm with relationship manager.
B20: 16 | C20: YES Bank | D20: Purchase Invoice Financing | E20: FB | F20: Revolving | G20: Main (New) | H20: INR | I20: 100 | J20: =I20 -> 100 | L20: =IF(UseFullUtilisation=TRUE(),J20,IF(K20="",0,K20)) -> 100 | M20: =IFERROR(L20/J20,0) -> 1 | N20: =J20-L20 -> 0 | O20: To be decided | P20: - | R20: TBD | S20: - | T20: On Maturity | U20: 3 | V20: - | W20: =Z20 -> 46100 | X20: - | Y20: - | Z20: 46100 | AA20: 46142 | AB20: Working capital requirements | AC20: 1st p-p hypothecation over current assets | AD20: YBL Renewal cum Addendum dated 19-Mar-2026 | AE20: New facility; Interest payable upfront.
B21: 17 | C21: YES Bank | D21: Cash Credit | E21: FB | F21: Revolving | G21: Main (re-sized 19-Mar-2026) | H21: INR | I21: 25 | J21: =I21 -> 25 | L21: =IF(UseFullUtilisation=TRUE(),J21,IF(K21="",0,K21)) -> 25 | M21: =IFERROR(L21/J21,0) -> 1 | N21: =J21-L21 -> 0 | O21: 3M MCLR (YBL) | P21: 0.0007 | Q21: =BMK_3M_MCLR_YBL+P21 -> 0.0907 | R21: Floating | S21: - | T21: On Demand | U21: 12 | V21: - | W21: =Z21 -> 46100 | X21: - | Y21: - | Z21: 46100 | AA21: Assumed annual review | AB21: Working capital | AC21: 1st p-p on CA; mortgage on Faridabad property; 2nd p-p on FA; PG | AD21: YBL Renewal cum Addendum dated 19-Mar-2026 | AE21: Pricing moved T-Bill+1.98% -> 3M MCLR+0.07% on 19-Mar-2026.
B22: 18 | C22: YES Bank | D22: Letter of Credit | E22: NFB | F22: Revolving | G22: Main | H22: INR | I22: 200 | J22: =I22 -> 200 | L22: =IF(UseFullUtilisation=TRUE(),J22,IF(K22="",0,K22)) -> 200 | M22: =IFERROR(L22/J22,0) -> 1 | N22: =J22-L22 -> 0 | O22: Fixed commission | P22: - | R22: Fixed | S22: - | T22: On Maturity | U22: 7 | V22: - | W22: =Z22 -> 46100 | X22: - | Y22: - | Z22: 46100 | AA22: 46472 | AB22: Procurement of raw materials | AC22: 1st p-p on CA; mortgage on Faridabad property; 2nd p-p on FA; PG | AD22: YBL Renewal cum Addendum dated 19-Mar-2026 | AE22: Overall WC cap INR 200 Cr net of receivable finance (INR 1 Cr). | Validity rolled +1 year (orig: 2026-03-26) per Assumption #12: annual-renewal WC facilities presumed operationally renewed. Confirm with relationship manager.
B23: 19 | C23: YES Bank | D23: Financial BG / SBLC | E23: NFB | F23: Revolving | G23: Sub-limit of LC (Main) | H23: INR | I23: 200 | J23: =I23 -> 200 | L23: =IF(UseFullUtilisation=TRUE(),J23,IF(K23="",0,K23)) -> 200 | M23: =IFERROR(L23/J23,0) -> 1 | N23: =J23-L23 -> 0 | O23: Fixed commission | P23: - | Q23: 0.005 | R23: Fixed | S23: - | T23: On Maturity | U23: 6 | V23: - | W23: =Z23 -> 46100 | X23: - | Y23: - | Z23: 46100 | AA23: Per renewal cycle | AB23: Securing payment for raw materials / paper | AC23: 1st p-p on CA; mortgage on Faridabad property; 2nd p-p on FA; PG | AD23: YBL Renewal cum Addendum dated 19-Mar-2026 | AE23: Commission cut 25 bps on 19-Mar-2026.
B24: 20 | C24: YES Bank | D24: Working Capital Demand Loan (WCDL) | E24: FB | F24: Revolving | G24: Sub-limit of LC (Main) | H24: INR | I24: 50 | J24: =I24 -> 50 | L24: =IF(UseFullUtilisation=TRUE(),J24,IF(K24="",0,K24)) -> 50 | M24: =IFERROR(L24/J24,0) -> 1 | N24: =J24-L24 -> 0 | O24: To be decided | P24: - | R24: TBD | S24: - | T24: On Demand | U24: 6 | V24: - | W24: =Z24 -> 46100 | X24: - | Y24: - | Z24: 46100 | AA24: Per renewal cycle | AB24: Working capital | AC24: 1st p-p on CA; mortgage on Faridabad property; 2nd p-p on FA; PG | AD24: YBL Renewal cum Addendum dated 19-Mar-2026 | AE24: Min utilisation covenant: 40% of YBL limits.
B25: 21 | C25: YES Bank | D25: Term Loan (Refinance Canara) | E25: FB-Term | F25: Non-Revolving | G25: Main | H25: INR | I25: 320.7 | J25: =I25 -> 320.7 | L25: =IF(UseFullUtilisation=TRUE(),J25,IF(K25="",0,K25)) -> 320.7 | M25: =IFERROR(L25/J25,0) -> 1 | N25: =J25-L25 -> 0 | O25: 3M T-Bill | P25: 0.0252 | Q25: =BMK_3M_TBILL+P25 -> 0.077 | R25: Floating | S25: 0 | T25: Quarterly | U25: 146 | V25: 47 | W25: 45642 | X25: 45747 | Y25: 49948 | Z25: 45744 | AA25: 46253 | AB25: Refinance Canara TL + reimburse promoter loan + IA | AC25: 2nd p-p on CA; 1st p-p on FA; 1st p-p EM Kalinga Nagar | AD25: YBL TL Addendum dated 28-Mar-2025 | AE25: Spread 2.45% -> 2.52% on 28-Mar-2025. FF 0.45% of TL. | Maturity hardcoded to 30-Sep-2036 per sanction letter final-repayment clause (overrides EDATE(drawdown, 146m) calc which gives 16-Feb-2037). 47 quarterly instalments over 141 months from drawdown 16-Dec-2024 end on 30-Sep-2036. | Validity rolled +1 year (orig: 2025-08-19) per Assumption #12: annual-renewal WC facilities presumed operationally renewed. Confirm with relationship manager. | RepStart hardcoded to 31-Mar-2025 (first quarterly instalment per sanction-letter dates: 30-Jun/30-Sep/31-Dec/31-Mar). 47 quarterly instalments from 31-Mar-2025 end on 30-Sep-2036. | ⚠ ASSUMPTION: Modelled as 47 EQI of ₹6.82 Cr. Sanction letter (16-Dec-2024) specifies 'quarterly instalments' without explicitly stating 'equal'. Mentor's standalone model uses graduated/back-loaded schedule with face ₹306.59 Cr. Confirm with Paras Sir which schedule binding. If graduated, update Repayment Schedule rows 71-125.
B26: 22 | C26: Bajaj Finance | D26: Term Loan | E26: FB-Term | F26: Non-Revolving | G26: Main | H26: INR | I26: 150 | J26: =I26 -> 150 | L26: =IF(UseFullUtilisation=TRUE(),J26,IF(K26="",0,K26)) -> 150 | M26: =IFERROR(L26/J26,0) -> 1 | N26: =J26-L26 -> 0 | O26: Bajaj Floating Reference Rate (BFRR) | P26: 0.001 | Q26: =BMK_BFRR+P26 -> 0.086 | R26: Floating | S26: 12 | T26: Quarterly | U26: 96 | V26: 28 | W26: 45887 | X26: =IFERROR(EDATE(IF(W26="",Z26,W26),S26),"-") -> 46252 | Y26: =IFERROR(EDATE(IF(W26="",Z26,W26),U26),"-") -> 48809 | Z26: 45887 | AA26: 46265 | AB26: CAPEX reimbursement + CAPEX + GCP | AC26: 1st p-p on FA at Coke Plant Khurunti; 2nd p-p on CA; MSC 1.25x | AD26: Bajaj TL Sanction BFL/CL-MM/2025-26/JCL/01 dated 18-Aug-2025 | AE26: Floating; quarterly reset; WDV basis. No prepayment till 30-Sep-2026. | Validity rolled +1 year (orig: 2025-08-31) per Assumption #12: annual-renewal WC facilities presumed operationally renewed. Confirm with relationship manager.
B27: 23 | C27: ICICI Bank | D27: Cash Credit | E27: FB | F27: Revolving | G27: Main | H27: INR | I27: 50 | J27: =I27 -> 50 | L27: =IF(UseFullUtilisation=TRUE(),J27,IF(K27="",0,K27)) -> 50 | M27: =IFERROR(L27/J27,0) -> 1 | N27: =J27-L27 -> 0 | O27: 6M I-MCLR (ICICI) | P27: 0.0045 | Q27: =BMK_6M_IMCLR_ICICI+P27 -> 0.0875 | R27: Floating | S27: - | T27: On Demand | U27: 12 | V27: - | W27: =Z27 -> 45916 | X27: - | Y27: - | Z27: 45916 | AA27: 46268 | AB27: Working capital | AC27: 1st p-p on CA; 2nd p-p on FA; 2nd p-p mortgage Kalinga Nagar | AD27: ICICI Credit Arrangement Letter dated 16-Sep-2025 | AE27: Reset 6 monthly; one-way interchangeability CC->LC.
B28: 24 | C28: ICICI Bank | D28: Working Capital Demand Loan (WCDL) | E28: FB | F28: Revolving | G28: Sub-limit of CC | H28: INR | I28: 50 | J28: =I28 -> 50 | L28: =IF(UseFullUtilisation=TRUE(),J28,IF(K28="",0,K28)) -> 50 | M28: =IFERROR(L28/J28,0) -> 1 | N28: =J28-L28 -> 0 | O28: Repo Rate | P28: - | Q28: =BMK_REPO+IF(ISNUMBER(P28),P28,0) -> 0.0525 | R28: Floating | S28: - | T28: On Maturity | U28: 3 | V28: - | W28: =Z28 -> 45972 | X28: - | Y28: - | Z28: 45972 | AA28: 46268 | AB28: Working capital (bullet) | AC28: 1st p-p on CA; 2nd p-p on FA; 2nd p-p mortgage Kalinga Nagar | AD28: ICICI WCDL Addendum dated 11-Nov-2025 | AE28: Repo reset 15D/1M/3M by tenor. 0.50% prepayment premium. | ⚠ RATE INCOMPLETE: 5.25% reflects Repo only. Spread TBD at drawdown per sanction letter (16-Sep-2025). Market convention for WCDL above Repo: 50-100 bps spread. Update Q28 / column P28 when actual rate confirmed by ICICI RM.
B29: 25 | C29: ICICI Bank | D29: Letter of Credit (Inland/Foreign) | E29: NFB | F29: Revolving | G29: Main | H29: INR | I29: 150 | J29: =I29 -> 150 | L29: =IF(UseFullUtilisation=TRUE(),J29,IF(K29="",0,K29)) -> 150 | M29: =IFERROR(L29/J29,0) -> 1 | N29: =J29-L29 -> 0 | O29: Fixed commission | P29: - | Q29: 0.005 | R29: Fixed | S29: - | T29: On Maturity | U29: 5 | V29: - | W29: =Z29 -> 45916 | X29: - | Y29: - | Z29: 45916 | AA29: 46268 | AB29: RM, consumables, stores, spares, tools | AC29: 1st p-p on CA; 2nd p-p on FA; 2nd p-p mortgage Kalinga Nagar | AD29: ICICI Credit Arrangement Letter dated 16-Sep-2025 | AE29: LC to JSL Global Commodities Pte Ltd capped at INR 25 Cr.
B30: 26 | C30: ICICI Bank | D30: SBLC for Buyers' Credit | E30: NFB | F30: Revolving | G30: Sub-limit of LC | H30: INR | I30: 150 | J30: =I30 -> 150 | L30: =IF(UseFullUtilisation=TRUE(),J30,IF(K30="",0,K30)) -> 150 | M30: =IFERROR(L30/J30,0) -> 1 | N30: =J30-L30 -> 0 | O30: Fixed commission | P30: - | Q30: 0.005 | R30: Fixed | S30: - | T30: On Maturity | U30: 5 | V30: - | W30: =Z30 -> 45916 | X30: - | Y30: - | Z30: 45916 | AA30: 46268 | AB30: Buyer's credit (USD/INR) | AC30: 1st p-p on CA; 2nd p-p on FA; 2nd p-p mortgage Kalinga Nagar | AD30: ICICI Credit Arrangement Letter dated 16-Sep-2025 | AE30: Excluded from DP; no rollover beyond RBI guidelines.
B31: 27 | C31: ICICI Bank | D31: Bank Guarantee - Performance | E31: NFB | F31: Revolving | G31: Sub-limit of LC | H31: INR | I31: 25 | J31: =I31 -> 25 | L31: =IF(UseFullUtilisation=TRUE(),J31,IF(K31="",0,K31)) -> 25 | M31: =IFERROR(L31/J31,0) -> 1 | N31: =J31-L31 -> 0 | O31: Fixed commission | P31: - | Q31: 0.005 | R31: Fixed | S31: - | T31: On Maturity | U31: 36 | V31: - | W31: =Z31 -> 45916 | X31: - | Y31: - | Z31: 45916 | AA31: 46268 | AB31: Bid bond, EMD, performance, customs | AC31: 1st p-p on CA; 2nd p-p on FA; 2nd p-p mortgage Kalinga Nagar | AD31: ICICI Credit Arrangement Letter dated 16-Sep-2025 | AE31: SWIFT INR 1,000/BG; min commission INR 500/BG.
B32: 28 | C32: ICICI Bank | D32: Bank Guarantee - Financial | E32: NFB | F32: Revolving | G32: Sub-limit of LC | H32: INR | I32: 5 | J32: =I32 -> 5 | L32: =IF(UseFullUtilisation=TRUE(),J32,IF(K32="",0,K32)) -> 5 | M32: =IFERROR(L32/J32,0) -> 1 | N32: =J32-L32 -> 0 | O32: Fixed commission | P32: - | Q32: 0.006 | R32: Fixed | S32: - | T32: On Maturity | U32: 36 | V32: - | W32: =Z32 -> 45916 | X32: - | Y32: - | Z32: 45916 | AA32: 46268 | AB32: Financial guarantees | AC32: 1st p-p on CA; 2nd p-p on FA; 2nd p-p mortgage Kalinga Nagar | AD32: ICICI Credit Arrangement Letter dated 16-Sep-2025 | AE32: INR 50 mn per sanction letter.
B33: 29 | C33: South Indian Bank | D33: CCOL (Cash Credit) | E33: FB | F33: Revolving | G33: Sub-limit of LC | H33: INR | I33: 50 | J33: =I33 -> 50 | L33: =IF(UseFullUtilisation=TRUE(),J33,IF(K33="",0,K33)) -> 50 | M33: =IFERROR(L33/J33,0) -> 1 | N33: =J33-L33 -> 0 | O33: 12M MCLR (SIB) | P33: 0.0045 | Q33: =BMK_12M_MCLR_SIB+P33 -> 0.102 | R33: Floating | S33: - | T33: On Demand | U33: 12 | V33: - | W33: =Z33 -> 45829 | X33: - | Y33: - | Z33: 45829 | AA33: Annual renewal | AB33: Pre-sale and post-sale working capital | AC33: 1st p-p on CA; 2nd p-p on FA; 2nd p-p mortgage Kalinga Nagar | AD33: SIB Renewal BR/SANC/01/2025-26 dated 21-Jun-2025 | AE33: Annual reset.
B34: 30 | C34: South Indian Bank | D34: WCL / WCDL | E34: FB | F34: Revolving | G34: Sub-limit of CCOL | H34: INR | I34: 50 | J34: =I34 -> 50 | L34: =IF(UseFullUtilisation=TRUE(),J34,IF(K34="",0,K34)) -> 50 | M34: =IFERROR(L34/J34,0) -> 1 | N34: =J34-L34 -> 0 | O34: To be decided | P34: - | R34: TBD | S34: - | T34: On Maturity | U34: 12 | V34: - | W34: =Z34 -> 45829 | X34: - | Y34: - | Z34: 45829 | AA34: Annual renewal | AB34: Working capital (bullet) | AC34: 1st p-p on CA; 2nd p-p on FA; 2nd p-p mortgage Kalinga Nagar | AD34: SIB Renewal BR/SANC/01/2025-26 dated 21-Jun-2025 | AE34: Rate at each availment; rollover subject to rating/compliance.
B35: 31 | C35: South Indian Bank | D35: Inland / Import LC | E35: NFB | F35: Revolving | G35: Main | H35: INR | I35: 150 | J35: =I35 -> 150 | L35: =IF(UseFullUtilisation=TRUE(),J35,IF(K35="",0,K35)) -> 150 | M35: =IFERROR(L35/J35,0) -> 1 | N35: =J35-L35 -> 0 | O35: Fixed commission | P35: - | Q35: 0.0065 | R35: Fixed | S35: - | T35: On Maturity | U35: 6 | V35: - | W35: =Z35 -> 45829 | X35: - | Y35: - | Z35: 45829 | AA35: Annual renewal | AB35: Purchase / import of RM, trading goods, services | AC35: 1st p-p on CA; 2nd p-p on FA; 2nd p-p mortgage Kalinga Nagar | AD35: SIB Renewal BR/SANC/01/2025-26 dated 21-Jun-2025 | AE35: Total LC + Capex LC <= INR 150 Cr.
B36: 32 | C36: South Indian Bank | D36: Capex LC | E36: NFB | F36: Revolving | G36: Main (within LC umbrella) | H36: INR | I36: 50 | J36: =I36 -> 50 | L36: =IF(UseFullUtilisation=TRUE(),J36,IF(K36="",0,K36)) -> 50 | M36: =IFERROR(L36/J36,0) -> 1 | N36: =J36-L36 -> 0 | O36: Fixed commission | P36: - | Q36: 0.0075 | R36: Fixed | S36: - | T36: On Maturity | U36: 12 | V36: - | W36: =Z36 -> 45829 | X36: - | Y36: - | Z36: 45829 | AA36: Annual renewal | AB36: Capital goods and capital maintenance | AC36: 1st p-p on CA; 2nd p-p on FA; 2nd p-p mortgage Kalinga Nagar | AD36: SIB Renewal BR/SANC/01/2025-26 dated 21-Jun-2025 | AE36: Combined with Inland/Import LC limit.
B37: 33 | C37: South Indian Bank | D37: SBLC | E37: NFB | F37: Revolving | G37: Sub-limit of LC | H37: INR | I37: 150 | J37: =I37 -> 150 | L37: =IF(UseFullUtilisation=TRUE(),J37,IF(K37="",0,K37)) -> 150 | M37: =IFERROR(L37/J37,0) -> 1 | N37: =J37-L37 -> 0 | O37: Fixed commission | P37: - | Q37: 0.0065 | R37: Fixed | S37: - | T37: On Maturity | U37: 4 | V37: - | W37: =Z37 -> 45829 | X37: - | Y37: - | Z37: 45829 | AA37: Annual renewal | AB37: Buyer's credit for import payments | AC37: 1st p-p on CA; 2nd p-p on FA; 2nd p-p mortgage Kalinga Nagar | AD37: SIB Renewal BR/SANC/01/2025-26 dated 21-Jun-2025 | AE37: No rollover. BC all-in-cost: Benchmark + 300 bps cap.
B38: 34 | C38: South Indian Bank | D38: Forward Contract Limit | E38: Hedge | F38: Revolving | G38: Main | H38: INR | I38: 3 | J38: =I38 -> 3 | L38: =IF(UseFullUtilisation=TRUE(),J38,IF(K38="",0,K38)) -> 3 | M38: =IFERROR(L38/J38,0) -> 1 | N38: =J38-L38 -> 0 | O38: N/A | P38: - | Q38: 0 | R38: Fixed | S38: - | T38: On Settlement | U38: 12 | V38: - | W38: =Z38 -> 45829 | X38: - | Y38: - | Z38: 45829 | AA38: Annual renewal | AB38: Hedging exchange risk | AC38: N/A | AD38: SIB Renewal BR/SANC/01/2025-26 dated 21-Jun-2025 | AE38: Notional limit; no cash outflow unless settled.
B39: TOTAL | J39: =SUM(J5:J38) -> 3410.7 | K39: =SUM(K5:K38) -> 0 | L39: =SUM(L5:L38) -> 3410.7 | M39: =IFERROR(SUMPRODUCT('Facility Master'!$M$5:$M$38,'Facility Master'!$J$5:$J$38)/SUM('Facility Master'!$J$5:$J$38),0) -> 1 | N39: =SUM(N5:N38) -> 0 | Q39: =IFERROR(SUMPRODUCT('Facility Master'!$Q$5:$Q$38,'Facility Master'!$L$5:$L$38)/SUMIFS('Facility Master'!$L$5:$L$38,'Facility Master'!$Q$5:$Q$38,">0"),0) -> 0.03868182

Sheet Lender Summary
B2: LENDER SUMMARY
B3: All figures in INR Cr unless noted. Sourced from Facility Master via SUMIFS.
B5: # | C5: Lender | D5: Total Sanction | E5: Fund-Based Sanction | F5: Non-Fund Based Sanction | G5: Term Loan Sanction | H5: Effective Outstanding | I5: Available Headroom | J5: Weighted Avg Utilisation % | K5: Weighted Avg Cost (on FB+TL) | L5: Earliest Maturity | M5: # of Facilities | N5: Key Covenant / Notes | O5: Sub-limit Amount (double-counted in Total) | P5: Sanction-Letter Umbrella Cap (₹ Cr) | Q5: % of Cap Utilised
B6: 1 | C6: RBL Bank | D6: =IFERROR(SUMIFS('Facility Master'!$J$5:$J$38,'Facility Master'!$C$5:$C$38,C6),0) -> 1482 | E6: =IFERROR(SUMIFS('Facility Master'!$J$5:$J$38,'Facility Master'!$C$5:$C$38,C6,'Facility Master'!$E$5:$E$38,"FB")+SUMIFS('Facility Master'!$J$5:$J$38,'Facility Master'!$C$5:$C$38,C6,'Facility Master'!$E$5:$E$38,"FB-Term")+SUMIFS('Facility Master'!$J$5:$J$38,'Facility Master'!$C$5:$C$38,C6,'Facility Master'!$E$5:$E$38,"FB-FCY")+SUMIFS('Facility Master'!$J$5:$J$38,'Facility Master'!$C$5:$C$38,C6,'Facility Master'!$E$5:$E$38,"FB-FDbacked"),0) -> 972 | F6: =IFERROR(SUMIFS('Facility Master'!$J$5:$J$38,'Facility Master'!$C$5:$C$38,C6,'Facility Master'!$E$5:$E$38,"NFB")+SUMIFS('Facility Master'!$J$5:$J$38,'Facility Master'!$C$5:$C$38,C6,'Facility Master'!$E$5:$E$38,"NFB-FDbacked"),0) -> 490 | G6: =IFERROR(SUMIFS('Facility Master'!$J$5:$J$38,'Facility Master'!$C$5:$C$38,C6,'Facility Master'!$E$5:$E$38,"FB-Term"),0) -> 200 | H6: =IFERROR(SUMIFS('Facility Master'!$L$5:$L$38,'Facility Master'!$C$5:$C$38,C6),0) -> 1482 | I6: =D6-H6 -> 0 | J6: =IFERROR(H6/D6,0) -> 1 | K6: =IFERROR(SUMPRODUCT(('Facility Master'!$C$5:$C$38=C6)*('Facility Master'!$Q$5:$Q$38)*('Facility Master'!$L$5:$L$38))/SUMIFS('Facility Master'!$L$5:$L$38,'Facility Master'!$C$5:$C$38,C6,'Facility Master'!$Q$5:$Q$38,">0"),0) -> 0.041486486 | L6: ='Facility Master'!Y13 -> 47142 | M6: =COUNTIFS('Facility Master'!$C$5:$C$38,C6) -> 15 | N6: Overall cap INR 300 Cr excl. FD-backed | O6: 1182 | P6: 300 | Q6: =IFERROR(H6/P6,0) -> 4.94
B7: 2 | C7: YES Bank | D7: =IFERROR(SUMIFS('Facility Master'!$J$5:$J$38,'Facility Master'!$C$5:$C$38,C7),0) -> 895.7 | E7: =IFERROR(SUMIFS('Facility Master'!$J$5:$J$38,'Facility Master'!$C$5:$C$38,C7,'Facility Master'!$E$5:$E$38,"FB")+SUMIFS('Facility Master'!$J$5:$J$38,'Facility Master'!$C$5:$C$38,C7,'Facility Master'!$E$5:$E$38,"FB-Term")+SUMIFS('Facility Master'!$J$5:$J$38,'Facility Master'!$C$5:$C$38,C7,'Facility Master'!$E$5:$E$38,"FB-FCY")+SUMIFS('Facility Master'!$J$5:$J$38,'Facility Master'!$C$5:$C$38,C7,'Facility Master'!$E$5:$E$38,"FB-FDbacked"),0) -> 495.7 | F7: =IFERROR(SUMIFS('Facility Master'!$J$5:$J$38,'Facility Master'!$C$5:$C$38,C7,'Facility Master'!$E$5:$E$38,"NFB")+SUMIFS('Facility Master'!$J$5:$J$38,'Facility Master'!$C$5:$C$38,C7,'Facility Master'!$E$5:$E$38,"NFB-FDbacked"),0) -> 400 | G7: =IFERROR(SUMIFS('Facility Master'!$J$5:$J$38,'Facility Master'!$C$5:$C$38,C7,'Facility Master'!$E$5:$E$38,"FB-Term"),0) -> 320.7 | H7: =IFERROR(SUMIFS('Facility Master'!$L$5:$L$38,'Facility Master'!$C$5:$C$38,C7),0) -> 895.7 | I7: =D7-H7 -> 0 | J7: =IFERROR(H7/D7,0) -> 1 | K7: =IFERROR(SUMPRODUCT(('Facility Master'!$C$5:$C$38=C7)*('Facility Master'!$Q$5:$Q$38)*('Facility Master'!$L$5:$L$38))/SUMIFS('Facility Master'!$L$5:$L$38,'Facility Master'!$C$5:$C$38,C7,'Facility Master'!$Q$5:$Q$38,">0"),0) -> 0.051239509 | L7: ='Facility Master'!Y25 -> 49948 | M7: =COUNTIFS('Facility Master'!$C$5:$C$38,C7) -> 6 | N7: WC cap INR 200 Cr; FACR >1.33x post 19-Mar-2026 | O7: 250 | P7: 200 | Q7: =IFERROR(H7/P7,0) -> 4.4785
B8: 3 | C8: Bajaj Finance | D8: =IFERROR(SUMIFS('Facility Master'!$J$5:$J$38,'Facility Master'!$C$5:$C$38,C8),0) -> 150 | E8: =IFERROR(SUMIFS('Facility Master'!$J$5:$J$38,'Facility Master'!$C$5:$C$38,C8,'Facility Master'!$E$5:$E$38,"FB")+SUMIFS('Facility Master'!$J$5:$J$38,'Facility Master'!$C$5:$C$38,C8,'Facility Master'!$E$5:$E$38,"FB-Term")+SUMIFS('Facility Master'!$J$5:$J$38,'Facility Master'!$C$5:$C$38,C8,'Facility Master'!$E$5:$E$38,"FB-FCY")+SUMIFS('Facility Master'!$J$5:$J$38,'Facility Master'!$C$5:$C$38,C8,'Facility Master'!$E$5:$E$38,"FB-FDbacked"),0) -> 150 | F8: =IFERROR(SUMIFS('Facility Master'!$J$5:$J$38,'Facility Master'!$C$5:$C$38,C8,'Facility Master'!$E$5:$E$38,"NFB")+SUMIFS('Facility Master'!$J$5:$J$38,'Facility Master'!$C$5:$C$38,C8,'Facility Master'!$E$5:$E$38,"NFB-FDbacked"),0) -> 0 | G8: =IFERROR(SUMIFS('Facility Master'!$J$5:$J$38,'Facility Master'!$C$5:$C$38,C8,'Facility Master'!$E$5:$E$38,"FB-Term"),0) -> 150 | H8: =IFERROR(SUMIFS('Facility Master'!$L$5:$L$38,'Facility Master'!$C$5:$C$38,C8),0) -> 150 | I8: =D8-H8 -> 0 | J8: =IFERROR(H8/D8,0) -> 1 | K8: =IFERROR(SUMPRODUCT(('Facility Master'!$C$5:$C$38=C8)*('Facility Master'!$Q$5:$Q$38)*('Facility Master'!$L$5:$L$38))/SUMIFS('Facility Master'!$L$5:$L$38,'Facility Master'!$C$5:$C$38,C8,'Facility Master'!$Q$5:$Q$38,">0"),0) -> 0.086 | L8: ='Facility Master'!Y26 -> 48809 | M8: =COUNTIFS('Facility Master'!$C$5:$C$38,C8) -> 1 | N8: FACR >1.25x; no prepay till 30-Sep-2026 | O8: 0 | P8: 150 | Q8: =IFERROR(H8/P8,0) -> 1
B9: 4 | C9: ICICI Bank | D9: =IFERROR(SUMIFS('Facility Master'!$J$5:$J$38,'Facility Master'!$C$5:$C$38,C9),0) -> 430 | E9: =IFERROR(SUMIFS('Facility Master'!$J$5:$J$38,'Facility Master'!$C$5:$C$38,C9,'Facility Master'!$E$5:$E$38,"FB")+SUMIFS('Facility Master'!$J$5:$J$38,'Facility Master'!$C$5:$C$38,C9,'Facility Master'!$E$5:$E$38,"FB-Term")+SUMIFS('Facility Master'!$J$5:$J$38,'Facility Master'!$C$5:$C$38,C9,'Facility Master'!$E$5:$E$38,"FB-FCY")+SUMIFS('Facility Master'!$J$5:$J$38,'Facility Master'!$C$5:$C$38,C9,'Facility Master'!$E$5:$E$38,"FB-FDbacked"),0) -> 100 | F9: =IFERROR(SUMIFS('Facility Master'!$J$5:$J$38,'Facility Master'!$C$5:$C$38,C9,'Facility Master'!$E$5:$E$38,"NFB")+SUMIFS('Facility Master'!$J$5:$J$38,'Facility Master'!$C$5:$C$38,C9,'Facility Master'!$E$5:$E$38,"NFB-FDbacked"),0) -> 330 | G9: =IFERROR(SUMIFS('Facility Master'!$J$5:$J$38,'Facility Master'!$C$5:$C$38,C9,'Facility Master'!$E$5:$E$38,"FB-Term"),0) -> 0 | H9: =IFERROR(SUMIFS('Facility Master'!$L$5:$L$38,'Facility Master'!$C$5:$C$38,C9),0) -> 430 | I9: =D9-H9 -> 0 | J9: =IFERROR(H9/D9,0) -> 1 | K9: =IFERROR(SUMPRODUCT(('Facility Master'!$C$5:$C$38=C9)*('Facility Master'!$Q$5:$Q$38)*('Facility Master'!$L$5:$L$38))/SUMIFS('Facility Master'!$L$5:$L$38,'Facility Master'!$C$5:$C$38,C9,'Facility Master'!$Q$5:$Q$38,">0"),0) -> 0.020127907 | L9: ="-" -> - | M9: =COUNTIFS('Facility Master'!$C$5:$C$38,C9) -> 6 | N9: Aggregate cap INR 200 Cr; FB<=50, NFB<=150 | O9: 330 | P9: 200 | Q9: =IFERROR(H9/P9,0) -> 2.15
B10: 5 | C10: South Indian Bank | D10: =IFERROR(SUMIFS('Facility Master'!$J$5:$J$38,'Facility Master'!$C$5:$C$38,C10),0) -> 453 | E10: =IFERROR(SUMIFS('Facility Master'!$J$5:$J$38,'Facility Master'!$C$5:$C$38,C10,'Facility Master'!$E$5:$E$38,"FB")+SUMIFS('Facility Master'!$J$5:$J$38,'Facility Master'!$C$5:$C$38,C10,'Facility Master'!$E$5:$E$38,"FB-Term")+SUMIFS('Facility Master'!$J$5:$J$38,'Facility Master'!$C$5:$C$38,C10,'Facility Master'!$E$5:$E$38,"FB-FCY")+SUMIFS('Facility Master'!$J$5:$J$38,'Facility Master'!$C$5:$C$38,C10,'Facility Master'!$E$5:$E$38,"FB-FDbacked"),0) -> 100 | F10: =IFERROR(SUMIFS('Facility Master'!$J$5:$J$38,'Facility Master'!$C$5:$C$38,C10,'Facility Master'!$E$5:$E$38,"NFB")+SUMIFS('Facility Master'!$J$5:$J$38,'Facility Master'!$C$5:$C$38,C10,'Facility Master'!$E$5:$E$38,"NFB-FDbacked"),0) -> 350 | G10: =IFERROR(SUMIFS('Facility Master'!$J$5:$J$38,'Facility Master'!$C$5:$C$38,C10,'Facility Master'!$E$5:$E$38,"FB-Term"),0) -> 0 | H10: =IFERROR(SUMIFS('Facility Master'!$L$5:$L$38,'Facility Master'!$C$5:$C$38,C10),0) -> 453 | I10: =D10-H10 -> 0 | J10: =IFERROR(H10/D10,0) -> 1 | K10: =IFERROR(SUMPRODUCT(('Facility Master'!$C$5:$C$38=C10)*('Facility Master'!$Q$5:$Q$38)*('Facility Master'!$L$5:$L$38))/SUMIFS('Facility Master'!$L$5:$L$38,'Facility Master'!$C$5:$C$38,C10,'Facility Master'!$Q$5:$Q$38,">0"),0) -> 0.0185625 | L10: ="-" -> - | M10: =COUNTIFS('Facility Master'!$C$5:$C$38,C10) -> 6 | N10: LC+Capex LC combined cap INR 150 Cr | O10: 250 | P10: 150 | Q10: =IFERROR(H10/P10,0) -> 3.02
B11: Total | D11: =IFERROR(SUM(D6:D10),0) -> 3410.7 | E11: =IFERROR(SUM(E6:E10),0) -> 1817.7 | F11: =IFERROR(SUM(F6:F10),0) -> 1570 | G11: =IFERROR(SUM(G6:G10),0) -> 670.7 | H11: =IFERROR(SUM(H6:H10),0) -> 3410.7 | I11: =SUM(I6:I10) -> 0 | J11: =IFERROR(H11/D11,0) -> 1 | K11: =IFERROR(SUMPRODUCT(K6:K10,H6:H10)/H11,0) -> 0.040267984 | L11: =MIN('Facility Master'!Y13,'Facility Master'!Y25,'Facility Master'!Y26) -> 47142 | M11: =SUM(M6:M10) -> 34 | O11: =SUM(O6:O10) -> 2012 | P11: =SUM(P6:P10) -> 1000 | Q11: =IFERROR(H11/P11,0) -> 3.4107
B14: Lender Exposure Caps (from sanction letters)
B15: Lender | C15: Cap Description | E15: Cap (INR Cr) | F15: Source | H15: Current Exposure | J15: Headroom | L15: % Utilised
B16: RBL Bank | C16: Overall exposure excl. FD-backed | E16: 300 | F16: RBL 24-Jan-2024 & 31-Dec-2025 | H16: Reference only
B17: RBL Bank | C17: Overall FB WC excl. FD-backed | E17: 100 | F17: RBL 28-Feb-2025 | H17: Reference only
B18: RBL Bank | C18: Overall TL / Capex LC / SBLC | E18: 200 | F18: RBL 24-Jan-2024 | H18: Reference only
B19: RBL Bank | C19: Buyer's Credit WC + LER (total RBL) | E19: 100 | F19: RBL 13-Mar-2025 (BC-WC) | H19: Reference only
B20: RBL Bank | C20: Buyer's Credit CAPEX (total RBL) | E20: 172 | F20: RBL 27-Mar-2025 (BC-CAPEX) | H20: Reference only
B21: YES Bank | C21: Total sanctioned facilities | E21: 488.85 | F21: YBL 19-Mar-2026 | H21: Reference only
B22: YES Bank | C22: WC cap (net of receivable finance 1 Cr) | E22: 200 | F22: YBL 19-Mar-2026 | H22: Reference only
B23: YES Bank | C23: LC to group/associate companies | E23: 50 | F23: YBL 19-Mar-2026 | H23: Reference only
B24: ICICI Bank | C24: Aggregate sanctioned exposure | E24: 200 | F24: ICICI 16-Sep-2025 | H24: Reference only
B25: ICICI Bank | C25: Fund-based exposure | E25: 50 | F25: ICICI 16-Sep-2025 | H25: Reference only
B26: ICICI Bank | C26: Non-fund-based exposure | E26: 150 | F26: ICICI 16-Sep-2025 | H26: Reference only
B27: ICICI Bank | C27: LC to JSL Global Commodities | E27: 25 | F27: ICICI 16-Sep-2025 | H27: Reference only
... B29: South Indian Bank | C29: Forward contract ceiling | E29: 3 | F29: SIB 21-Jun-2025 | H29: Reference only
B31: NOTE ON RBL AGGREGATION: RBL Total Sanction of ₹1,482 Cr is a GROSS number that double-counts sub-limits (e.g., WCDL is a sub-limit of the LC Main Limit). The binding constraint is the Sanction-Letter Umbrella Cap of ₹300 Cr (excl. FD-backed). The Sub-limit Amount column quantifies the double-counted portion. For lender-concentration analysis, use the Umbrella Cap column rather than Total Sanction.

Sheet Working Capital Facilities
B2: WORKING CAPITAL FACILITIES
B3: All fund-based and non-fund-based WC lines from Facility Master. Includes CC, WCDL, PIF, PID, CCOL, FDOD, Buyer's Credit WC. LC/BG/SBLC are on the 'Non-Fund Based Facilities' tab.
B5: # | C5: Lender | D5: Facility | E5: Sub-limit Parent | F5: Sanction (INR Cr) | G5: Outstanding (INR Cr) | H5: Available (INR Cr) | I5: Utilisation % | J5: Benchmark | K5: Spread | L5: Effective Rate | M5: Tenor (Months) | N5: Validity Date | O5: Security (summary) | P5: Remarks
B6: 1 | C6: ='Facility Master'!C7 -> RBL Bank | D6: ='Facility Master'!D7 -> Invoice Discounting (PID) | E6: ='Facility Master'!G7 -> Standalone (under WC) | F6: ='Facility Master'!J7 -> 100 | G6: ='Facility Master'!L7 -> 100 | H6: ='Facility Master'!N7 -> 0 | I6: ='Facility Master'!M7 -> 1 | J6: ='Facility Master'!O7 -> To be decided | K6: =IFERROR('Facility Master'!P7,0) -> - | L6: =IFERROR('Facility Master'!Q7,0) -> 0 | M6: =IFERROR('Facility Master'!U7,0) -> 1 | N6: =IFERROR('Facility Master'!AA7,0) -> 46356 | O6: =IFERROR('Facility Master'!AC7,0) -> 1st p-p on current assets; 2nd p-p on FA; Personal guarantee | P6: =IFERROR('Facility Master'!AE7,0) -> Rate not specified in sanction letter. | Validity rolled +1 year (orig: 2025-11-30) per Assumption #12: annual-renewal WC facilities presumed operationally renewed. Confirm with relationship manager.
B7: 2 | C7: ='Facility Master'!C9 -> RBL Bank | D7: ='Facility Master'!D9 -> Pre-Acceptance LCBD | E7: ='Facility Master'!G9 -> Standalone (under WC) | F7: ='Facility Master'!J9 -> 100 | G7: ='Facility Master'!L9 -> 100 | H7: ='Facility Master'!N9 -> 0 | I7: ='Facility Master'!M9 -> 1 | J7: ='Facility Master'!O9 -> To be decided | K7: =IFERROR('Facility Master'!P9,0) -> - | L7: =IFERROR('Facility Master'!Q9,0) -> 0 | M7: =IFERROR('Facility Master'!U9,0) -> - | N7: =IFERROR('Facility Master'!AA9,0) -> 46356 | O7: =IFERROR('Facility Master'!AC9,0) -> 1st p-p on current assets; 2nd p-p on FA; Personal guarantee | P7: =IFERROR('Facility Master'!AE9,0) -> Rate not specified in sanction letter. | Validity rolled +1 year (orig: 2025-11-30) per Assumption #12: annual-renewal WC facilities presumed operationally renewed. Confirm with relationship manager.
B8: 3 | C8: ='Facility Master'!C10 -> RBL Bank | D8: ='Facility Master'!D10 -> Cash Credit | E8: ='Facility Master'!G10 -> Standalone (under WC) | F8: ='Facility Master'!J10 -> 100 | G8: ='Facility Master'!L10 -> 100 | H8: ='Facility Master'!N10 -> 0 | I8: ='Facility Master'!M10 -> 1 | J8: ='Facility Master'!O10 -> 1Y MCLR (RBL Bank) | K8: =IFERROR('Facility Master'!P10,0) -> 0.0005 | L8: =IFERROR('Facility Master'!Q10,0) -> 0.0905 | M8: =IFERROR('Facility Master'!U10,0) -> - | N8: =IFERROR('Facility Master'!AA10,0) -> 46356 | O8: =IFERROR('Facility Master'!AC10,0) -> 1st p-p on current assets; 2nd p-p on FA; Personal guarantee | P8: =IFERROR('Facility Master'!AE10,0) -> Pricing defined 28-Feb-2025; unchanged in 31-Dec-2025 letter. | Validity rolled +1 year (orig: 2025-11-30) per Assumption #12: annual-renewal WC facilities presumed operationally renewed. Confirm with relationship manager.
B9: 4 | C9: ='Facility Master'!C11 -> RBL Bank | D9: ='Facility Master'!D11 -> Working Capital Demand Loan (WCDL) | E9: ='Facility Master'!G11 -> Sub-limit of LC (Main) | F9: ='Facility Master'!J11 -> 100 | G9: ='Facility Master'!L11 -> 100 | H9: ='Facility Master'!N11 -> 0 | I9: ='Facility Master'!M11 -> 1 | J9: ='Facility Master'!O11 -> To be decided | K9: =IFERROR('Facility Master'!P11,0) -> - | L9: =IFERROR('Facility Master'!Q11,0) -> 0 | M9: =IFERROR('Facility Master'!U11,0) -> 4 | N9: =IFERROR('Facility Master'!AA11,0) -> 46356 | O9: =IFERROR('Facility Master'!AC11,0) -> 1st p-p on current assets; 2nd p-p on FA; Personal guarantee | P9: =IFERROR('Facility Master'!AE11,0) -> Rate set at drawdown. | Validity rolled +1 year (orig: 2025-11-30) per Assumption #12: annual-renewal WC facilities presumed operationally renewed. Confirm with relationship manager.
B10: 5 | C10: ='Facility Master'!C16 -> RBL Bank | D10: ='Facility Master'!D16 -> Overdraft backed by 100% FD (FDOD) | E10: ='Facility Master'!G16 -> Main | F10: ='Facility Master'!J16 -> 100 | G10: ='Facility Master'!L16 -> 100 | H10: ='Facility Master'!N16 -> 0 | I10: ='Facility Master'!M16 -> 1 | J10: ='Facility Master'!O16 -> FD rate | K10: =IFERROR('Facility Master'!P16,0) -> 0.0025 | L10: =IFERROR('Facility Master'!Q16,0) -> 0 | M10: =IFERROR('Facility Master'!U16,0) -> 12 | N10: =IFERROR('Facility Master'!AA16,0) -> 46356 | O10: =IFERROR('Facility Master'!AC16,0) -> Exclusive charge on FD = 100% of facility | P10: =IFERROR('Facility Master'!AE16,0) -> Excluded from INR 300 Cr overall cap. | Validity rolled +1 year (orig: 2025-11-30) per Assumption #12: annual-renewal WC facilities presumed operationally renewed. Confirm with relationship manager.
B11: 6 | C11: ='Facility Master'!C18 -> RBL Bank | D11: ='Facility Master'!D18 -> Buyer's Credit from GIFT City - WC | E11: ='Facility Master'!G18 -> Backed by BG/SBLC from RBL | F11: ='Facility Master'!J18 -> 100 | G11: ='Facility Master'!L18 -> 100 | H11: ='Facility Master'!N18 -> 0 | I11: ='Facility Master'!M18 -> 1 | J11: ='Facility Master'!O18 -> Term SOFR (USD) | K11: =IFERROR('Facility Master'!P18,0) -> - | L11: =IFERROR('Facility Master'!Q18,0) -> 0 | M11: =IFERROR('Facility Master'!U18,0) -> 6 | N11: =IFERROR('Facility Master'!AA18,0) -> 46356 | O11: =IFERROR('Facility Master'!AC18,0) -> RBL-issued BG/SBLC | P11: =IFERROR('Facility Master'!AE18,0) -> Total RBL exposure (incl. LER) capped at INR 100 Cr. | Sanctioned INR capped at ₹100 Cr per sanction letter (binding limit). USD sanctioned limit is USD 11M, but total RBL exposure ring-fenced at ₹100 Cr regardless of FX. Formula: =MIN(USD×FX/10, 100). | Validity rolled +1 year (orig: 2025-11-30) per Assumption #12: annual-renewal WC facilities presumed operationally renewed. Confirm with relationship manager. | LC commission unspecified in sanction letter ('applicable commission plus taxes'). Model shows 0 pending confirmation from RM. Typical market rate for sub-180-day inland LC is 0.40%-0.60% p.a. Update Facility Master Q18 when confirmed.
B12: 7 | C12: ='Facility Master'!C19 -> RBL Bank | D12: ='Facility Master'!D19 -> Buyer's Credit from GIFT City - CAPEX | E12: ='Facility Master'!G19 -> Backed by BG/SBLC from RBL | F12: ='Facility Master'!J19 -> 172 | G12: ='Facility Master'!L19 -> 172 | H12: ='Facility Master'!N19 -> 0 | I12: ='Facility Master'!M19 -> 1 | J12: ='Facility Master'!O19 -> Term SOFR (USD) | K12: =IFERROR('Facility Master'!P19,0) -> - | L12: =IFERROR('Facility Master'!Q19,0) -> 0 | M12: =IFERROR('Facility Master'!U19,0) -> 36 | N12: =IFERROR('Facility Master'!AA19,0) -> 46356 | O12: =IFERROR('Facility Master'!AC19,0) -> RBL-issued BG/SBLC | P12: =IFERROR('Facility Master'!AE19,0) -> Total RBL exposure capped at INR 172 Cr (implied FX ~86). | Sanctioned INR capped at ₹172 Cr per sanction letter (binding limit). USD sanctioned limit is USD 20M, but total RBL exposure ring-fenced at ₹172 Cr regardless of FX. Formula: =MIN(USD×FX/10, 172). | Validity rolled +1 year (orig: 2025-11-30) per Assumption #12: annual-renewal WC facilities presumed operationally renewed. Confirm with relationship manager.
B13: 8 | C13: ='Facility Master'!C20 -> YES Bank | D13: ='Facility Master'!D20 -> Purchase Invoice Financing | E13: ='Facility Master'!G20 -> Main (New) | F13: ='Facility Master'!J20 -> 100 | G13: ='Facility Master'!L20 -> 100 | H13: ='Facility Master'!N20 -> 0 | I13: ='Facility Master'!M20 -> 1 | J13: ='Facility Master'!O20 -> To be decided | K13: =IFERROR('Facility Master'!P20,0) -> - | L13: =IFERROR('Facility Master'!Q20,0) -> 0 | M13: =IFERROR('Facility Master'!U20,0) -> 3 | N13: =IFERROR('Facility Master'!AA20,0) -> 46142 | O13: =IFERROR('Facility Master'!AC20,0) -> 1st p-p hypothecation over current assets | P13: =IFERROR('Facility Master'!AE20,0) -> New facility; Interest payable upfront.
B14: 9 | C14: ='Facility Master'!C21 -> YES Bank | D14: ='Facility Master'!D21 -> Cash Credit | E14: ='Facility Master'!G21 -> Main (re-sized 19-Mar-2026) | F14: ='Facility Master'!J21 -> 25 | G14: ='Facility Master'!L21 -> 25 | H14: ='Facility Master'!N21 -> 0 | I14: ='Facility Master'!M21 -> 1 | J14: ='Facility Master'!O21 -> 3M MCLR (YBL) | K14: =IFERROR('Facility Master'!P21,0) -> 0.0007 | L14: =IFERROR('Facility Master'!Q21,0) -> 0.0907 | M14: =IFERROR('Facility Master'!U21,0) -> 12 | N14: =IFERROR('Facility Master'!AA21,0) -> Assumed annual review | O14: =IFERROR('Facility Master'!AC21,0) -> 1st p-p on CA; mortgage on Faridabad property; 2nd p-p on FA; PG | P14: =IFERROR('Facility Master'!AE21,0) -> Pricing moved T-Bill+1.98% -> 3M MCLR+0.07% on 19-Mar-2026.
B15: 10 | C15: ='Facility Master'!C24 -> YES Bank | D15: ='Facility Master'!D24 -> Working Capital Demand Loan (WCDL) | E15: ='Facility Master'!G24 -> Sub-limit of LC (Main) | F15: ='Facility Master'!J24 -> 50 | G15: ='Facility Master'!L24 -> 50 | H15: ='Facility Master'!N24 -> 0 | I15: ='Facility Master'!M24 -> 1 | J15: ='Facility Master'!O24 -> To be decided | K15: =IFERROR('Facility Master'!P24,0) -> - | L15: =IFERROR('Facility Master'!Q24,0) -> 0 | M15: =IFERROR('Facility Master'!U24,0) -> 6 | N15: =IFERROR('Facility Master'!AA24,0) -> Per renewal cycle | O15: =IFERROR('Facility Master'!AC24,0) -> 1st p-p on CA; mortgage on Faridabad property; 2nd p-p on FA; PG | P15: =IFERROR('Facility Master'!AE24,0) -> Min utilisation covenant: 40% of YBL limits.
B16: 11 | C16: ='Facility Master'!C27 -> ICICI Bank | D16: ='Facility Master'!D27 -> Cash Credit | E16: ='Facility Master'!G27 -> Main | F16: ='Facility Master'!J27 -> 50 | G16: ='Facility Master'!L27 -> 50 | H16: ='Facility Master'!N27 -> 0 | I16: ='Facility Master'!M27 -> 1 | J16: ='Facility Master'!O27 -> 6M I-MCLR (ICICI) | K16: =IFERROR('Facility Master'!P27,0) -> 0.0045 | L16: =IFERROR('Facility Master'!Q27,0) -> 0.0875 | M16: =IFERROR('Facility Master'!U27,0) -> 12 | N16: =IFERROR('Facility Master'!AA27,0) -> 46268 | O16: =IFERROR('Facility Master'!AC27,0) -> 1st p-p on CA; 2nd p-p on FA; 2nd p-p mortgage Kalinga Nagar | P16: =IFERROR('Facility Master'!AE27,0) -> Reset 6 monthly; one-way interchangeability CC->LC.
B17: 12 | C17: ='Facility Master'!C28 -> ICICI Bank | D17: ='Facility Master'!D28 -> Working Capital Demand Loan (WCDL) | E17: ='Facility Master'!G28 -> Sub-limit of CC | F17: ='Facility Master'!J28 -> 50 | G17: ='Facility Master'!L28 -> 50 | H17: ='Facility Master'!N28 -> 0 | I17: ='Facility Master'!M28 -> 1 | J17: ='Facility Master'!O28 -> Repo Rate | K17: =IFERROR('Facility Master'!P28,0) -> - | L17: =IFERROR('Facility Master'!Q28,0) -> 0.0525 | M17: =IFERROR('Facility Master'!U28,0) -> 3 | N17: =IFERROR('Facility Master'!AA28,0) -> 46268 | O17: =IFERROR('Facility Master'!AC28,0) -> 1st p-p on CA; 2nd p-p on FA; 2nd p-p mortgage Kalinga Nagar | P17: =IFERROR('Facility Master'!AE28,0) -> Repo reset 15D/1M/3M by tenor. 0.50% prepayment premium. | ⚠ RATE INCOMPLETE: 5.25% reflects Repo only. Spread TBD at drawdown per sanction letter (16-Sep-2025). Market convention for WCDL above Repo: 50-100 bps spread. Update Q28 / column P28 when actual rate confirmed by ICICI RM.
B18: 13 | C18: ='Facility Master'!C33 -> South Indian Bank | D18: ='Facility Master'!D33 -> CCOL (Cash Credit) | E18: ='Facility Master'!G33 -> Sub-limit of LC | F18: ='Facility Master'!J33 -> 50 | G18: ='Facility Master'!L33 -> 50 | H18: ='Facility Master'!N33 -> 0 | I18: ='Facility Master'!M33 -> 1 | J18: ='Facility Master'!O33 -> 12M MCLR (SIB) | K18: =IFERROR('Facility Master'!P33,0) -> 0.0045 | L18: =IFERROR('Facility Master'!Q33,0) -> 0.102 | M18: =IFERROR('Facility Master'!U33,0) -> 12 | N18: =IFERROR('Facility Master'!AA33,0) -> Annual renewal | O18: =IFERROR('Facility Master'!AC33,0) -> 1st p-p on CA; 2nd p-p on FA; 2nd p-p mortgage Kalinga Nagar | P18: =IFERROR('Facility Master'!AE33,0) -> Annual reset.
B19: 14 | C19: ='Facility Master'!C34 -> South Indian Bank | D19: ='Facility Master'!D34 -> WCL / WCDL | E19: ='Facility Master'!G34 -> Sub-limit of CCOL | F19: ='Facility Master'!J34 -> 50 | G19: ='Facility Master'!L34 -> 50 | H19: ='Facility Master'!N34 -> 0 | I19: ='Facility Master'!M34 -> 1 | J19: ='Facility Master'!O34 -> To be decided | K19: =IFERROR('Facility Master'!P34,0) -> - | L19: =IFERROR('Facility Master'!Q34,0) -> 0 | M19: =IFERROR('Facility Master'!U34,0) -> 12 | N19: =IFERROR('Facility Master'!AA34,0) -> Annual renewal | O19: =IFERROR('Facility Master'!AC34,0) -> 1st p-p on CA; 2nd p-p on FA; 2nd p-p mortgage Kalinga Nagar | P19: =IFERROR('Facility Master'!AE34,0) -> Rate at each availment; rollover subject to rating/compliance.
B20: Total | F20: =SUM(F6:F19) -> 1147 | G20: =SUM(G6:G19) -> 1147 | H20: =SUM(H6:H19) -> 0 | I20: =IFERROR(G20/F20,0) -> 1 | L20: =IFERROR(SUMPRODUCT(L6:L19,G6:G19)/SUMIFS(G6:G19,L6:L19,">0"),0) -> 0.085154545
B22: Working Capital Summary
B23: Total WC Sanctioned (INR Cr) | G23: =F20 -> 1147
B24: Total WC Utilised (INR Cr) | G24: =G20 -> 1147
B25: Unutilised Headroom (INR Cr) | G25: =H20 -> 0
B26: Weighted Avg WC Interest Rate | G26: =L20 -> 0.085154545

Sheet Term Loans
B2: TERM LOANS
B3: Three amortising term loans total INR 670.7 Cr sanctioned. Principal Outstanding and Principal Repaid below are derived from the Repayment Schedule. Quarterly instalment amounts are derived from Sanction ÷ Number of Instalments (EQI basis).
B5: # | C5: Lender | D5: Facility | E5: Sanction (INR Cr) | F5: Effective Outstanding (INR Cr) | G5: Drawdown Date | H5: Moratorium (Months) | I5: Repayment Start Date | J5: Maturity Date | K5: Quarterly Instalment (INR Cr) | L5: Benchmark | M5: Spread | N5: Effective Rate | O5: Remaining Instalments | P5: Principal Repaid (INR Cr) | Q5: Principal Outstanding (INR Cr) | R5: Security Package | S5: Key Financial Covenants
B6: 1 | C6: ='Facility Master'!C13 -> RBL Bank | D6: ='Facility Master'!D13 -> Term Loan - Main Limit | E6: ='Facility Master'!J13 -> 200 | F6: ='Facility Master'!L13 -> 200 | G6: ='Facility Master'!W13 -> 45315 | H6: ='Facility Master'!S13 -> 24 | I6: ='Facility Master'!X13 -> 46046 | J6: ='Facility Master'!Y13 -> 47142 | K6: =IFERROR(E6/'Facility Master'!V13,0) -> 16.666667 | L6: ='Facility Master'!O13 -> 1Y MCLR (RBL Bank) | M6: ='Facility Master'!P13 -> 0.0075 | N6: ='Facility Master'!Q13 -> 0.0975 | O6: =COUNTIFS('Repayment Schedule'!C10:C62,">"&AsOfDate,'Repayment Schedule'!G10:G62,">0") -> 11 | P6: =TL_9_PRINC_REPAID_TO_DATE -> 16.666667 | Q6: =TL_9_PRINC_OUTSTD -> 183.33333 | R6: 1st p-p on FA; 1st p-p mortgage on immovable; 2nd p-p on CA | S6: DSCR>1.25x; TermDebt/EBITDA<2.5x; TOL/TNW<3.0x; Rating>=A-
B7: 2 | C7: ='Facility Master'!C25 -> YES Bank | D7: ='Facility Master'!D25 -> Term Loan (Refinance Canara) | E7: ='Facility Master'!J25 -> 320.7 | F7: ='Facility Master'!L25 -> 320.7 | G7: ='Facility Master'!W25 -> 45642 | H7: ='Facility Master'!S25 -> 0 | I7: ='Facility Master'!X25 -> 45747 | J7: ='Facility Master'!Y25 -> 49948 | K7: =IFERROR(E7/'Facility Master'!V25,0) -> 6.8234043 | L7: ='Facility Master'!O25 -> 3M T-Bill | M7: ='Facility Master'!P25 -> 0.0252 | N7: ='Facility Master'!Q25 -> 0.077 | O7: =COUNTIFS('Repayment Schedule'!C72:C124,">"&AsOfDate,'Repayment Schedule'!G72:G124,">0") -> 42 | P7: =TL_21_PRINC_REPAID_TO_DATE -> 34.117021 | Q7: =TL_21_PRINC_OUTSTD -> 286.58298 | R7: 2nd p-p on CA; 1st p-p on FA; 1st p-p EM Kalinga Nagar | S7: DSCR>1.20x; TD/EBITDA<4.5x till FY27 / <3.5x FY28+; TD/ATNW<2.0x; FACR>1.33x
B8: 3 | C8: ='Facility Master'!C26 -> Bajaj Finance | D8: ='Facility Master'!D26 -> Term Loan | E8: ='Facility Master'!J26 -> 150 | F8: ='Facility Master'!L26 -> 150 | G8: ='Facility Master'!W26 -> 45887 | H8: ='Facility Master'!S26 -> 12 | I8: ='Facility Master'!X26 -> 46252 | J8: ='Facility Master'!Y26 -> 48809 | K8: =IFERROR(E8/'Facility Master'!V26,0) -> 5.3571429 | L8: ='Facility Master'!O26 -> Bajaj Floating Reference Rate (BFRR) | M8: ='Facility Master'!P26 -> 0.001 | N8: ='Facility Master'!Q26 -> 0.086 | O8: =COUNTIFS('Repayment Schedule'!C134:C186,">"&AsOfDate,'Repayment Schedule'!G134:G186,">0") -> 28 | P8: =TL_22_PRINC_REPAID_TO_DATE -> 0 | Q8: =TL_22_PRINC_OUTSTD -> 150 | R8: 1st p-p on FA at Coke Plant Khurunti; 2nd p-p on CA; MSC 1.25x | S8: DSCR>1.20x; TD/EBITDA<=4.0x; TD/ATNW<2.0x; ICR>=3.5x; FACR>1.25x
B9: Total | E9: =SUM(E6:E8) -> 670.7 | F9: =SUM(F6:F8) -> 670.7 | K9: =SUM(K6:K8) -> 28.847214 | P9: =SUM(P6:P8) -> 50.783688 | Q9: =SUM(Q6:Q8) -> 619.91631

Sheet Non-Fund Based Facilities
B2: NON-FUND BASED FACILITIES
B3: LC, SBLC, BG, Capex LC, Forex hedging / LER. Commission = Sanctioned × Commission Rate (or utilised, if user prefers). NFB facilities do not impact debt balance unless invoked.
B5: # | C5: Lender | D5: Facility | E5: Sub-limit Parent | F5: Sanction (INR Cr) | G5: Utilised (INR Cr) | H5: Available (INR Cr) | I5: Utilisation % | J5: Commission Rate p.a. | K5: Tenor (Months) | L5: Validity Date | M5: Annual Commission Cost (INR Cr) | N5: Security (summary) | O5: Remarks
B6: 1 | C6: ='Facility Master'!C5 -> RBL Bank | D6: ='Facility Master'!D5 -> Letter of Credit - Main Limit | E6: ='Facility Master'!G5 -> Main | F6: ='Facility Master'!J5 -> 100 | G6: ='Facility Master'!L5 -> 100 | H6: ='Facility Master'!N5 -> 0 | I6: ='Facility Master'!M5 -> 1 | J6: ='Facility Master'!Q5 -> 0.0045 | K6: =IFERROR('Facility Master'!U5,0) -> 6 | L6: =IFERROR('Facility Master'!AA5,0) -> 46356 | M6: =IFERROR(F6*J6,0) -> 0.45 | N6: =IFERROR('Facility Master'!AC5,0) -> 1st p-p on current assets; 2nd p-p on FA; Personal guarantee | O6: =IFERROR('Facility Master'!AE5,0) -> Pricing revised from 0.50% to 0.45% on 31-Dec-2025. | Validity rolled +1 year (orig: 2025-11-30) per Assumption #12: annual-renewal WC facilities presumed operationally renewed. Confirm with relationship manager.
B7: 2 | C7: ='Facility Master'!C6 -> RBL Bank | D7: ='Facility Master'!D6 -> Bank Guarantee | E7: ='Facility Master'!G6 -> Sub-limit of LC (Main) | F7: ='Facility Master'!J6 -> 25 | G7: ='Facility Master'!L6 -> 25 | H7: ='Facility Master'!N6 -> 0 | I7: ='Facility Master'!M6 -> 1 | J7: ='Facility Master'!Q6 -> 0.005 | K7: =IFERROR('Facility Master'!U6,0) -> 12 | L7: =IFERROR('Facility Master'!AA6,0) -> 46356 | M7: =IFERROR(F7*J7,0) -> 0.125 | N7: =IFERROR('Facility Master'!AC6,0) -> 1st p-p on current assets; 2nd p-p on FA; Personal guarantee | O7: =IFERROR('Facility Master'!AE6,0) -> Pricing per 28-Feb-2025 table; BG not re-priced on 31-Dec-2025. | Validity rolled +1 year (orig: 2025-11-30) per Assumption #12: annual-renewal WC facilities presumed operationally renewed. Confirm with relationship manager. | ⚠ COMMISSION RATE TBD: Original RBL sanction (25-Nov-2022) specifies 1.00% p.a. for BGs. 31-Dec-2025 renewal does not explicitly revise BG rate downward. 0.50% is inferred from the 28-Feb-2025 pricing table but NOT confirmed in writing by RBL for the renewed sanction. Confirm 0.50% with RBL RM before finalising lender reporting / commission accrual.
B8: 3 | C8: ='Facility Master'!C8 -> RBL Bank | D8: ='Facility Master'!D8 -> SBLC | E8: ='Facility Master'!G8 -> Sub-limit of LC (Main) | F8: ='Facility Master'!J8 -> 100 | G8: ='Facility Master'!L8 -> 100 | H8: ='Facility Master'!N8 -> 0 | I8: ='Facility Master'!M8 -> 1 | J8: ='Facility Master'!Q8 -> 0.005 | K8: =IFERROR('Facility Master'!U8,0) -> 6 | L8: =IFERROR('Facility Master'!AA8,0) -> 46356 | M8: =IFERROR(F8*J8,0) -> 0.5 | N8: =IFERROR('Facility Master'!AC8,0) -> Same as LC | O8: =IFERROR('Facility Master'!AE8,0) -> SBLC sub-limit introduced via 13-Mar-2025 modification. | Validity rolled +1 year (orig: 2025-11-30) per Assumption #12: annual-renewal WC facilities presumed operationally renewed. Confirm with relationship manager. | Commission 0.50% per 28-Feb-2025 pricing, unchanged in 31-Dec-2025 renewal ('all other terms continue'). Earlier 13-Mar-2025 modification said 'TBD at transaction' for this sub-limit but was overridden by 31-Dec-2025 renewal.
B9: 4 | C9: ='Facility Master'!C12 -> RBL Bank | D9: ='Facility Master'!D12 -> Loan Equivalent Risk (LER) | E9: ='Facility Master'!G12 -> Main | F9: ='Facility Master'!J12 -> 20 | G9: ='Facility Master'!L12 -> 20 | H9: ='Facility Master'!N12 -> 0 | I9: ='Facility Master'!M12 -> 1 | J9: ='Facility Master'!Q12 -> 0 | K9: =IFERROR('Facility Master'!U12,0) -> 12 | L9: =IFERROR('Facility Master'!AA12,0) -> 46356 | M9: =IFERROR(F9*J9,0) -> 0 | N9: =IFERROR('Facility Master'!AC12,0) -> Unsecured | O9: =IFERROR('Facility Master'!AE12,0) -> Notional limit; 75% MTM trigger. | Validity rolled +1 year (orig: 2025-11-30) per Assumption #12: annual-renewal WC facilities presumed operationally renewed. Confirm with relationship manager.
B10: 5 | C10: ='Facility Master'!C14 -> RBL Bank | D10: ='Facility Master'!D14 -> SBLC for Buyer's Credit (GIFT City) | E10: ='Facility Master'!G14 -> Main | F10: ='Facility Master'!J14 -> 190 | G10: ='Facility Master'!L14 -> 190 | H10: ='Facility Master'!N14 -> 0 | I10: ='Facility Master'!M14 -> 1 | J10: ='Facility Master'!Q14 -> 0.005 | K10: =IFERROR('Facility Master'!U14,0) -> 36 | L10: =IFERROR('Facility Master'!AA14,0) -> 46356 | M10: =IFERROR(F10*J10,0) -> 0.95 | N10: =IFERROR('Facility Master'!AC14,0) -> 1st p-p on FA; 1st p-p mortgage on immovable; 2nd p-p on CA | O10: =IFERROR('Facility Master'!AE14,0) -> Limit increased 172 -> 190 Cr on 31-Dec-2025. | Validity rolled +1 year (orig: 2025-11-30) per Assumption #12: annual-renewal WC facilities presumed operationally renewed. Confirm with relationship manager.
B11: 6 | C11: ='Facility Master'!C15 -> RBL Bank | D11: ='Facility Master'!D15 -> Capex LC | E11: ='Facility Master'!G15 -> Main | F11: ='Facility Master'!J15 -> 25 | G11: ='Facility Master'!L15 -> 25 | H11: ='Facility Master'!N15 -> 0 | I11: ='Facility Master'!M15 -> 1 | J11: ='Facility Master'!Q15 -> 0.005 | K11: =IFERROR('Facility Master'!U15,0) -> 36 | L11: =IFERROR('Facility Master'!AA15,0) -> 46356 | M11: =IFERROR(F11*J11,0) -> 0.125 | N11: =IFERROR('Facility Master'!AC15,0) -> 1st p-p on FA; 1st p-p mortgage on immovable; 2nd p-p on CA | O11: =IFERROR('Facility Master'!AE15,0) -> Originally 24-Jan-2024; converted revolving 28-Feb-2025. | Validity rolled +1 year (orig: 2025-11-30) per Assumption #12: annual-renewal WC facilities presumed operationally renewed. Confirm with relationship manager. | Commission TBD at disbursement per sanction letter. FD-backed LC typically carries nil-to-very-low commission (lender's own-FD collateral). Model shows 0.
B12: 7 | C12: ='Facility Master'!C17 -> RBL Bank | D12: ='Facility Master'!D17 -> LC backed by 100% FD | E12: ='Facility Master'!G17 -> Sub-limit of FDOD | F12: ='Facility Master'!J17 -> 50 | G12: ='Facility Master'!L17 -> 50 | H12: ='Facility Master'!N17 -> 0 | I12: ='Facility Master'!M17 -> 1 | J12: ='Facility Master'!Q17 -> 0 | K12: =IFERROR('Facility Master'!U17,0) -> 12 | L12: =IFERROR('Facility Master'!AA17,0) -> 46356 | M12: =IFERROR(F12*J12,0) -> 0 | N12: =IFERROR('Facility Master'!AC17,0) -> Exclusive charge on FD = 100% of facility | O12: =IFERROR('Facility Master'!AE17,0) -> Rate not specified in sanction letter. | Validity rolled +1 year (orig: 2025-11-30) per Assumption #12: annual-renewal WC facilities presumed operationally renewed. Confirm with relationship manager.
B13: 8 | C13: ='Facility Master'!C22 -> YES Bank | D13: ='Facility Master'!D22 -> Letter of Credit | E13: ='Facility Master'!G22 -> Main | F13: ='Facility Master'!J22 -> 200 | G13: ='Facility Master'!L22 -> 200 | H13: ='Facility Master'!N22 -> 0 | I13: ='Facility Master'!M22 -> 1 | J13: ='Facility Master'!Q22 -> 0 | K13: =IFERROR('Facility Master'!U22,0) -> 7 | L13: =IFERROR('Facility Master'!AA22,0) -> 46472 | M13: =IFERROR(F13*J13,0) -> 0 | N13: =IFERROR('Facility Master'!AC22,0) -> 1st p-p on CA; mortgage on Faridabad property; 2nd p-p on FA; PG | O13: =IFERROR('Facility Master'!AE22,0) -> Overall WC cap INR 200 Cr net of receivable finance (INR 1 Cr). | Validity rolled +1 year (orig: 2026-03-26) per Assumption #12: annual-renewal WC facilities presumed operationally renewed. Confirm with relationship manager.
B14: 9 | C14: ='Facility Master'!C23 -> YES Bank | D14: ='Facility Master'!D23 -> Financial BG / SBLC | E14: ='Facility Master'!G23 -> Sub-limit of LC (Main) | F14: ='Facility Master'!J23 -> 200 | G14: ='Facility Master'!L23 -> 200 | H14: ='Facility Master'!N23 -> 0 | I14: ='Facility Master'!M23 -> 1 | J14: ='Facility Master'!Q23 -> 0.005 | K14: =IFERROR('Facility Master'!U23,0) -> 6 | L14: =IFERROR('Facility Master'!AA23,0) -> Per renewal cycle | M14: =IFERROR(F14*J14,0) -> 1 | N14: =IFERROR('Facility Master'!AC23,0) -> 1st p-p on CA; mortgage on Faridabad property; 2nd p-p on FA; PG | O14: =IFERROR('Facility Master'!AE23,0) -> Commission cut 25 bps on 19-Mar-2026.
B15: 10 | C15: ='Facility Master'!C29 -> ICICI Bank | D15: ='Facility Master'!D29 -> Letter of Credit (Inland/Foreign) | E15: ='Facility Master'!G29 -> Main | F15: ='Facility Master'!J29 -> 150 | G15: ='Facility Master'!L29 -> 150 | H15: ='Facility Master'!N29 -> 0 | I15: ='Facility Master'!M29 -> 1 | J15: ='Facility Master'!Q29 -> 0.005 | K15: =IFERROR('Facility Master'!U29,0) -> 5 | L15: =IFERROR('Facility Master'!AA29,0) -> 46268 | M15: =IFERROR(F15*J15,0) -> 0.75 | N15: =IFERROR('Facility Master'!AC29,0) -> 1st p-p on CA; 2nd p-p on FA; 2nd p-p mortgage Kalinga Nagar | O15: =IFERROR('Facility Master'!AE29,0) -> LC to JSL Global Commodities Pte Ltd capped at INR 25 Cr.
B16: 11 | C16: ='Facility Master'!C30 -> ICICI Bank | D16: ='Facility Master'!D30 -> SBLC for Buyers' Credit | E16: ='Facility Master'!G30 -> Sub-limit of LC | F16: ='Facility Master'!J30 -> 150 | G16: ='Facility Master'!L30 -> 150 | H16: ='Facility Master'!N30 -> 0 | I16: ='Facility Master'!M30 -> 1 | J16: ='Facility Master'!Q30 -> 0.005 | K16: =IFERROR('Facility Master'!U30,0) -> 5 | L16: =IFERROR('Facility Master'!AA30,0) -> 46268 | M16: =IFERROR(F16*J16,0) -> 0.75 | N16: =IFERROR('Facility Master'!AC30,0) -> 1st p-p on CA; 2nd p-p on FA; 2nd p-p mortgage Kalinga Nagar | O16: =IFERROR('Facility Master'!AE30,0) -> Excluded from DP; no rollover beyond RBI guidelines.
B17: 12 | C17: ='Facility Master'!C31 -> ICICI Bank | D17: ='Facility Master'!D31 -> Bank Guarantee - Performance | E17: ='Facility Master'!G31 -> Sub-limit of LC | F17: ='Facility Master'!J31 -> 25 | G17: ='Facility Master'!L31 -> 25 | H17: ='Facility Master'!N31 -> 0 | I17: ='Facility Master'!M31 -> 1 | J17: ='Facility Master'!Q31 -> 0.005 | K17: =IFERROR('Facility Master'!U31,0) -> 36 | L17: =IFERROR('Facility Master'!AA31,0) -> 46268 | M17: =IFERROR(F17*J17,0) -> 0.125 | N17: =IFERROR('Facility Master'!AC31,0) -> 1st p-p on CA; 2nd p-p on FA; 2nd p-p mortgage Kalinga Nagar | O17: =IFERROR('Facility Master'!AE31,0) -> SWIFT INR 1,000/BG; min commission INR 500/BG.
B18: 13 | C18: ='Facility Master'!C32 -> ICICI Bank | D18: ='Facility Master'!D32 -> Bank Guarantee - Financial | E18: ='Facility Master'!G32 -> Sub-limit of LC | F18: ='Facility Master'!J32 -> 5 | G18: ='Facility Master'!L32 -> 5 | H18: ='Facility Master'!N32 -> 0 | I18: ='Facility Master'!M32 -> 1 | J18: ='Facility Master'!Q32 -> 0.006 | K18: =IFERROR('Facility Master'!U32,0) -> 36 | L18: =IFERROR('Facility Master'!AA32,0) -> 46268 | M18: =IFERROR(F18*J18,0) -> 0.03 | N18: =IFERROR('Facility Master'!AC32,0) -> 1st p-p on CA; 2nd p-p on FA; 2nd p-p mortgage Kalinga Nagar | O18: =IFERROR('Facility Master'!AE32,0) -> INR 50 mn per sanction letter.
B19: 14 | C19: ='Facility Master'!C35 -> South Indian Bank | D19: ='Facility Master'!D35 -> Inland / Import LC | E19: ='Facility Master'!G35 -> Main | F19: ='Facility Master'!J35 -> 150 | G19: ='Facility Master'!L35 -> 150 | H19: ='Facility Master'!N35 -> 0 | I19: ='Facility Master'!M35 -> 1 | J19: ='Facility Master'!Q35 -> 0.0065 | K19: =IFERROR('Facility Master'!U35,0) -> 6 | L19: =IFERROR('Facility Master'!AA35,0) -> Annual renewal | M19: =IFERROR(F19*J19,0) -> 0.975 | N19: =IFERROR('Facility Master'!AC35,0) -> 1st p-p on CA; 2nd p-p on FA; 2nd p-p mortgage Kalinga Nagar | O19: =IFERROR('Facility Master'!AE35,0) -> Total LC + Capex LC <= INR 150 Cr.
B20: 15 | C20: ='Facility Master'!C36 -> South Indian Bank | D20: ='Facility Master'!D36 -> Capex LC | E20: ='Facility Master'!G36 -> Main (within LC umbrella) | F20: ='Facility Master'!J36 -> 50 | G20: ='Facility Master'!L36 -> 50 | H20: ='Facility Master'!N36 -> 0 | I20: ='Facility Master'!M36 -> 1 | J20: ='Facility Master'!Q36 -> 0.0075 | K20: =IFERROR('Facility Master'!U36,0) -> 12 | L20: =IFERROR('Facility Master'!AA36,0) -> Annual renewal | M20: =IFERROR(F20*J20,0) -> 0.375 | N20: =IFERROR('Facility Master'!AC36,0) -> 1st p-p on CA; 2nd p-p on FA; 2nd p-p mortgage Kalinga Nagar | O20: =IFERROR('Facility Master'!AE36,0) -> Combined with Inland/Import LC limit.
B21: 16 | C21: ='Facility Master'!C37 -> South Indian Bank | D21: ='Facility Master'!D37 -> SBLC | E21: ='Facility Master'!G37 -> Sub-limit of LC | F21: ='Facility Master'!J37 -> 150 | G21: ='Facility Master'!L37 -> 150 | H21: ='Facility Master'!N37 -> 0 | I21: ='Facility Master'!M37 -> 1 | J21: ='Facility Master'!Q37 -> 0.0065 | K21: =IFERROR('Facility Master'!U37,0) -> 4 | L21: =IFERROR('Facility Master'!AA37,0) -> Annual renewal | M21: =IFERROR(F21*J21,0) -> 0.975 | N21: =IFERROR('Facility Master'!AC37,0) -> 1st p-p on CA; 2nd p-p on FA; 2nd p-p mortgage Kalinga Nagar | O21: =IFERROR('Facility Master'!AE37,0) -> No rollover. BC all-in-cost: Benchmark + 300 bps cap.
B22: 17 | C22: ='Facility Master'!C38 -> South Indian Bank | D22: ='Facility Master'!D38 -> Forward Contract Limit | E22: ='Facility Master'!G38 -> Main | F22: ='Facility Master'!J38 -> 3 | G22: ='Facility Master'!L38 -> 3 | H22: ='Facility Master'!N38 -> 0 | I22: ='Facility Master'!M38 -> 1 | J22: ='Facility Master'!Q38 -> 0 | K22: =IFERROR('Facility Master'!U38,0) -> 12 | L22: =IFERROR('Facility Master'!AA38,0) -> Annual renewal | M22: =IFERROR(F22*J22,0) -> 0 | N22: =IFERROR('Facility Master'!AC38,0) -> N/A | O22: =IFERROR('Facility Master'!AE38,0) -> Notional limit; no cash outflow unless settled.
B23: Total | F23: =SUM(F6:F22) -> 1593 | G23: =SUM(G6:G22) -> 1593 | H23: =SUM(H6:H22) -> 0 | I23: =IFERROR(G23/F23,0) -> 1 | M23: =IFERROR(SUM(M6:M22),0) -> 7.13

Sheet Repayment Schedule
B2: REPAYMENT SCHEDULE - Term Loans (Quarterly)
B3: Quarterly schedule for each term loan covering the full contractual tenor. Principal amount is Sanctioned ÷ Number of Instalments (EQI), applied from Repayment Start Date. Interest = Opening × Rate × (Days / 365). Consolidated section at the bottom sums across all TLs.
B5: 1) RBL Bank — Term Loan - Main Limit (200 INR Cr) — S.No. 9
B6: Sanctioned (INR Cr) | C6: Drawdown | D6: Moratorium (m) | E6: Rep. Start | F6: Maturity | G6: # Instalments | H6: Qtr Instalment | I6: Eff. Rate (p.a.)
B7: ='Facility Master'!J13 -> 200 | C7: ='Facility Master'!W13 -> 45315 | D7: ='Facility Master'!S13 -> 24 | E7: ='Facility Master'!X13 -> 46046 | F7: ='Facility Master'!Y13 -> 47142 | G7: ='Facility Master'!V13 -> 12 | H7: ='Facility Master'!J13/'Facility Master'!V13 -> 16.666667 | I7: ='Facility Master'!Q13 -> 0.0975
B9: # | C9: Period End | D9: Period Label | E9: Opening Balance | F9: Drawdown | G9: Principal Repayment | H9: Closing Balance | I9: Interest Rate | J9: Days | K9: Interest Expense | L9: Total Debt Service
B10: 1 | C10: 45382 | D10: Q4 FY24 | E10: 0 | F10: =IF(C10>='Facility Master'!W13,'Facility Master'!J13,0) -> 200 | G10: =IFERROR(IF(AND('Facility Master'!X13<>"-",C10>='Facility Master'!X13,C10<='Facility Master'!Y13),MIN(E10+F10,'Facility Master'!J13/'Facility Master'!V13),0),0) -> 0 | H10: =E10+F10-G10 -> 200 | I10: ='Facility Master'!Q13 -> 0.0975 | J10: =IF(AND(E10=0,F10=0),0,IF('Facility Master'!W13>=C10,0,C10-MAX('Facility Master'!W13,EDATE(C10,-3)))) -> 67 | K10: =IFERROR(E10*I10*J10/DaysInYear,0) -> 0 | L10: =G10+K10 -> 0
B11: 2 | C11: 45473 | D11: Q1 FY25 | E11: =H10 -> 200 | F11: =IF(AND('Facility Master'!W13>C10,'Facility Master'!W13<=C11),'Facility Master'!J13,0) -> 0 | G11: =IFERROR(IF(AND('Facility Master'!X13<>"-",C11>='Facility Master'!X13,C11<='Facility Master'!Y13),MIN(E11+F11,'Facility Master'!J13/'Facility Master'!V13),0),0) -> 0 | H11: =E11+F11-G11 -> 200 | I11: ='Facility Master'!Q13 -> 0.0975 | J11: =C11-C10 -> 91 | K11: =IFERROR(E11*I11*J11/DaysInYear,0) -> 4.8616438 | L11: =G11+K11 -> 4.8616438
B12: 3 | C12: 45565 | D12: Q2 FY25 | E12: =H11 -> 200 | F12: =IF(AND('Facility Master'!W13>C11,'Facility Master'!W13<=C12),'Facility Master'!J13,0) -> 0 | G12: =IFERROR(IF(AND('Facility Master'!X13<>"-",C12>='Facility Master'!X13,C12<='Facility Master'!Y13),MIN(E12+F12,'Facility Master'!J13/'Facility Master'!V13),0),0) -> 0 | H12: =E12+F12-G12 -> 200 | I12: ='Facility Master'!Q13 -> 0.0975 | J12: =C12-C11 -> 92 | K12: =IFERROR(E12*I12*J12/DaysInYear,0) -> 4.9150685 | L12: =G12+K12 -> 4.9150685
B13: 4 | C13: 45657 | D13: Q3 FY25 | E13: =H12 -> 200 | F13: =IF(AND('Facility Master'!W13>C12,'Facility Master'!W13<=C13),'Facility Master'!J13,0) -> 0 | G13: =IFERROR(IF(AND('Facility Master'!X13<>"-",C13>='Facility Master'!X13,C13<='Facility Master'!Y13),MIN(E13+F13,'Facility Master'!J13/'Facility Master'!V13),0),0) -> 0 | H13: =E13+F13-G13 -> 200 | I13: ='Facility Master'!Q13 -> 0.0975 | J13: =C13-C12 -> 92 | K13: =IFERROR(E13*I13*J13/DaysInYear,0) -> 4.9150685 | L13: =G13+K13 -> 4.9150685
B14: 5 | C14: 45747 | D14: Q4 FY25 | E14: =H13 -> 200 | F14: =IF(AND('Facility Master'!W13>C13,'Facility Master'!W13<=C14),'Facility Master'!J13,0) -> 0 | G14: =IFERROR(IF(AND('Facility Master'!X13<>"-",C14>='Facility Master'!X13,C14<='Facility Master'!Y13),MIN(E14+F14,'Facility Master'!J13/'Facility Master'!V13),0),0) -> 0 | H14: =E14+F14-G14 -> 200 | I14: ='Facility Master'!Q13 -> 0.0975 | J14: =C14-C13 -> 90 | K14: =IFERROR(E14*I14*J14/DaysInYear,0) -> 4.8082192 | L14: =G14+K14 -> 4.8082192
B15: 6 | C15: 45838 | D15: Q1 FY26 | E15: =H14 -> 200 | F15: =IF(AND('Facility Master'!W13>C14,'Facility Master'!W13<=C15),'Facility Master'!J13,0) -> 0 | G15: =IFERROR(IF(AND('Facility Master'!X13<>"-",C15>='Facility Master'!X13,C15<='Facility Master'!Y13),MIN(E15+F15,'Facility Master'!J13/'Facility Master'!V13),0),0) -> 0 | H15: =E15+F15-G15 -> 200 | I15: ='Facility Master'!Q13 -> 0.0975 | J15: =C15-C14 -> 91 | K15: =IFERROR(E15*I15*J15/DaysInYear,0) -> 4.8616438 | L15: =G15+K15 -> 4.8616438
B16: 7 | C16: 45930 | D16: Q2 FY26 | E16: =H15 -> 200 | F16: =IF(AND('Facility Master'!W13>C15,'Facility Master'!W13<=C16),'Facility Master'!J13,0) -> 0 | G16: =IFERROR(IF(AND('Facility Master'!X13<>"-",C16>='Facility Master'!X13,C16<='Facility Master'!Y13),MIN(E16+F16,'Facility Master'!J13/'Facility Master'!V13),0),0) -> 0 | H16: =E16+F16-G16 -> 200 | I16: ='Facility Master'!Q13 -> 0.0975 | J16: =C16-C15 -> 92 | K16: =IFERROR(E16*I16*J16/DaysInYear,0) -> 4.9150685 | L16: =G16+K16 -> 4.9150685
B17: 8 | C17: 46022 | D17: Q3 FY26 | E17: =H16 -> 200 | F17: =IF(AND('Facility Master'!W13>C16,'Facility Master'!W13<=C17),'Facility Master'!J13,0) -> 0 | G17: =IFERROR(IF(AND('Facility Master'!X13<>"-",C17>='Facility Master'!X13,C17<='Facility Master'!Y13),MIN(E17+F17,'Facility Master'!J13/'Facility Master'!V13),0),0) -> 0 | H17: =E17+F17-G17 -> 200 | I17: ='Facility Master'!Q13 -> 0.0975 | J17: =C17-C16 -> 92 | K17: =IFERROR(E17*I17*J17/DaysInYear,0) -> 4.9150685 | L17: =G17+K17 -> 4.9150685
B18: 9 | C18: 46112 | D18: Q4 FY26 | E18: =H17 -> 200 | F18: =IF(AND('Facility Master'!W13>C17,'Facility Master'!W13<=C18),'Facility Master'!J13,0) -> 0 | G18: =IFERROR(IF(AND('Facility Master'!X13<>"-",C18>='Facility Master'!X13,C18<='Facility Master'!Y13),MIN(E18+F18,'Facility Master'!J13/'Facility Master'!V13),0),0) -> 16.666667 | H18: =E18+F18-G18 -> 183.33333 | I18: ='Facility Master'!Q13 -> 0.0975 | J18: =C18-C17 -> 90 | K18: =IFERROR(E18*I18*J18/DaysInYear,0) -> 4.8082192 | L18: =G18+K18 -> 21.474886
B19: 10 | C19: 46203 | D19: Q1 FY27 | E19: =H18 -> 183.33333 | F19: =IF(AND('Facility Master'!W13>C18,'Facility Master'!W13<=C19),'Facility Master'!J13,0) -> 0 | G19: =IFERROR(IF(AND('Facility Master'!X13<>"-",C19>='Facility Master'!X13,C19<='Facility Master'!Y13),MIN(E19+F19,'Facility Master'!J13/'Facility Master'!V13),0),0) -> 16.666667 | H19: =E19+F19-G19 -> 166.66667 | I19: ='Facility Master'!Q13 -> 0.0975 | J19: =C19-C18 -> 91 | K19: =IFERROR(E19*I19*J19/DaysInYear,0) -> 4.4565068 | L19: =G19+K19 -> 21.123174
B20: 11 | C20: 46295 | D20: Q2 FY27 | E20: =H19 -> 166.66667 | F20: =IF(AND('Facility Master'!W13>C19,'Facility Master'!W13<=C20),'Facility Master'!J13,0) -> 0 | G20: =IFERROR(IF(AND('Facility Master'!X13<>"-",C20>='Facility Master'!X13,C20<='Facility Master'!Y13),MIN(E20+F20,'Facility Master'!J13/'Facility Master'!V13),0),0) -> 16.666667 | H20: =E20+F20-G20 -> 150 | I20: ='Facility Master'!Q13 -> 0.0975 | J20: =C20-C19 -> 92 | K20: =IFERROR(E20*I20*J20/DaysInYear,0) -> 4.0958904 | L20: =G20+K20 -> 20.762557
B21: 12 | C21: 46387 | D21: Q3 FY27 | E21: =H20 -> 150 | F21: =IF(AND('Facility Master'!W13>C20,'Facility Master'!W13<=C21),'Facility Master'!J13,0) -> 0 | G21: =IFERROR(IF(AND('Facility Master'!X13<>"-",C21>='Facility Master'!X13,C21<='Facility Master'!Y13),MIN(E21+F21,'Facility Master'!J13/'Facility Master'!V13),0),0) -> 16.666667 | H21: =E21+F21-G21 -> 133.33333 | I21: ='Facility Master'!Q13 -> 0.0975 | J21: =C21-C20 -> 92 | K21: =IFERROR(E21*I21*J21/DaysInYear,0) -> 3.6863014 | L21: =G21+K21 -> 20.352968
B22: 13 | C22: 46477 | D22: Q4 FY27 | E22: =H21 -> 133.33333 | F22: =IF(AND('Facility Master'!W13>C21,'Facility Master'!W13<=C22),'Facility Master'!J13,0) -> 0 | G22: =IFERROR(IF(AND('Facility Master'!X13<>"-",C22>='Facility Master'!X13,C22<='Facility Master'!Y13),MIN(E22+F22,'Facility Master'!J13/'Facility Master'!V13),0),0) -> 16.666667 | H22: =E22+F22-G22 -> 116.66667 | I22: ='Facility Master'!Q13 -> 0.0975 | J22: =C22-C21 -> 90 | K22: =IFERROR(E22*I22*J22/DaysInYear,0) -> 3.2054795 | L22: =G22+K22 -> 19.872146
B23: 14 | C23: 46568 | D23: Q1 FY28 | E23: =H22 -> 116.66667 | F23: =IF(AND('Facility Master'!W13>C22,'Facility Master'!W13<=C23),'Facility Master'!J13,0) -> 0 | G23: =IFERROR(IF(AND('Facility Master'!X13<>"-",C23>='Facility Master'!X13,C23<='Facility Master'!Y13),MIN(E23+F23,'Facility Master'!J13/'Facility Master'!V13),0),0) -> 16.666667 | H23: =E23+F23-G23 -> 100 | I23: ='Facility Master'!Q13 -> 0.0975 | J23: =C23-C22 -> 91 | K23: =IFERROR(E23*I23*J23/DaysInYear,0) -> 2.8359589 | L23: =G23+K23 -> 19.502626
B24: 15 | C24: 46660 | D24: Q2 FY28 | E24: =H23 -> 100 | F24: =IF(AND('Facility Master'!W13>C23,'Facility Master'!W13<=C24),'Facility Master'!J13,0) -> 0 | G24: =IFERROR(IF(AND('Facility Master'!X13<>"-",C24>='Facility Master'!X13,C24<='Facility Master'!Y13),MIN(E24+F24,'Facility Master'!J13/'Facility Master'!V13),0),0) -> 16.666667 | H24: =E24+F24-G24 -> 83.333333 | I24: ='Facility Master'!Q13 -> 0.0975 | J24: =C24-C23 -> 92 | K24: =IFERROR(E24*I24*J24/DaysInYear,0) -> 2.4575342 | L24: =G24+K24 -> 19.124201
B25: 16 | C25: 46752 | D25: Q3 FY28 | E25: =H24 -> 83.333333 | F25: =IF(AND('Facility Master'!W13>C24,'Facility Master'!W13<=C25),'Facility Master'!J13,0) -> 0 | G25: =IFERROR(IF(AND('Facility Master'!X13<>"-",C25>='Facility Master'!X13,C25<='Facility Master'!Y13),MIN(E25+F25,'Facility Master'!J13/'Facility Master'!V13),0),0) -> 16.666667 | H25: =E25+F25-G25 -> 66.666667 | I25: ='Facility Master'!Q13 -> 0.0975 | J25: =C25-C24 -> 92 | K25: =IFERROR(E25*I25*J25/DaysInYear,0) -> 2.0479452 | L25: =G25+K25 -> 18.714612
B26: 17 | C26: 46843 | D26: Q4 FY28 | E26: =H25 -> 66.666667 | F26: =IF(AND('Facility Master'!W13>C25,'Facility Master'!W13<=C26),'Facility Master'!J13,0) -> 0 | G26: =IFERROR(IF(AND('Facility Master'!X13<>"-",C26>='Facility Master'!X13,C26<='Facility Master'!Y13),MIN(E26+F26,'Facility Master'!J13/'Facility Master'!V13),0),0) -> 16.666667 | H26: =E26+F26-G26 -> 50 | I26: ='Facility Master'!Q13 -> 0.0975 | J26: =C26-C25 -> 91 | K26: =IFERROR(E26*I26*J26/DaysInYear,0) -> 1.6205479 | L26: =G26+K26 -> 18.287215
B27: 18 | C27: 46934 | D27: Q1 FY29 | E27: =H26 -> 50 | F27: =IF(AND('Facility Master'!W13>C26,'Facility Master'!W13<=C27),'Facility Master'!J13,0) -> 0 | G27: =IFERROR(IF(AND('Facility Master'!X13<>"-",C27>='Facility Master'!X13,C27<='Facility Master'!Y13),MIN(E27+F27,'Facility Master'!J13/'Facility Master'!V13),0),0) -> 16.666667 | H27: =E27+F27-G27 -> 33.333333 | I27: ='Facility Master'!Q13 -> 0.0975 | J27: =C27-C26 -> 91 | K27: =IFERROR(E27*I27*J27/DaysInYear,0) -> 1.215411 | L27: =G27+K27 -> 17.882078
B28: 19 | C28: 47026 | D28: Q2 FY29 | E28: =H27 -> 33.333333 | F28: =IF(AND('Facility Master'!W13>C27,'Facility Master'!W13<=C28),'Facility Master'!J13,0) -> 0 | G28: =IFERROR(IF(AND('Facility Master'!X13<>"-",C28>='Facility Master'!X13,C28<='Facility Master'!Y13),MIN(E28+F28,'Facility Master'!J13/'Facility Master'!V13),0),0) -> 16.666667 | H28: =E28+F28-G28 -> 16.666667 | I28: ='Facility Master'!Q13 -> 0.0975 | J28: =C28-C27 -> 92 | K28: =IFERROR(E28*I28*J28/DaysInYear,0) -> 0.81917808 | L28: =G28+K28 -> 17.485845
B29: 20 | C29: 47118 | D29: Q3 FY29 | E29: =H28 -> 16.666667 | F29: =IF(AND('Facility Master'!W13>C28,'Facility Master'!W13<=C29),'Facility Master'!J13,0) -> 0 | G29: =IFERROR(IF(AND('Facility Master'!X13<>"-",C29>='Facility Master'!X13,C29<='Facility Master'!Y13),MIN(E29+F29,'Facility Master'!J13/'Facility Master'!V13),0),0) -> 16.666667 | H29: =E29+F29-G29 -> 0 | I29: ='Facility Master'!Q13 -> 0.0975 | J29: =C29-C28 -> 92 | K29: =IFERROR(E29*I29*J29/DaysInYear,0) -> 0.40958904 | L29: =G29+K29 -> 17.076256
B30: 21 | C30: 47208 | D30: Q4 FY29 | E30: =H29 -> 0 | F30: =IF(AND('Facility Master'!W13>C29,'Facility Master'!W13<=C30),'Facility Master'!J13,0) -> 0 | G30: =IFERROR(IF(AND('Facility Master'!X13<>"-",C30>='Facility Master'!X13,C30<='Facility Master'!Y13),MIN(E30+F30,'Facility Master'!J13/'Facility Master'!V13),0),0) -> 0 | H30: =E30+F30-G30 -> 0 | I30: ='Facility Master'!Q13 -> 0.0975 | J30: =C30-C29 -> 90 | K30: =IFERROR(E30*I30*J30/DaysInYear,0) -> 0 | L30: =G30+K30 -> 0
B31: 22 | C31: 47299 | D31: Q1 FY30 | E31: =H30 -> 0 | F31: =IF(AND('Facility Master'!W13>C30,'Facility Master'!W13<=C31),'Facility Master'!J13,0) -> 0 | G31: =IFERROR(IF(AND('Facility Master'!X13<>"-",C31>='Facility Master'!X13,C31<='Facility Master'!Y13),MIN(E31+F31,'Facility Master'!J13/'Facility Master'!V13),0),0) -> 0 | H31: =E31+F31-G31 -> 0 | I31: ='Facility Master'!Q13 -> 0.0975 | J31: =C31-C30 -> 91 | K31: =IFERROR(E31*I31*J31/DaysInYear,0) -> 0 | L31: =G31+K31 -> 0
B32: 23 | C32: 47391 | D32: Q2 FY30 | E32: =H31 -> 0 | F32: =IF(AND('Facility Master'!W13>C31,'Facility Master'!W13<=C32),'Facility Master'!J13,0) -> 0 | G32: =IFERROR(IF(AND('Facility Master'!X13<>"-",C32>='Facility Master'!X13,C32<='Facility Master'!Y13),MIN(E32+F32,'Facility Master'!J13/'Facility Master'!V13),0),0) -> 0 | H32: =E32+F32-G32 -> 0 | I32: ='Facility Master'!Q13 -> 0.0975 | J32: =C32-C31 -> 92 | K32: =IFERROR(E32*I32*J32/DaysInYear,0) -> 0 | L32: =G32+K32 -> 0
B33: 24 | C33: 47483 | D33: Q3 FY30 | E33: =H32 -> 0 | F33: =IF(AND('Facility Master'!W13>C32,'Facility Master'!W13<=C33),'Facility Master'!J13,0) -> 0 | G33: =IFERROR(IF(AND('Facility Master'!X13<>"-",C33>='Facility Master'!X13,C33<='Facility Master'!Y13),MIN(E33+F33,'Facility Master'!J13/'Facility Master'!V13),0),0) -> 0 | H33: =E33+F33-G33 -> 0 | I33: ='Facility Master'!Q13 -> 0.0975 | J33: =C33-C32 -> 92 | K33: =IFERROR(E33*I33*J33/DaysInYear,0) -> 0 | L33: =G33+K33 -> 0
B34: 25 | C34: 47573 | D34: Q4 FY30 | E34: =H33 -> 0 | F34: =IF(AND('Facility Master'!W13>C33,'Facility Master'!W13<=C34),'Facility Master'!J13,0) -> 0 | G34: =IFERROR(IF(AND('Facility Master'!X13<>"-",C34>='Facility Master'!X13,C34<='Facility Master'!Y13),MIN(E34+F34,'Facility Master'!J13/'Facility Master'!V13),0),0) -> 0 | H34: =E34+F34-G34 -> 0 | I34: ='Facility Master'!Q13 -> 0.0975 | J34: =C34-C33 -> 90 | K34: =IFERROR(E34*I34*J34/DaysInYear,0) -> 0 | L34: =G34+K34 -> 0
B35: 26 | C35: 47664 | D35: Q1 FY31 | E35: =H34 -> 0 | F35: =IF(AND('Facility Master'!W13>C34,'Facility Master'!W13<=C35),'Facility Master'!J13,0) -> 0 | G35: =IFERROR(IF(AND('Facility Master'!X13<>"-",C35>='Facility Master'!X13,C35<='Facility Master'!Y13),MIN(E35+F35,'Facility Master'!J13/'Facility Master'!V13),0),0) -> 0 | H35: =E35+F35-G35 -> 0 | I35: ='Facility Master'!Q13 -> 0.0975 | J35: =C35-C34 -> 91 | K35: =IFERROR(E35*I35*J35/DaysInYear,0) -> 0 | L35: =G35+K35 -> 0
B36: 27 | C36: 47756 | D36: Q2 FY31 | E36: =H35 -> 0 | F36: =IF(AND('Facility Master'!W13>C35,'Facility Master'!W13<=C36),'Facility Master'!J13,0) -> 0 | G36: =IFERROR(IF(AND('Facility Master'!X13<>"-",C36>='Facility Master'!X13,C36<='Facility Master'!Y13),MIN(E36+F36,'Facility Master'!J13/'Facility Master'!V13),0),0) -> 0 | H36: =E36+F36-G36 -> 0 | I36: ='Facility Master'!Q13 -> 0.0975 | J36: =C36-C35 -> 92 | K36: =IFERROR(E36*I36*J36/DaysInYear,0) -> 0 | L36: =G36+K36 -> 0
B37: 28 | C37: 47848 | D37: Q3 FY31 | E37: =H36 -> 0 | F37: =IF(AND('Facility Master'!W13>C36,'Facility Master'!W13<=C37),'Facility Master'!J13,0) -> 0 | G37: =IFERROR(IF(AND('Facility Master'!X13<>"-",C37>='Facility Master'!X13,C37<='Facility Master'!Y13),MIN(E37+F37,'Facility Master'!J13/'Facility Master'!V13),0),0) -> 0 | H37: =E37+F37-G37 -> 0 | I37: ='Facility Master'!Q13 -> 0.0975 | J37: =C37-C36 -> 92 | K37: =IFERROR(E37*I37*J37/DaysInYear,0) -> 0 | L37: =G37+K37 -> 0
B38: 29 | C38: 47938 | D38: Q4 FY31 | E38: =H37 -> 0 | F38: =IF(AND('Facility Master'!W13>C37,'Facility Master'!W13<=C38),'Facility Master'!J13,0) -> 0 | G38: =IFERROR(IF(AND('Facility Master'!X13<>"-",C38>='Facility Master'!X13,C38<='Facility Master'!Y13),MIN(E38+F38,'Facility Master'!J13/'Facility Master'!V13),0),0) -> 0 | H38: =E38+F38-G38 -> 0 | I38: ='Facility Master'!Q13 -> 0.0975 | J38: =C38-C37 -> 90 | K38: =IFERROR(E38*I38*J38/DaysInYear,0) -> 0 | L38: =G38+K38 -> 0
B39: 30 | C39: 48029 | D39: Q1 FY32 | E39: =H38 -> 0 | F39: =IF(AND('Facility Master'!W13>C38,'Facility Master'!W13<=C39),'Facility Master'!J13,0) -> 0 | G39: =IFERROR(IF(AND('Facility Master'!X13<>"-",C39>='Facility Master'!X13,C39<='Facility Master'!Y13),MIN(E39+F39,'Facility Master'!J13/'Facility Master'!V13),0),0) -> 0 | H39: =E39+F39-G39 -> 0 | I39: ='Facility Master'!Q13 -> 0.0975 | J39: =C39-C38 -> 91 | K39: =IFERROR(E39*I39*J39/DaysInYear,0) -> 0 | L39: =G39+K39 -> 0
B40: 31 | C40: 48121 | D40: Q2 FY32 | E40: =H39 -> 0 | F40: =IF(AND('Facility Master'!W13>C39,'Facility Master'!W13<=C40),'Facility Master'!J13,0) -> 0 | G40: =IFERROR(IF(AND('Facility Master'!X13<>"-",C40>='Facility Master'!X13,C40<='Facility Master'!Y13),MIN(E40+F40,'Facility Master'!J13/'Facility Master'!V13),0),0) -> 0 | H40: =E40+F40-G40 -> 0 | I40: ='Facility Master'!Q13 -> 0.0975 | J40: =C40-C39 -> 92 | K40: =IFERROR(E40*I40*J40/DaysInYear,0) -> 0 | L40: =G40+K40 -> 0
B41: 32 | C41: 48213 | D41: Q3 FY32 | E41: =H40 -> 0 | F41: =IF(AND('Facility Master'!W13>C40,'Facility Master'!W13<=C41),'Facility Master'!J13,0) -> 0 | G41: =IFERROR(IF(AND('Facility Master'!X13<>"-",C41>='Facility Master'!X13,C41<='Facility Master'!Y13),MIN(E41+F41,'Facility Master'!J13/'Facility Master'!V13),0),0) -> 0 | H41: =E41+F41-G41 -> 0 | I41: ='Facility Master'!Q13 -> 0.0975 | J41: =C41-C40 -> 92 | K41: =IFERROR(E41*I41*J41/DaysInYear,0) -> 0 | L41: =G41+K41 -> 0
B42: 33 | C42: 48304 | D42: Q4 FY32 | E42: =H41 -> 0 | F42: =IF(AND('Facility Master'!W13>C41,'Facility Master'!W13<=C42),'Facility Master'!J13,0) -> 0 | G42: =IFERROR(IF(AND('Facility Master'!X13<>"-",C42>='Facility Master'!X13,C42<='Facility Master'!Y13),MIN(E42+F42,'Facility Master'!J13/'Facility Master'!V13),0),0) -> 0 | H42: =E42+F42-G42 -> 0 | I42: ='Facility Master'!Q13 -> 0.0975 | J42: =C42-C41 -> 91 | K42: =IFERROR(E42*I42*J42/DaysInYear,0) -> 0 | L42: =G42+K42 -> 0
B43: 34 | C43: 48395 | D43: Q1 FY33 | E43: =H42 -> 0 | F43: =IF(AND('Facility Master'!W13>C42,'Facility Master'!W13<=C43),'Facility Master'!J13,0) -> 0 | G43: =IFERROR(IF(AND('Facility Master'!X13<>"-",C43>='Facility Master'!X13,C43<='Facility Master'!Y13),MIN(E43+F43,'Facility Master'!J13/'Facility Master'!V13),0),0) -> 0 | H43: =E43+F43-G43 -> 0 | I43: ='Facility Master'!Q13 -> 0.0975 | J43: =C43-C42 -> 91 | K43: =IFERROR(E43*I43*J43/DaysInYear,0) -> 0 | L43: =G43+K43 -> 0
B44: 35 | C44: 48487 | D44: Q2 FY33 | E44: =H43 -> 0 | F44: =IF(AND('Facility Master'!W13>C43,'Facility Master'!W13<=C44),'Facility Master'!J13,0) -> 0 | G44: =IFERROR(IF(AND('Facility Master'!X13<>"-",C44>='Facility Master'!X13,C44<='Facility Master'!Y13),MIN(E44+F44,'Facility Master'!J13/'Facility Master'!V13),0),0) -> 0 | H44: =E44+F44-G44 -> 0 | I44: ='Facility Master'!Q13 -> 0.0975 | J44: =C44-C43 -> 92 | K44: =IFERROR(E44*I44*J44/DaysInYear,0) -> 0 | L44: =G44+K44 -> 0
B45: 36 | C45: 48579 | D45: Q3 FY33 | E45: =H44 -> 0 | F45: =IF(AND('Facility Master'!W13>C44,'Facility Master'!W13<=C45),'Facility Master'!J13,0) -> 0 | G45: =IFERROR(IF(AND('Facility Master'!X13<>"-",C45>='Facility Master'!X13,C45<='Facility Master'!Y13),MIN(E45+F45,'Facility Master'!J13/'Facility Master'!V13),0),0) -> 0 | H45: =E45+F45-G45 -> 0 | I45: ='Facility Master'!Q13 -> 0.0975 | J45: =C45-C44 -> 92 | K45: =IFERROR(E45*I45*J45/DaysInYear,0) -> 0 | L45: =G45+K45 -> 0
B46: 37 | C46: 48669 | D46: Q4 FY33 | E46: =H45 -> 0 | F46: =IF(AND('Facility Master'!W13>C45,'Facility Master'!W13<=C46),'Facility Master'!J13,0) -> 0 | G46: =IFERROR(IF(AND('Facility Master'!X13<>"-",C46>='Facility Master'!X13,C46<='Facility Master'!Y13),MIN(E46+F46,'Facility Master'!J13/'Facility Master'!V13),0),0) -> 0 | H46: =E46+F46-G46 -> 0 | I46: ='Facility Master'!Q13 -> 0.0975 | J46: =C46-C45 -> 90 | K46: =IFERROR(E46*I46*J46/DaysInYear,0) -> 0 | L46: =G46+K46 -> 0
B47: 38 | C47: 48760 | D47: Q1 FY34 | E47: =H46 -> 0 | F47: =IF(AND('Facility Master'!W13>C46,'Facility Master'!W13<=C47),'Facility Master'!J13,0) -> 0 | G47: =IFERROR(IF(AND('Facility Master'!X13<>"-",C47>='Facility Master'!X13,C47<='Facility Master'!Y13),MIN(E47+F47,'Facility Master'!J13/'Facility Master'!V13),0),0) -> 0 | H47: =E47+F47-G47 -> 0 | I47: ='Facility Master'!Q13 -> 0.0975 | J47: =C47-C46 -> 91 | K47: =IFERROR(E47*I47*J47/DaysInYear,0) -> 0 | L47: =G47+K47 -> 0
B48: 39 | C48: 48852 | D48: Q2 FY34 | E48: =H47 -> 0 | F48: =IF(AND('Facility Master'!W13>C47,'Facility Master'!W13<=C48),'Facility Master'!J13,0) -> 0 | G48: =IFERROR(IF(AND('Facility Master'!X13<>"-",C48>='Facility Master'!X13,C48<='Facility Master'!Y13),MIN(E48+F48,'Facility Master'!J13/'Facility Master'!V13),0),0) -> 0 | H48: =E48+F48-G48 -> 0 | I48: ='Facility Master'!Q13 -> 0.0975 | J48: =C48-C47 -> 92 | K48: =IFERROR(E48*I48*J48/DaysInYear,0) -> 0 | L48: =G48+K48 -> 0
B49: 40 | C49: 48944 | D49: Q3 FY34 | E49: =H48 -> 0 | F49: =IF(AND('Facility Master'!W13>C48,'Facility Master'!W13<=C49),'Facility Master'!J13,0) -> 0 | G49: =IFERROR(IF(AND('Facility Master'!X13<>"-",C49>='Facility Master'!X13,C49<='Facility Master'!Y13),MIN(E49+F49,'Facility Master'!J13/'Facility Master'!V13),0),0) -> 0 | H49: =E49+F49-G49 -> 0 | I49: ='Facility Master'!Q13 -> 0.0975 | J49: =C49-C48 -> 92 | K49: =IFERROR(E49*I49*J49/DaysInYear,0) -> 0 | L49: =G49+K49 -> 0
B50: 41 | C50: 49034 | D50: Q4 FY34 | E50: =H49 -> 0 | F50: =IF(AND('Facility Master'!W13>C49,'Facility Master'!W13<=C50),'Facility Master'!J13,0) -> 0 | G50: =IFERROR(IF(AND('Facility Master'!X13<>"-",C50>='Facility Master'!X13,C50<='Facility Master'!Y13),MIN(E50+F50,'Facility Master'!J13/'Facility Master'!V13),0),0) -> 0 | H50: =E50+F50-G50 -> 0 | I50: ='Facility Master'!Q13 -> 0.0975 | J50: =C50-C49 -> 90 | K50: =IFERROR(E50*I50*J50/DaysInYear,0) -> 0 | L50: =G50+K50 -> 0
B51: 42 | C51: 49125 | D51: Q1 FY35 | E51: =H50 -> 0 | F51: =IF(AND('Facility Master'!W13>C50,'Facility Master'!W13<=C51),'Facility Master'!J13,0) -> 0 | G51: =IFERROR(IF(AND('Facility Master'!X13<>"-",C51>='Facility Master'!X13,C51<='Facility Master'!Y13),MIN(E51+F51,'Facility Master'!J13/'Facility Master'!V13),0),0) -> 0 | H51: =E51+F51-G51 -> 0 | I51: ='Facility Master'!Q13 -> 0.0975 | J51: =C51-C50 -> 91 | K51: =IFERROR(E51*I51*J51/DaysInYear,0) -> 0 | L51: =G51+K51 -> 0
B52: 43 | C52: 49217 | D52: Q2 FY35 | E52: =H51 -> 0 | F52: =IF(AND('Facility Master'!W13>C51,'Facility Master'!W13<=C52),'Facility Master'!J13,0) -> 0 | G52: =IFERROR(IF(AND('Facility Master'!X13<>"-",C52>='Facility Master'!X13,C52<='Facility Master'!Y13),MIN(E52+F52,'Facility Master'!J13/'Facility Master'!V13),0),0) -> 0 | H52: =E52+F52-G52 -> 0 | I52: ='Facility Master'!Q13 -> 0.0975 | J52: =C52-C51 -> 92 | K52: =IFERROR(E52*I52*J52/DaysInYear,0) -> 0 | L52: =G52+K52 -> 0
B53: 44 | C53: 49309 | D53: Q3 FY35 | E53: =H52 -> 0 | F53: =IF(AND('Facility Master'!W13>C52,'Facility Master'!W13<=C53),'Facility Master'!J13,0) -> 0 | G53: =IFERROR(IF(AND('Facility Master'!X13<>"-",C53>='Facility Master'!X13,C53<='Facility Master'!Y13),MIN(E53+F53,'Facility Master'!J13/'Facility Master'!V13),0),0) -> 0 | H53: =E53+F53-G53 -> 0 | I53: ='Facility Master'!Q13 -> 0.0975 | J53: =C53-C52 -> 92 | K53: =IFERROR(E53*I53*J53/DaysInYear,0) -> 0 | L53: =G53+K53 -> 0
B54: 45 | C54: 49399 | D54: Q4 FY35 | E54: =H53 -> 0 | F54: =IF(AND('Facility Master'!W13>C53,'Facility Master'!W13<=C54),'Facility Master'!J13,0) -> 0 | G54: =IFERROR(IF(AND('Facility Master'!X13<>"-",C54>='Facility Master'!X13,C54<='Facility Master'!Y13),MIN(E54+F54,'Facility Master'!J13/'Facility Master'!V13),0),0) -> 0 | H54: =E54+F54-G54 -> 0 | I54: ='Facility Master'!Q13 -> 0.0975 | J54: =C54-C53 -> 90 | K54: =IFERROR(E54*I54*J54/DaysInYear,0) -> 0 | L54: =G54+K54 -> 0
B55: 46 | C55: 49490 | D55: Q1 FY36 | E55: =H54 -> 0 | F55: =IF(AND('Facility Master'!W13>C54,'Facility Master'!W13<=C55),'Facility Master'!J13,0) -> 0 | G55: =IFERROR(IF(AND('Facility Master'!X13<>"-",C55>='Facility Master'!X13,C55<='Facility Master'!Y13),MIN(E55+F55,'Facility Master'!J13/'Facility Master'!V13),0),0) -> 0 | H55: =E55+F55-G55 -> 0 | I55: ='Facility Master'!Q13 -> 0.0975 | J55: =C55-C54 -> 91 | K55: =IFERROR(E55*I55*J55/DaysInYear,0) -> 0 | L55: =G55+K55 -> 0
B56: 47 | C56: 49582 | D56: Q2 FY36 | E56: =H55 -> 0 | F56: =IF(AND('Facility Master'!W13>C55,'Facility Master'!W13<=C56),'Facility Master'!J13,0) -> 0 | G56: =IFERROR(IF(AND('Facility Master'!X13<>"-",C56>='Facility Master'!X13,C56<='Facility Master'!Y13),MIN(E56+F56,'Facility Master'!J13/'Facility Master'!V13),0),0) -> 0 | H56: =E56+F56-G56 -> 0 | I56: ='Facility Master'!Q13 -> 0.0975 | J56: =C56-C55 -> 92 | K56: =IFERROR(E56*I56*J56/DaysInYear,0) -> 0 | L56: =G56+K56 -> 0
B57: 48 | C57: 49674 | D57: Q3 FY36 | E57: =H56 -> 0 | F57: =IF(AND('Facility Master'!W13>C56,'Facility Master'!W13<=C57),'Facility Master'!J13,0) -> 0 | G57: =IFERROR(IF(AND('Facility Master'!X13<>"-",C57>='Facility Master'!X13,C57<='Facility Master'!Y13),MIN(E57+F57,'Facility Master'!J13/'Facility Master'!V13),0),0) -> 0 | H57: =E57+F57-G57 -> 0 | I57: ='Facility Master'!Q13 -> 0.0975 | J57: =C57-C56 -> 92 | K57: =IFERROR(E57*I57*J57/DaysInYear,0) -> 0 | L57: =G57+K57 -> 0
B58: 49 | C58: 49765 | D58: Q4 FY36 | E58: =H57 -> 0 | F58: =IF(AND('Facility Master'!W13>C57,'Facility Master'!W13<=C58),'Facility Master'!J13,0) -> 0 | G58: =IFERROR(IF(AND('Facility Master'!X13<>"-",C58>='Facility Master'!X13,C58<='Facility Master'!Y13),MIN(E58+F58,'Facility Master'!J13/'Facility Master'!V13),0),0) -> 0 | H58: =E58+F58-G58 -> 0 | I58: ='Facility Master'!Q13 -> 0.0975 | J58: =C58-C57 -> 91 | K58: =IFERROR(E58*I58*J58/DaysInYear,0) -> 0 | L58: =G58+K58 -> 0
B59: 50 | C59: 49856 | D59: Q1 FY37 | E59: =H58 -> 0 | F59: =IF(AND('Facility Master'!W13>C58,'Facility Master'!W13<=C59),'Facility Master'!J13,0) -> 0 | G59: =IFERROR(IF(AND('Facility Master'!X13<>"-",C59>='Facility Master'!X13,C59<='Facility Master'!Y13),MIN(E59+F59,'Facility Master'!J13/'Facility Master'!V13),0),0) -> 0 | H59: =E59+F59-G59 -> 0 | I59: ='Facility Master'!Q13 -> 0.0975 | J59: =C59-C58 -> 91 | K59: =IFERROR(E59*I59*J59/DaysInYear,0) -> 0 | L59: =G59+K59 -> 0
B60: 51 | C60: 49948 | D60: Q2 FY37 | E60: =H59 -> 0 | F60: =IF(AND('Facility Master'!W13>C59,'Facility Master'!W13<=C60),'Facility Master'!J13,0) -> 0 | G60: =IFERROR(IF(AND('Facility Master'!X13<>"-",C60>='Facility Master'!X13,C60<='Facility Master'!Y13),MIN(E60+F60,'Facility Master'!J13/'Facility Master'!V13),0),0) -> 0 | H60: =E60+F60-G60 -> 0 | I60: ='Facility Master'!Q13 -> 0.0975 | J60: =C60-C59 -> 92 | K60: =IFERROR(E60*I60*J60/DaysInYear,0) -> 0 | L60: =G60+K60 -> 0
B61: 52 | C61: 50040 | D61: Q3 FY37 | E61: =H60 -> 0 | F61: =IF(AND('Facility Master'!W13>C60,'Facility Master'!W13<=C61),'Facility Master'!J13,0) -> 0 | G61: =IFERROR(IF(AND('Facility Master'!X13<>"-",C61>='Facility Master'!X13,C61<='Facility Master'!Y13),MIN(E61+F61,'Facility Master'!J13/'Facility Master'!V13),0),0) -> 0 | H61: =E61+F61-G61 -> 0 | I61: ='Facility Master'!Q13 -> 0.0975 | J61: =C61-C60 -> 92 | K61: =IFERROR(E61*I61*J61/DaysInYear,0) -> 0 | L61: =G61+K61 -> 0
B62: 53 | C62: 50130 | D62: Q4 FY37 | E62: =H61 -> 0 | F62: =IF(AND('Facility Master'!W13>C61,'Facility Master'!W13<=C62),'Facility Master'!J13,0) -> 0 | G62: =IFERROR(IF(AND('Facility Master'!X13<>"-",C62>='Facility Master'!X13,C62<='Facility Master'!Y13),MIN(E62+F62,'Facility Master'!J13/'Facility Master'!V13),0),0) -> 0 | H62: =E62+F62-G62 -> 0 | I62: ='Facility Master'!Q13 -> 0.0975 | J62: =C62-C61 -> 90 | K62: =IFERROR(E62*I62*J62/DaysInYear,0) -> 0 | L62: =G62+K62 -> 0
B63: TOTAL | F63: =SUM(F10:F62) -> 200 | G63: =SUM(G10:G62) -> 200 | K63: =SUM(K10:K62) -> 65.850342 | L63: =SUM(L10:L62) -> 265.85034
B64: KPIs (as of AsOfDate) | E64: Princ. Repaid | F64: =SUMIFS(G10:G62,C10:C62,"<="&AsOfDate) -> 16.666667 | G64: Princ. Outstanding | H64: ='Facility Master'!J13-F64 -> 183.33333
B67: 2) YES Bank — Term Loan (Refinance Canara) (320.7 INR Cr) — S.No. 21
B68: Sanctioned (INR Cr) | C68: Drawdown | D68: Moratorium (m) | E68: Rep. Start | F68: Maturity | G68: # Instalments | H68: Qtr Instalment | I68: Eff. Rate (p.a.)
B69: ='Facility Master'!J25 -> 320.7 | C69: ='Facility Master'!W25 -> 45642 | D69: ='Facility Master'!S25 -> 0 | E69: ='Facility Master'!X25 -> 45747 | F69: ='Facility Master'!Y25 -> 49948 | G69: ='Facility Master'!V25 -> 47 | H69: ='Facility Master'!J25/'Facility Master'!V25 -> 6.8234043 | I69: ='Facility Master'!Q25 -> 0.077
B71: # | C71: Period End | D71: Period Label | E71: Opening Balance | F71: Drawdown | G71: Principal Repayment | H71: Closing Balance | I71: Interest Rate | J71: Days | K71: Interest Expense | L71: Total Debt Service
B72: 1 | C72: 45382 | D72: Q4 FY24 | E72: 0 | F72: =IF(C72>='Facility Master'!W25,'Facility Master'!J25,0) -> 0 | G72: =IFERROR(IF(AND('Facility Master'!X25<>"-",C72>='Facility Master'!X25,C72<='Facility Master'!Y25),MIN(E72+F72,'Facility Master'!J25/'Facility Master'!V25),0),0) -> 0 | H72: =E72+F72-G72 -> 0 | I72: ='Facility Master'!Q25 -> 0.077 | J72: =IF(AND(E72=0,F72=0),0,IF('Facility Master'!W25>=C72,0,C72-MAX('Facility Master'!W25,EDATE(C72,-3)))) -> 0 | K72: =IFERROR(E72*I72*J72/DaysInYear,0) -> 0 | L72: =G72+K72 -> 0
B73: 2 | C73: 45473 | D73: Q1 FY25 | E73: =H72 -> 0 | F73: =IF(AND('Facility Master'!W25>C72,'Facility Master'!W25<=C73),'Facility Master'!J25,0) -> 0 | G73: =IFERROR(IF(AND('Facility Master'!X25<>"-",C73>='Facility Master'!X25,C73<='Facility Master'!Y25),MIN(E73+F73,'Facility Master'!J25/'Facility Master'!V25),0),0) -> 0 | H73: =E73+F73-G73 -> 0 | I73: ='Facility Master'!Q25 -> 0.077 | J73: =C73-C72 -> 91 | K73: =IFERROR(E73*I73*J73/DaysInYear,0) -> 0 | L73: =G73+K73 -> 0
B74: 3 | C74: 45565 | D74: Q2 FY25 | E74: =H73 -> 0 | F74: =IF(AND('Facility Master'!W25>C73,'Facility Master'!W25<=C74),'Facility Master'!J25,0) -> 0 | G74: =IFERROR(IF(AND('Facility Master'!X25<>"-",C74>='Facility Master'!X25,C74<='Facility Master'!Y25),MIN(E74+F74,'Facility Master'!J25/'Facility Master'!V25),0),0) -> 0 | H74: =E74+F74-G74 -> 0 | I74: ='Facility Master'!Q25 -> 0.077 | J74: =C74-C73 -> 92 | K74: =IFERROR(E74*I74*J74/DaysInYear,0) -> 0 | L74: =G74+K74 -> 0
B75: 4 | C75: 45657 | D75: Q3 FY25 | E75: =H74 -> 0 | F75: =IF(AND('Facility Master'!W25>C74,'Facility Master'!W25<=C75),'Facility Master'!J25,0) -> 320.7 | G75: =IFERROR(IF(AND('Facility Master'!X25<>"-",C75>='Facility Master'!X25,C75<='Facility Master'!Y25),MIN(E75+F75,'Facility Master'!J25/'Facility Master'!V25),0),0) -> 0 | H75: =E75+F75-G75 -> 320.7 | I75: ='Facility Master'!Q25 -> 0.077 | J75: =C75-C74 -> 92 | K75: =IFERROR(E75*I75*J75/DaysInYear,0) -> 0 | L75: =G75+K75 -> 0
B76: 5 | C76: 45747 | D76: Q4 FY25 | E76: =H75 -> 320.7 | F76: =IF(AND('Facility Master'!W25>C75,'Facility Master'!W25<=C76),'Facility Master'!J25,0) -> 0 | G76: =IFERROR(IF(AND('Facility Master'!X25<>"-",C76>='Facility Master'!X25,C76<='Facility Master'!Y25),MIN(E76+F76,'Facility Master'!J25/'Facility Master'!V25),0),0) -> 6.8234043 | H76: =E76+F76-G76 -> 313.8766 | I76: ='Facility Master'!Q25 -> 0.077 | J76: =C76-C75 -> 90 | K76: =IFERROR(E76*I76*J76/DaysInYear,0) -> 6.0889068 | L76: =G76+K76 -> 12.912311
B77: 6 | C77: 45838 | D77: Q1 FY26 | E77: =H76 -> 313.8766 | F77: =IF(AND('Facility Master'!W25>C76,'Facility Master'!W25<=C77),'Facility Master'!J25,0) -> 0 | G77: =IFERROR(IF(AND('Facility Master'!X25<>"-",C77>='Facility Master'!X25,C77<='Facility Master'!Y25),MIN(E77+F77,'Facility Master'!J25/'Facility Master'!V25),0),0) -> 6.8234043 | H77: =E77+F77-G77 -> 307.05319 | I77: ='Facility Master'!Q25 -> 0.077 | J77: =C77-C76 -> 91 | K77: =IFERROR(E77*I77*J77/DaysInYear,0) -> 6.0255707 | L77: =G77+K77 -> 12.848975
B78: 7 | C78: 45930 | D78: Q2 FY26 | E78: =H77 -> 307.05319 | F78: =IF(AND('Facility Master'!W25>C77,'Facility Master'!W25<=C78),'Facility Master'!J25,0) -> 0 | G78: =IFERROR(IF(AND('Facility Master'!X25<>"-",C78>='Facility Master'!X25,C78<='Facility Master'!Y25),MIN(E78+F78,'Facility Master'!J25/'Facility Master'!V25),0),0) -> 6.8234043 | H78: =E78+F78-G78 -> 300.22979 | I78: ='Facility Master'!Q25 -> 0.077 | J78: =C78-C77 -> 92 | K78: =IFERROR(E78*I78*J78/DaysInYear,0) -> 5.9593556 | L78: =G78+K78 -> 12.78276
B79: 8 | C79: 46022 | D79: Q3 FY26 | E79: =H78 -> 300.22979 | F79: =IF(AND('Facility Master'!W25>C78,'Facility Master'!W25<=C79),'Facility Master'!J25,0) -> 0 | G79: =IFERROR(IF(AND('Facility Master'!X25<>"-",C79>='Facility Master'!X25,C79<='Facility Master'!Y25),MIN(E79+F79,'Facility Master'!J25/'Facility Master'!V25),0),0) -> 6.8234043 | H79: =E79+F79-G79 -> 293.40638 | I79: ='Facility Master'!Q25 -> 0.077 | J79: =C79-C78 -> 92 | K79: =IFERROR(E79*I79*J79/DaysInYear,0) -> 5.8269255 | L79: =G79+K79 -> 12.65033
B80: 9 | C80: 46112 | D80: Q4 FY26 | E80: =H79 -> 293.40638 | F80: =IF(AND('Facility Master'!W25>C79,'Facility Master'!W25<=C80),'Facility Master'!J25,0) -> 0 | G80: =IFERROR(IF(AND('Facility Master'!X25<>"-",C80>='Facility Master'!X25,C80<='Facility Master'!Y25),MIN(E80+F80,'Facility Master'!J25/'Facility Master'!V25),0),0) -> 6.8234043 | H80: =E80+F80-G80 -> 286.58298 | I80: ='Facility Master'!Q25 -> 0.077 | J80: =C80-C79 -> 90 | K80: =IFERROR(E80*I80*J80/DaysInYear,0) -> 5.570702 | L80: =G80+K80 -> 12.394106
B81: 10 | C81: 46203 | D81: Q1 FY27 | E81: =H80 -> 286.58298 | F81: =IF(AND('Facility Master'!W25>C80,'Facility Master'!W25<=C81),'Facility Master'!J25,0) -> 0 | G81: =IFERROR(IF(AND('Facility Master'!X25<>"-",C81>='Facility Master'!X25,C81<='Facility Master'!Y25),MIN(E81+F81,'Facility Master'!J25/'Facility Master'!V25),0),0) -> 6.8234043 | H81: =E81+F81-G81 -> 279.75957 | I81: ='Facility Master'!Q25 -> 0.077 | J81: =C81-C80 -> 91 | K81: =IFERROR(E81*I81*J81/DaysInYear,0) -> 5.501608 | L81: =G81+K81 -> 12.325012
B82: 11 | C82: 46295 | D82: Q2 FY27 | E82: =H81 -> 279.75957 | F82: =IF(AND('Facility Master'!W25>C81,'Facility Master'!W25<=C82),'Facility Master'!J25,0) -> 0 | G82: =IFERROR(IF(AND('Facility Master'!X25<>"-",C82>='Facility Master'!X25,C82<='Facility Master'!Y25),MIN(E82+F82,'Facility Master'!J25/'Facility Master'!V25),0),0) -> 6.8234043 | H82: =E82+F82-G82 -> 272.93617 | I82: ='Facility Master'!Q25 -> 0.077 | J82: =C82-C81 -> 92 | K82: =IFERROR(E82*I82*J82/DaysInYear,0) -> 5.4296351 | L82: =G82+K82 -> 12.253039
B83: 12 | C83: 46387 | D83: Q3 FY27 | E83: =H82 -> 272.93617 | F83: =IF(AND('Facility Master'!W25>C82,'Facility Master'!W25<=C83),'Facility Master'!J25,0) -> 0 | G83: =IFERROR(IF(AND('Facility Master'!X25<>"-",C83>='Facility Master'!X25,C83<='Facility Master'!Y25),MIN(E83+F83,'Facility Master'!J25/'Facility Master'!V25),0),0) -> 6.8234043 | H83: =E83+F83-G83 -> 266.11277 | I83: ='Facility Master'!Q25 -> 0.077 | J83: =C83-C82 -> 92 | K83: =IFERROR(E83*I83*J83/DaysInYear,0) -> 5.297205 | L83: =G83+K83 -> 12.120609
B84: 13 | C84: 46477 | D84: Q4 FY27 | E84: =H83 -> 266.11277 | F84: =IF(AND('Facility Master'!W25>C83,'Facility Master'!W25<=C84),'Facility Master'!J25,0) -> 0 | G84: =IFERROR(IF(AND('Facility Master'!X25<>"-",C84>='Facility Master'!X25,C84<='Facility Master'!Y25),MIN(E84+F84,'Facility Master'!J25/'Facility Master'!V25),0),0) -> 6.8234043 | H84: =E84+F84-G84 -> 259.28936 | I84: ='Facility Master'!Q25 -> 0.077 | J84: =C84-C83 -> 90 | K84: =IFERROR(E84*I84*J84/DaysInYear,0) -> 5.0524972 | L84: =G84+K84 -> 11.875901
